Workbook
Name \p: #REF!
Name \Q: #REF!
Name \t: #REF!
Name \v: #REF!
Name ____DAT1: #REF!
Name ____DAT10: #REF!
Name ____DAT11: #REF!
Name ____DAT12: #REF!
Name ____DAT13: #REF!
Name ____DAT14: #REF!
Name ____DAT2: #REF!
Name ____DAT3: #REF!
Name ____DAT4: #REF!
Name ____DAT5: #REF!
Name ____DAT6: #REF!
Name ____DAT7: #REF!
Name ____DAT8: #REF!
Name ____DAT9: #REF!
Name ____tab2: #REF!
Name ____tab6: #REF!
Name ___DAT1: #REF!
Name ___DAT10: #REF!
Name ___DAT11: #REF!
Name ___DAT12: #REF!
Name ___DAT13: #REF!
Name ___DAT14: #REF!
Name ___DAT2: #REF!
Name ___DAT3: #REF!
Name ___DAT4: #REF!
Name ___DAT5: #REF!
Name ___DAT6: #REF!
Name ___DAT7: #REF!
Name ___DAT8: #REF!
Name ___DAT9: #REF!
Name ___tab2: #REF!
Name ___tab6: #REF!
Name __DAT1: #REF!
Name __DAT10: #REF!
Name __DAT11: #REF!
Name __DAT12: #REF!
Name __DAT13: #REF!
Name __DAT14: #REF!
Name __DAT15: #REF!
Name __DAT16: #REF!
Name __DAT17: #REF!
Name __DAT18: #REF!
Name __DAT19: #REF!
Name __DAT2: #REF!
Name __DAT20: #REF!
Name __DAT21: #REF!
Name __DAT22: #REF!
Name __DAT23: #REF!
Name __DAT24: #REF!
Name __DAT3: #REF!
Name __DAT4: #REF!
Name __DAT5: #REF!
Name __DAT6: #REF!
Name __DAT7: #REF!
Name __DAT8: #REF!
Name __DAT9: #REF!

Sheet Executive Summary
B1: EXPORA MIS YTD AUG 2027
B4: Currency (Rs) | C4: Consolidated
C5: 46113 | D5: 46143 | E5: 46174 | F5: 46204 | G5: 46235 | H5: YTD 2627
B6: Revenue Booked | C6: =C25+C59+C78 -> #REF! | D6: =D25+D59+D78 -> #REF! | E6: =E25+E59+E78 -> #REF! | F6: =F25+F59+F78 -> #REF! | G6: =G25+G59+G78 -> #REF! | H6: =SUM(C6:G6) -> #REF!
B7: COGS | C7: =C26+C60+C79 -> #REF! | D7: =D26+D60+D79 -> #REF! | E7: =E26+E60+E79 -> #REF! | F7: =F26+F60+F79 -> #REF! | G7: =G26+G60+G79 -> #REF! | H7: =SUM(C7:G7) -> #REF!
B8: GM | C8: =C6-C7 -> #REF! | D8: =D6-D7 -> #REF! | E8: =E6-E7 -> #REF! | F8: =F6-F7 -> #REF! | G8: =G6-G7 -> #REF! | H8: =H6-H7 -> #REF!
B9: GM% | C9: =C8/C6 -> #REF! | D9: =D8/D6 -> #REF! | E9: =E8/E6 -> #REF! | F9: =F8/F6 -> #REF! | G9: =G8/G6 -> #REF! | H9: =H8/H6 -> #REF!
B10: Direct Expenses | C10: =C29+C63+C82 -> #REF! | D10: =D29+D63+D82 -> #REF! | E10: =E29+E63+E82 -> #REF! | F10: =F29+F63+F82 -> #REF! | G10: =G29+G63+G82 -> #REF! | H10: =SUM(C10:G10) -> #REF!
B11: CM | C11: =C30+C64+C83 -> #REF! | D11: =D30+D64+D83 -> #REF! | E11: =E30+E64+E83 -> #REF! | F11: =F30+F64+F83 -> #REF! | G11: =G30+G64+G83 -> #REF! | H11: =SUM(C11:G11) -> #REF!
B12: CM% | C12: =C11/C6 -> #REF! | D12: =D11/D6 -> #REF! | E12: =E11/E6 -> #REF! | F12: =F11/F6 -> #REF! | G12: =G11/G6 -> #REF! | H12: =H11/H6 -> #REF!
B13: Other Income | C13: =C32+C66+C85 -> #REF! | D13: =D32+D66+D85 -> #REF! | E13: =E32+E66+E85 -> #REF! | F13: =F32+F66+F85 -> #REF! | G13: =G32+G66+G85 -> #REF! | H13: =SUM(C13:G13) -> #REF!
B14: Fixed Expenses | C14: =C33+C67+C86 -> #REF! | D14: =D33+D67+D86 -> #REF! | E14: =E33+E67+E86 -> #REF! | F14: =F33+F67+F86 -> #REF! | G14: =G33+G67+G86 -> #REF! | H14: =SUM(C14:G14) -> #REF!
B15: EBITDA | C15: =C11+C13-C14 -> #REF! | D15: =D11+D13-D14 -> #REF! | E15: =E11+E13-E14 -> #REF! | F15: =F11+F13-F14 -> #REF! | G15: =G11+G13-G14 -> #REF! | H15: =SUM(C15:G15) -> #REF!
B16: EBITDA% | C16: =C15/C6 -> #REF! | D16: =D15/D6 -> #REF! | E16: =E15/E6 -> #REF! | F16: =F15/F6 -> #REF! | G16: =G15/G6 -> #REF! | H16: =H15/H6 -> #REF!
B17: Finance Cost | C17: =C36+C70+C89 -> #REF! | D17: =D36+D70+D89 -> #REF! | E17: =E36+E70+E89 -> #REF! | F17: =F36+F70+F89 -> #REF! | G17: =G36+G70+G89 -> #REF! | H17: =SUM(C17:G17) -> #REF!
B18: Depriciation | C18: =C37+C71+C90 -> #REF! | D18: =D37+D71+D90 -> #REF! | E18: =E37+E71+E90 -> #REF! | F18: =F37+F71+F90 -> #REF! | G18: =G37+G71+G90 -> #REF! | H18: =SUM(C18:G18) -> #REF!
B19: FX Gain/loss | C19: =C38+C72+C91 -> #REF! | D19: =D38+D72+D91 -> #REF! | E19: =E38+E72+E91 -> #REF! | F19: =F38+F72+F91 -> #REF! | G19: =G38+G72+G91 -> #REF! | H19: =SUM(C19:G19) -> #REF!
B20: Net Profit | C20: =C39+C73+C92 -> #REF! | D20: =D39+D73+D92 -> #REF! | E20: =E39+E73+E92 -> #REF! | F20: =F39+F73+F92 -> #REF! | G20: =G39+G73+G92 -> #REF! | H20: =SUM(C20:G20) -> #REF!
B21: Net Profit % | C21: =C20/C6 -> #REF! | D21: =D20/D6 -> #REF! | E21: =E20/E6 -> #REF! | F21: =F20/F6 -> #REF! | G21: =G20/G6 -> #REF! | H21: =H20/H6 -> #REF!
B23: Currency (Rs) | C23: Tradearch
C24: 46113 | D24: 46143 | E24: 46174 | F24: 46204 | G24: 46235 | H24: YTD 2627
B25: Revenue Booked | C25: =PL!#REF! -> #REF! | D25: =PL!#REF! -> #REF! | E25: =PL!#REF! -> #REF! | F25: =PL!#REF! -> #REF! | G25: =PL!#REF! -> #REF! | H25: =SUM(C25:G25) -> #REF!
B26: COGS | C26: =PL!#REF! -> #REF! | D26: =PL!#REF! -> #REF! | E26: =PL!#REF! -> #REF! | F26: =PL!#REF! -> #REF! | G26: =PL!#REF! -> #REF! | H26: =SUM(C26:G26) -> #REF!
B27: GM | C27: =C25-C26 -> #REF! | D27: =D25-D26 -> #REF! | E27: =E25-E26 -> #REF! | F27: =F25-F26 -> #REF! | G27: =G25-G26 -> #REF! | H27: =H25-H26 -> #REF!
B28: GM% | C28: =C27/C25 -> #REF! | D28: =D27/D25 -> #REF! | E28: =E27/E25 -> #REF! | F28: =F27/F25 -> #REF! | G28: =G27/G25 -> #REF! | H28: =H27/H25 -> #REF!
B29: Direct Expenses | C29: =PL!#REF!-PL!#REF! -> #REF! | D29: =PL!#REF!-PL!#REF! -> #REF! | E29: =PL!#REF!-PL!#REF! -> #REF! | F29: =PL!#REF!-PL!#REF! -> #REF! | G29: =PL!#REF!-PL!#REF! -> #REF! | H29: =SUM(C29:G29) -> #REF!
B30: CM | C30: =C27-C29 -> #REF! | D30: =D27-D29 -> #REF! | E30: =E27-E29 -> #REF! | F30: =F27-F29 -> #REF! | G30: =G27-G29 -> #REF! | H30: =SUM(C30:G30) -> #REF!
B31: CM% | C31: =C30/C25 -> #REF! | D31: =D30/D25 -> #REF! | E31: =E30/E25 -> #REF! | F31: =F30/F25 -> #REF! | G31: =G30/G25 -> #REF! | H31: =H30/H25 -> #REF!
B32: Other Income | C32: =PL!#REF! -> #REF! | D32: =PL!#REF! -> #REF! | E32: =PL!#REF! -> #REF! | F32: =PL!#REF! -> #REF! | G32: =PL!#REF! -> #REF! | H32: =SUM(C32:G32) -> #REF!
B33: Fixed Expenses | C33: =PL!#REF! -> #REF! | D33: =PL!#REF! -> #REF! | E33: =PL!#REF! -> #REF! | F33: =PL!#REF! -> #REF! | G33: =PL!#REF! -> #REF! | H33: =SUM(C33:G33) -> #REF!
B34: EBITDA | C34: =C30+C32-C33 -> #REF! | D34: =D30+D32-D33 -> #REF! | E34: =E30+E32-E33 -> #REF! | F34: =F30+F32-F33 -> #REF! | G34: =G30+G32-G33 -> #REF! | H34: =SUM(C34:G34) -> #REF!
B35: EBITDA% | C35: =C34/C25 -> #REF! | D35: =D34/D25 -> #REF! | E35: =E34/E25 -> #REF! | F35: =F34/F25 -> #REF! | G35: =G34/G25 -> #REF! | H35: =H34/H25 -> #REF!
B36: Finance Cost | C36: =PL!#REF! -> #REF! | D36: =PL!#REF! -> #REF! | E36: =PL!#REF! -> #REF! | F36: =PL!#REF! -> #REF! | G36: =PL!#REF! -> #REF! | H36: =SUM(C36:G36) -> #REF!
B37: Depriciation | C37: =PL!#REF! -> #REF! | D37: =PL!#REF! -> #REF! | E37: =PL!#REF! -> #REF! | F37: =PL!#REF! -> #REF! | G37: =PL!#REF! -> #REF! | H37: =SUM(C37:G37) -> #REF!
B38: FX Gain/loss | C38: =PL!#REF! -> #REF! | D38: =PL!#REF! -> #REF! | E38: =PL!#REF! -> #REF! | F38: =PL!#REF! -> #REF! | G38: =PL!#REF! -> #REF! | H38: =SUM(C38:G38) -> #REF!
B39: Net Profit | C39: =C34-C36-C37-C38 -> #REF! | D39: =D34-D36-D37-D38 -> #REF! | E39: =E34-E36-E37-E38 -> #REF! | F39: =F34-F36-F37-F38 -> #REF! | G39: =G34-G36-G37-G38 -> #REF! | H39: =SUM(C39:G39) -> #REF!
B40: Net Profit % | C40: =C39/C25 -> #REF! | D40: =D39/D25 -> #REF! | E40: =E39/E25 -> #REF! | F40: =F39/F25 -> #REF! | G40: =G39/G25 -> #REF! | H40: =H39/H25 -> #REF!
B57: Currency (Rs) | C57: Arha General Trading Co (AGT)
C58: 46113 | D58: 46143 | E58: 46174 | F58: 46204 | G58: 46235 | H58: YTD 2627
B59: Revenue Booked | C59: =PL!C6 -> 0 | D59: =PL!D6 -> 0 | E59: =PL!E6 -> 0 | F59: =PL!F6 -> 0 | G59: =PL!G6 -> 0 | H59: =SUM(C59:G59) -> 0
B60: COGS | C60: =PL!C10 -> 0 | D60: =PL!D10 -> 0 | E60: =PL!E10 -> 0 | F60: =PL!F10 -> 0 | G60: =PL!G10 -> 0 | H60: =SUM(C60:G60) -> 0
B61: GM | C61: =C59-C60 -> 0 | D61: =D59-D60 -> 0 | E61: =E59-E60 -> 0 | F61: =F59-F60 -> 0 | G61: =G59-G60 -> 0 | H61: =H59-H60 -> 0
B62: GM% | C62: =C61/C59 -> #DIV/0! | D62: =D61/D59 -> #DIV/0! | E62: =E61/E59 -> #DIV/0! | F62: =F61/F59 -> #DIV/0! | G62: =G61/G59 -> #DIV/0! | H62: =H61/H59 -> #DIV/0!
B63: Direct Expenses | C63: =PL!C19-PL!C15 -> 0 | D63: =PL!D19-PL!D15 -> 0 | E63: =PL!E19-PL!E15 -> 0 | F63: =PL!F19-PL!F15 -> 0 | G63: =PL!G19-PL!G15 -> 0 | H63: =SUM(C63:G63) -> 0
B64: CM | C64: =C61-C63 -> 0 | D64: =D61-D63 -> 0 | E64: =E61-E63 -> 0 | F64: =F61-F63 -> 0 | G64: =G61-G63 -> 0 | H64: =SUM(C64:G64) -> 0
B65: CM% | C65: =C64/C59 -> #DIV/0! | D65: =D64/D59 -> #DIV/0! | E65: =E64/E59 -> #DIV/0! | F65: =F64/F59 -> #DIV/0! | G65: =G64/G59 -> #DIV/0! | H65: =H64/H59 -> #DIV/0!
B66: Other Income | C66: =PL!C46 -> 0 | D66: =PL!D46 -> 0 | E66: =PL!E46 -> 0 | F66: =PL!F46 -> 0 | G66: =PL!G46 -> 0 | H66: =SUM(C66:G66) -> 0
B67: Fixed Expenses | C67: =PL!C137 -> 0 | D67: =PL!D137 -> 0 | E67: =PL!E137 -> 0 | F67: =PL!F137 -> 0 | G67: =PL!G137 -> 0 | H67: =SUM(C67:G67) -> 0
B68: EBITDA | C68: =C64+C66-C67 -> 0 | D68: =D64+D66-D67 -> 0 | E68: =E64+E66-E67 -> 0 | F68: =F64+F66-F67 -> 0 | G68: =G64+G66-G67 -> 0 | H68: =SUM(C68:G68) -> 0
B69: EBITDA% | C69: =C68/C59 -> #DIV/0! | D69: =D68/D59 -> #DIV/0! | E69: =E68/E59 -> #DIV/0! | F69: =F68/F59 -> #DIV/0! | G69: =G68/G59 -> #DIV/0! | H69: =H68/H59 -> #DIV/0!
B70: Finance Cost | C70: =PL!C143 -> 0 | D70: =PL!D143 -> 0 | E70: =PL!E143 -> 0 | F70: =PL!F143 -> 0 | G70: =PL!G143 -> 0 | H70: =SUM(C70:G70) -> 0
B71: Depriciation | C71: =PL!C161 -> 0 | D71: =PL!D161 -> 0 | E71: =PL!E161 -> 0 | F71: =PL!F161 -> 0 | G71: =PL!G161 -> 0 | H71: =SUM(C71:G71) -> 0
B72: FX Gain/loss | C72: =PL!C142 -> 0 | D72: =PL!D142 -> 0 | E72: =PL!E142 -> 0 | F72: =PL!F142 -> 0 | G72: =PL!G142 -> 0 | H72: =SUM(C72:G72) -> 0
B73: Net Profit | C73: =C68-C70-C71-C72 -> 0 | D73: =D68-D70-D71-D72 -> 0 | E73: =E68-E70-E71-E72 -> 0 | F73: =F68-F70-F71-F72 -> 0 | G73: =G68-G70-G71-G72 -> 0 | H73: =SUM(C73:G73) -> 0
B74: Net Profit % | C74: =C73/C59 -> #DIV/0! | D74: =D73/D59 -> #DIV/0! | E74: =E73/E59 -> #DIV/0! | F74: =F73/F59 -> #DIV/0! | G74: =G73/G59 -> #DIV/0! | H74: =H73/H59 -> #DIV/0!
B76: Currency (Rs) | C76: Aspirarch Lanka
C77: 46113 | D77: 46143 | E77: 46174 | F77: 46204 | G77: 46235 | H77: YTD 2627
B78: Revenue Booked | C78: =PL!#REF! -> #REF! | D78: =PL!#REF! -> #REF! | E78: =PL!#REF! -> #REF! | F78: =PL!#REF! -> #REF! | G78: =PL!#REF! -> #REF! | H78: =SUM(C78:G78) -> #REF!
B79: COGS | C79: =PL!#REF! -> #REF! | D79: =PL!#REF! -> #REF! | E79: =PL!#REF! -> #REF! | F79: =PL!#REF! -> #REF! | G79: =PL!#REF! -> #REF! | H79: =SUM(C79:G79) -> #REF!
B80: GM | C80: =C78-C79 -> #REF! | D80: =D78-D79 -> #REF! | E80: =E78-E79 -> #REF! | F80: =F78-F79 -> #REF! | G80: =G78-G79 -> #REF! | H80: =H78-H79 -> #REF!
B81: GM% | C81: =C80/C78 -> #REF! | D81: =D80/D78 -> #REF! | E81: =E80/E78 -> #REF! | F81: =F80/F78 -> #REF! | G81: =G80/G78 -> #REF! | H81: =H80/H78 -> #REF!
B82: Direct Expenses | C82: =PL!#REF!-PL!#REF! -> #REF! | D82: =PL!#REF!-PL!#REF! -> #REF! | E82: =PL!#REF!-PL!#REF! -> #REF! | F82: =PL!#REF!-PL!#REF! -> #REF! | G82: =PL!#REF!-PL!#REF! -> #REF! | H82: =SUM(C82:G82) -> #REF!
B83: CM | C83: =C80-C82 -> #REF! | D83: =D80-D82 -> #REF! | E83: =E80-E82 -> #REF! | F83: =F80-F82 -> #REF! | G83: =G80-G82 -> #REF! | H83: =SUM(C83:G83) -> #REF!
B84: CM% | C84: =C83/C78 -> #REF! | D84: =D83/D78 -> #REF! | E84: =E83/E78 -> #REF! | F84: =F83/F78 -> #REF! | G84: =G83/G78 -> #REF! | H84: =H83/H78 -> #REF!
B85: Other Income | C85: =PL!#REF! -> #REF! | D85: =PL!#REF! -> #REF! | E85: =PL!#REF! -> #REF! | F85: =PL!#REF! -> #REF! | G85: =PL!#REF! -> #REF! | H85: =SUM(C85:G85) -> #REF!
B86: Fixed Expenses | C86: =PL!#REF! -> #REF! | D86: =PL!#REF! -> #REF! | E86: =PL!#REF! -> #REF! | F86: =PL!#REF! -> #REF! | G86: =PL!#REF! -> #REF! | H86: =SUM(C86:G86) -> #REF!
B87: EBITDA | C87: =C83+C85-C86 -> #REF! | D87: =D83+D85-D86 -> #REF! | E87: =E83+E85-E86 -> #REF! | F87: =F83+F85-F86 -> #REF! | G87: =G83+G85-G86 -> #REF! | H87: =SUM(C87:G87) -> #REF!
B88: EBITDA% | C88: =C87/C78 -> #REF! | D88: =D87/D78 -> #REF! | E88: =E87/E78 -> #REF! | F88: =F87/F78 -> #REF! | G88: =G87/G78 -> #REF! | H88: =H87/H78 -> #REF!
B89: Finance Cost | C89: =PL!#REF! -> #REF! | D89: =PL!#REF! -> #REF! | E89: =PL!#REF! -> #REF! | F89: =PL!#REF! -> #REF! | G89: =PL!#REF! -> #REF! | H89: =SUM(C89:G89) -> #REF!
B90: Depriciation | C90: =PL!#REF! -> #REF! | D90: =PL!#REF! -> #REF! | E90: =PL!#REF! -> #REF! | F90: =PL!#REF! -> #REF! | G90: =PL!#REF! -> #REF! | H90: =SUM(C90:G90) -> #REF!
B91: FX Gain/loss | C91: =PL!#REF! -> #REF! | D91: =PL!#REF! -> #REF! | E91: =PL!#REF! -> #REF! | F91: =PL!#REF! -> #REF! | G91: =PL!#REF! -> #REF! | H91: =SUM(C91:G91) -> #REF!
B92: Net Profit | C92: =C87-C89-C90-C91 -> #REF! | D92: =D87-D89-D90-D91 -> #REF! | E92: =E87-E89-E90-E91 -> #REF! | F92: =F87-F89-F90-F91 -> #REF! | G92: =G87-G89-G90-G91 -> #REF! | H92: =SUM(C92:G92) -> #REF!
B93: Net Profit % | C93: =C92/C78 -> #REF! | D93: =D92/D78 -> #REF! | E93: =E92/E78 -> #REF! | F93: =F92/F78 -> #REF! | G93: =G92/G78 -> #REF! | H93: =H92/H78 -> #REF!

Sheet PL
B1: Tradearch Market Platforms Private Limited
B2: Profit and Loss for the period April 21 to October 2024 | C2: =#REF! -> #REF!
B3: Figures in Rs
C4: AGT
B5: Currency (Rs) | C5: Apr-25 | D5: May-25 | E5: June-25 | F5: July-25 | G5: Aug-25 | H5: YTD FY26
B6: Revenue Booked | C6: =SUM(C7:C8) -> 0 | D6: =SUM(D7:D8) -> 0 | E6: =SUM(E7:E8) -> 0 | F6: =SUM(F7:F8) -> 0 | G6: =SUM(G7:G8) -> 0 | H6: =SUM(C6:G6) -> 0
B7: Sales | C7: =-SUMIFS('AGT TB Apr -25'!H:H,'AGT TB Apr -25'!S:S,B7) -> 0 | D7: =-SUMIFS('AGT TB Apr -25'!I:I,'AGT TB Apr -25'!S:S,B7) -> 0 | E7: =-SUMIFS('AGT TB Apr -25'!J:J,'AGT TB Apr -25'!S:S,B7) -> 0 | F7: =-SUMIFS('AGT TB Apr -25'!K:K,'AGT TB Apr -25'!S:S,B7) -> 0 | G7: =-SUMIFS('AGT TB Apr -25'!L:L,'AGT TB Apr -25'!S:S,B7) -> 0 | H7: =SUM(C7:G7) -> 0
B8: Cash Discount - Income | C8: =-SUMIFS('AGT TB Apr -25'!H:H,'AGT TB Apr -25'!S:S,B8) -> 0 | D8: =-SUMIFS('AGT TB Apr -25'!I:I,'AGT TB Apr -25'!S:S,B8) -> 0 | E8: =-SUMIFS('AGT TB Apr -25'!J:J,'AGT TB Apr -25'!S:S,B8) -> 0 | F8: =-SUMIFS('AGT TB Apr -25'!K:K,'AGT TB Apr -25'!S:S,B8) -> 0 | G8: =-SUMIFS('AGT TB Apr -25'!L:L,'AGT TB Apr -25'!S:S,B8) -> 0 | H8: =SUM(C8:G8) -> 0
B9: Inventorisation | C9: =SUMIFS('AGT TB Apr -25'!H:H,'AGT TB Apr -25'!S:S,B9) -> 0 | D9: =SUMIFS('AGT TB Apr -25'!I:I,'AGT TB Apr -25'!S:S,B9) -> 0 | E9: =SUMIFS('AGT TB Apr -25'!J:J,'AGT TB Apr -25'!S:S,B9) -> 0 | F9: =SUMIFS('AGT TB Apr -25'!K:K,'AGT TB Apr -25'!S:S,B9) -> 0 | G9: =SUMIFS('AGT TB Apr -25'!L:L,'AGT TB Apr -25'!S:S,B9) -> 0 | H9: =SUM(C9:G9) -> 0
B10: COGS | C10: =SUMIFS('AGT TB Apr -25'!H:H,'AGT TB Apr -25'!S:S,B10) -> 0 | D10: =SUMIFS('AGT TB Apr -25'!I:I,'AGT TB Apr -25'!S:S,B10) -> 0 | E10: =SUMIFS('AGT TB Apr -25'!J:J,'AGT TB Apr -25'!S:S,B10) -> 0 | F10: =SUMIFS('AGT TB Apr -25'!K:K,'AGT TB Apr -25'!S:S,B10) -> 0 | G10: =SUMIFS('AGT TB Apr -25'!L:L,'AGT TB Apr -25'!S:S,B10) -> 0 | H10: =SUM(C10:G10) -> 0
A11: =#REF!+#REF!-#REF! -> #REF! | B11: Opening Stock | C11: ='AGT TB Apr -25'!#REF! -> #REF! | D11: ='AGT TB Apr -25'!#REF! -> #REF! | E11: ='AGT TB Apr -25'!#REF! -> #REF! | F11: ='AGT TB Apr -25'!#REF! -> #REF! | G11: ='AGT TB Apr -25'!#REF! -> #REF! | H11: =SUM(C11:G11) -> #REF!
B12: Purchase | C12: =SUMIFS('AGT TB Apr -25'!H:H,'AGT TB Apr -25'!S:S,B12) -> 0 | D12: =SUMIFS('AGT TB Apr -25'!I:I,'AGT TB Apr -25'!S:S,B12) -> 0 | E12: =SUMIFS('AGT TB Apr -25'!J:J,'AGT TB Apr -25'!S:S,B12) -> 0 | F12: =SUMIFS('AGT TB Apr -25'!K:K,'AGT TB Apr -25'!S:S,B12) -> 0 | G12: =SUMIFS('AGT TB Apr -25'!L:L,'AGT TB Apr -25'!S:S,B12) -> 0 | H12: =SUM(C12:G12) -> 0
A13: =#REF! -> #REF! | H13: =SUM(C13:G13) -> 0
B14: Closing Stock | C14: =SUMIFS('AGT TB Apr -25'!H:H,'AGT TB Apr -25'!S:S,B14) -> 0 | D14: =SUMIFS('AGT TB Apr -25'!I:I,'AGT TB Apr -25'!S:S,B14) -> 0 | E14: =SUMIFS('AGT TB Apr -25'!J:J,'AGT TB Apr -25'!S:S,B14) -> 0 | F14: =SUMIFS('AGT TB Apr -25'!K:K,'AGT TB Apr -25'!S:S,B14) -> 0 | G14: =SUMIFS('AGT TB Apr -25'!L:L,'AGT TB Apr -25'!S:S,B14) -> 0 | H14: =SUM(C14:G14) -> 0
B15: Direct Income | C15: =SUM(C16:C18) -> 0 | D15: =SUM(D16:D18) -> 0 | E15: =SUM(E16:E18) -> 0 | F15: =SUM(F16:F18) -> 0 | G15: =SUM(G16:G18) -> 0 | H15: =SUM(C15:G15) -> 0
B16: Duty Drawback | C16: =-SUMIFS('AGT TB Apr -25'!H:H,'AGT TB Apr -25'!S:S,B16) -> 0 | D16: =-SUMIFS('AGT TB Apr -25'!I:I,'AGT TB Apr -25'!S:S,B16) -> 0 | E16: =-SUMIFS('AGT TB Apr -25'!J:J,'AGT TB Apr -25'!S:S,B16) -> 0 | F16: =-SUMIFS('AGT TB Apr -25'!K:K,'AGT TB Apr -25'!S:S,B16) -> 0 | G16: =-SUMIFS('AGT TB Apr -25'!L:L,'AGT TB Apr -25'!S:S,B16) -> 0 | H16: =SUM(C16:G16) -> 0
B17: Making Charges | C17: =-SUMIFS('AGT TB Apr -25'!H:H,'AGT TB Apr -25'!S:S,B17) -> 0 | D17: =-SUMIFS('AGT TB Apr -25'!I:I,'AGT TB Apr -25'!S:S,B17) -> 0 | E17: =-SUMIFS('AGT TB Apr -25'!J:J,'AGT TB Apr -25'!S:S,B17) -> 0 | F17: =-SUMIFS('AGT TB Apr -25'!K:K,'AGT TB Apr -25'!S:S,B17) -> 0 | G17: =-SUMIFS('AGT TB Apr -25'!L:L,'AGT TB Apr -25'!S:S,B17) -> 0 | H17: =SUM(C17:G17) -> 0
A18: =#REF!+#REF!-#REF! -> #REF! | B18: Rodtep Income | C18: =-SUMIFS('AGT TB Apr -25'!H:H,'AGT TB Apr -25'!S:S,B18) -> 0 | D18: =-SUMIFS('AGT TB Apr -25'!I:I,'AGT TB Apr -25'!S:S,B18) -> 0 | E18: =-SUMIFS('AGT TB Apr -25'!J:J,'AGT TB Apr -25'!S:S,B18) -> 0 | F18: =-SUMIFS('AGT TB Apr -25'!K:K,'AGT TB Apr -25'!S:S,B18) -> 0 | G18: =-SUMIFS('AGT TB Apr -25'!L:L,'AGT TB Apr -25'!S:S,B18) -> 0 | H18: =SUM(C18:G18) -> 0
B19: Direct Expenses | C19: =SUM(C20:C40) -> 0 | D19: =SUM(D20:D40) -> 0 | E19: =SUM(E20:E40) -> 0 | F19: =SUM(F20:F40) -> 0 | G19: =SUM(G20:G40) -> 0 | H19: =SUM(C19:G19) -> 0
B20: Labour charges on Gold & Diamond | C20: =-SUMIFS('AGT TB Apr -25'!H:H,'AGT TB Apr -25'!S:S,B20) -> 0 | D20: =-SUMIFS('AGT TB Apr -25'!I:I,'AGT TB Apr -25'!S:S,B20) -> 0 | E20: =-SUMIFS('AGT TB Apr -25'!J:J,'AGT TB Apr -25'!S:S,B20) -> 0 | F20: =-SUMIFS('AGT TB Apr -25'!K:K,'AGT TB Apr -25'!S:S,B20) -> 0 | G20: =-SUMIFS('AGT TB Apr -25'!L:L,'AGT TB Apr -25'!S:S,B20) -> 0 | H20: =SUM(C20:G20) -> 0
B21: Provision for Direct Expense | H21: =SUM(C21:G21) -> 0
B22: Freight & forwarding Charges | C22: =SUMIFS('AGT TB Apr -25'!H:H,'AGT TB Apr -25'!S:S,B22) -> 0 | D22: =SUMIFS('AGT TB Apr -25'!I:I,'AGT TB Apr -25'!S:S,B22) -> 0 | E22: =SUMIFS('AGT TB Apr -25'!J:J,'AGT TB Apr -25'!S:S,B22) -> 0 | F22: =SUMIFS('AGT TB Apr -25'!K:K,'AGT TB Apr -25'!S:S,B22) -> 0 | G22: =SUMIFS('AGT TB Apr -25'!L:L,'AGT TB Apr -25'!S:S,B22) -> 0 | H22: =SUM(C22:G22) -> 0
B23: Labour Charges | C23: =SUMIFS('AGT TB Apr -25'!H:H,'AGT TB Apr -25'!S:S,B23) -> 0 | D23: =SUMIFS('AGT TB Apr -25'!I:I,'AGT TB Apr -25'!S:S,B23) -> 0 | E23: =SUMIFS('AGT TB Apr -25'!J:J,'AGT TB Apr -25'!S:S,B23) -> 0 | F23: =SUMIFS('AGT TB Apr -25'!K:K,'AGT TB Apr -25'!S:S,B23) -> 0 | G23: =SUMIFS('AGT TB Apr -25'!L:L,'AGT TB Apr -25'!S:S,B23) -> 0 | H23: =SUM(C23:G23) -> 0
B24: Prior Period Direct Expense | C24: =SUMIFS('AGT TB Apr -25'!H:H,'AGT TB Apr -25'!S:S,B24) -> 0 | D24: =SUMIFS('AGT TB Apr -25'!I:I,'AGT TB Apr -25'!S:S,B24) -> 0 | E24: =SUMIFS('AGT TB Apr -25'!J:J,'AGT TB Apr -25'!S:S,B24) -> 0 | F24: =SUMIFS('AGT TB Apr -25'!K:K,'AGT TB Apr -25'!S:S,B24) -> 0 | G24: =SUMIFS('AGT TB Apr -25'!L:L,'AGT TB Apr -25'!S:S,B24) -> 0 | H24: =SUM(C24:G24) -> 0
B25: Custom Duty | C25: =SUMIFS('AGT TB Apr -25'!H:H,'AGT TB Apr -25'!S:S,B25) -> 0 | D25: =SUMIFS('AGT TB Apr -25'!I:I,'AGT TB Apr -25'!S:S,B25) -> 0 | E25: =SUMIFS('AGT TB Apr -25'!J:J,'AGT TB Apr -25'!S:S,B25) -> 0 | F25: =SUMIFS('AGT TB Apr -25'!K:K,'AGT TB Apr -25'!S:S,B25) -> 0 | G25: =SUMIFS('AGT TB Apr -25'!L:L,'AGT TB Apr -25'!S:S,B25) -> 0 | H25: =SUM(C25:G25) -> 0
B26: Testing and Inspection Charge | C26: =SUMIFS('AGT TB Apr -25'!H:H,'AGT TB Apr -25'!S:S,B26) -> 0 | D26: =SUMIFS('AGT TB Apr -25'!I:I,'AGT TB Apr -25'!S:S,B26) -> 0 | E26: =SUMIFS('AGT TB Apr -25'!J:J,'AGT TB Apr -25'!S:S,B26) -> 0 | F26: =SUMIFS('AGT TB Apr -25'!K:K,'AGT TB Apr -25'!S:S,B26) -> 0 | G26: =SUMIFS('AGT TB Apr -25'!L:L,'AGT TB Apr -25'!S:S,B26) -> 0 | H26: =SUM(C26:G26) -> 0
B27: Transportation Charges | C27: =SUMIFS('AGT TB Apr -25'!H:H,'AGT TB Apr -25'!S:S,B27) -> 0 | D27: =SUMIFS('AGT TB Apr -25'!I:I,'AGT TB Apr -25'!S:S,B27) -> 0 | E27: =SUMIFS('AGT TB Apr -25'!J:J,'AGT TB Apr -25'!S:S,B27) -> 0 | F27: =SUMIFS('AGT TB Apr -25'!K:K,'AGT TB Apr -25'!S:S,B27) -> 0 | G27: =SUMIFS('AGT TB Apr -25'!L:L,'AGT TB Apr -25'!S:S,B27) -> 0 | H27: =SUM(C27:G27) -> 0
B28: Commission & Brokerage Charges | C28: =SUMIFS('AGT TB Apr -25'!H:H,'AGT TB Apr -25'!S:S,B28) -> 0 | D28: =SUMIFS('AGT TB Apr -25'!I:I,'AGT TB Apr -25'!S:S,B28) -> 0 | E28: =SUMIFS('AGT TB Apr -25'!J:J,'AGT TB Apr -25'!S:S,B28) -> 0 | F28: =SUMIFS('AGT TB Apr -25'!K:K,'AGT TB Apr -25'!S:S,B28) -> 0 | G28: =SUMIFS('AGT TB Apr -25'!L:L,'AGT TB Apr -25'!S:S,B28) -> 0 | H28: =SUM(C28:G28) -> 0
B29: Spice testing expenses | C29: =SUMIFS('AGT TB Apr -25'!H:H,'AGT TB Apr -25'!S:S,B29) -> 0 | D29: =SUMIFS('AGT TB Apr -25'!I:I,'AGT TB Apr -25'!S:S,B29) -> 0 | E29: =SUMIFS('AGT TB Apr -25'!J:J,'AGT TB Apr -25'!S:S,B29) -> 0 | F29: =SUMIFS('AGT TB Apr -25'!K:K,'AGT TB Apr -25'!S:S,B29) -> 0 | G29: =SUMIFS('AGT TB Apr -25'!L:L,'AGT TB Apr -25'!S:S,B29) -> 0 | H29: =SUM(C29:G29) -> 0
B30: Export Insurance Policy | C30: =SUMIFS('AGT TB Apr -25'!H:H,'AGT TB Apr -25'!S:S,B30) -> 0 | D30: =SUMIFS('AGT TB Apr -25'!I:I,'AGT TB Apr -25'!S:S,B30) -> 0 | E30: =SUMIFS('AGT TB Apr -25'!J:J,'AGT TB Apr -25'!S:S,B30) -> 0 | F30: =SUMIFS('AGT TB Apr -25'!K:K,'AGT TB Apr -25'!S:S,B30) -> 0 | G30: =SUMIFS('AGT TB Apr -25'!L:L,'AGT TB Apr -25'!S:S,B30) -> 0 | H30: =SUM(C30:G30) -> 0
B31: Bank charges against Import/MTT Transactio | C31: =SUMIFS('AGT TB Apr -25'!H:H,'AGT TB Apr -25'!S:S,B31) -> 0 | D31: =SUMIFS('AGT TB Apr -25'!I:I,'AGT TB Apr -25'!S:S,B31) -> 0 | E31: =SUMIFS('AGT TB Apr -25'!J:J,'AGT TB Apr -25'!S:S,B31) -> 0 | F31: =SUMIFS('AGT TB Apr -25'!K:K,'AGT TB Apr -25'!S:S,B31) -> 0 | G31: =SUMIFS('AGT TB Apr -25'!L:L,'AGT TB Apr -25'!S:S,B31) -> 0 | H31: =SUM(C31:G31) -> 0
B32: Cleaning & Packing | C32: =SUMIFS('AGT TB Apr -25'!H:H,'AGT TB Apr -25'!S:S,B32) -> 0 | D32: =SUMIFS('AGT TB Apr -25'!I:I,'AGT TB Apr -25'!S:S,B32) -> 0 | E32: =SUMIFS('AGT TB Apr -25'!J:J,'AGT TB Apr -25'!S:S,B32) -> 0 | F32: =SUMIFS('AGT TB Apr -25'!K:K,'AGT TB Apr -25'!S:S,B32) -> 0 | G32: =SUMIFS('AGT TB Apr -25'!L:L,'AGT TB Apr -25'!S:S,B32) -> 0 | H32: =SUM(C32:G32) -> 0
B33: QC Charges | C33: =SUMIFS('AGT TB Apr -25'!H:H,'AGT TB Apr -25'!S:S,B33) -> 0 | D33: =SUMIFS('AGT TB Apr -25'!I:I,'AGT TB Apr -25'!S:S,B33) -> 0 | E33: =SUMIFS('AGT TB Apr -25'!J:J,'AGT TB Apr -25'!S:S,B33) -> 0 | F33: =SUMIFS('AGT TB Apr -25'!K:K,'AGT TB Apr -25'!S:S,B33) -> 0 | G33: =SUMIFS('AGT TB Apr -25'!L:L,'AGT TB Apr -25'!S:S,B33) -> 0 | H33: =SUM(C33:G33) -> 0
... B40: Excess Weight Charges | C40: =SUMIFS('AGT TB Apr -25'!H:H,'AGT TB Apr -25'!S:S,B40) -> 0 | D40: =SUMIFS('AGT TB Apr -25'!I:I,'AGT TB Apr -25'!S:S,B40) -> 0 | E40: =SUMIFS('AGT TB Apr -25'!J:J,'AGT TB Apr -25'!S:S,B40) -> 0 | F40: =SUMIFS('AGT TB Apr -25'!K:K,'AGT TB Apr -25'!S:S,B40) -> 0 | G40: =SUMIFS('AGT TB Apr -25'!L:L,'AGT TB Apr -25'!S:S,B40) -> 0 | H40: =SUM(C40:G40) -> 0
B41: Gross Profit | C41: =C6-C10-C19+C15+C9 -> 0 | D41: =D6-D10-D19+D15+D9 -> 0 | E41: =E6-E10-E19+E15+E9 -> 0 | F41: =F6-F10-F19+F15+F9 -> 0 | G41: =G6-G10-G19+G15+G9 -> 0 | H41: =SUM(C41:G41) -> 0
B42: GP % | C42: =C41/C6% -> #DIV/0! | D42: =D41/D6% -> #DIV/0! | E42: =E41/E6% -> #DIV/0! | F42: =F41/F6% -> #DIV/0! | G42: =G41/G6% -> #DIV/0! | H42: =SUM(C42:G42) -> #DIV/0!
B43: Incorrect Provision Adjustment | H43: =SUM(C43:G43) -> 0
B44: Updated Gross Profit | C44: =C41+C43 -> 0 | D44: =D41+D43 -> 0 | E44: =E41+E43 -> 0 | F44: =F41+F43 -> 0 | G44: =G41+G43 -> 0 | H44: =SUM(C44:G44) -> 0
B45: Revised GP % | C45: =C44/C6% -> #DIV/0! | D45: =D44/D6% -> #DIV/0! | E45: =E44/E6% -> #DIV/0! | F45: =F44/F6% -> #DIV/0! | G45: =G44/G6% -> #DIV/0! | H45: =SUM(C45:G45) -> #DIV/0!
B46: Indirect Income | C46: =SUM(C47:C49) -> 0 | D46: =SUM(D47:D49) -> 0 | E46: =SUM(E47:E49) -> 0 | F46: =SUM(F47:F49) -> 0 | G46: =SUM(G47:G49) -> 0 | H46: =SUM(C46:G46) -> 0
B47: Interest on FD | C47: =-SUMIFS('AGT TB Apr -25'!H:H,'AGT TB Apr -25'!S:S,B47) -> 0 | D47: =-SUMIFS('AGT TB Apr -25'!I:I,'AGT TB Apr -25'!S:S,B47) -> 0 | E47: =-SUMIFS('AGT TB Apr -25'!J:J,'AGT TB Apr -25'!S:S,B47) -> 0 | F47: =-SUMIFS('AGT TB Apr -25'!K:K,'AGT TB Apr -25'!S:S,B47) -> 0 | G47: =-SUMIFS('AGT TB Apr -25'!L:L,'AGT TB Apr -25'!S:S,B47) -> 0 | H47: =SUM(C47:G47) -> 0
B48: Other Income | C48: =-SUMIFS('AGT TB Apr -25'!H:H,'AGT TB Apr -25'!S:S,B48) -> 0 | D48: =-SUMIFS('AGT TB Apr -25'!I:I,'AGT TB Apr -25'!S:S,B48) -> 0 | E48: =-SUMIFS('AGT TB Apr -25'!J:J,'AGT TB Apr -25'!S:S,B48) -> 0 | F48: =-SUMIFS('AGT TB Apr -25'!K:K,'AGT TB Apr -25'!S:S,B48) -> 0 | G48: =-SUMIFS('AGT TB Apr -25'!L:L,'AGT TB Apr -25'!S:S,B48) -> 0 | H48: =SUM(C48:G48) -> 0
B49: Interest on Income Tax Refund | C49: =-SUMIFS('AGT TB Apr -25'!H:H,'AGT TB Apr -25'!S:S,B49) -> 0 | D49: =-SUMIFS('AGT TB Apr -25'!I:I,'AGT TB Apr -25'!S:S,B49) -> 0 | E49: =-SUMIFS('AGT TB Apr -25'!J:J,'AGT TB Apr -25'!S:S,B49) -> 0 | F49: =-SUMIFS('AGT TB Apr -25'!K:K,'AGT TB Apr -25'!S:S,B49) -> 0 | G49: =-SUMIFS('AGT TB Apr -25'!L:L,'AGT TB Apr -25'!S:S,B49) -> 0 | H49: =SUM(C49:G49) -> 0
B50: Employee Costs | C50: =SUM(C51:C59) -> 0 | D50: =SUM(D51:D59) -> 0 | E50: =SUM(E51:E59) -> 0 | F50: =SUM(F51:F59) -> 0 | G50: =SUM(G51:G59) -> 0 | H50: =SUM(C50:G50) -> 0
B51: Salaries* | C51: =SUMIFS('AGT TB Apr -25'!H:H,'AGT TB Apr -25'!S:S,B51)+C140 -> 0 | D51: =SUMIFS('AGT TB Apr -25'!I:I,'AGT TB Apr -25'!S:S,B51)+D140 -> 0 | E51: =SUMIFS('AGT TB Apr -25'!J:J,'AGT TB Apr -25'!S:S,B51)+E140 -> 0 | F51: =SUMIFS('AGT TB Apr -25'!K:K,'AGT TB Apr -25'!S:S,B51)+F140 -> 0 | G51: =SUMIFS('AGT TB Apr -25'!L:L,'AGT TB Apr -25'!S:S,B51)+G140 -> 0 | H51: =SUM(C51:G51) -> 0
B52: Staff Welfare | C52: =SUMIFS('AGT TB Apr -25'!H:H,'AGT TB Apr -25'!S:S,B52) -> 0 | D52: =SUMIFS('AGT TB Apr -25'!I:I,'AGT TB Apr -25'!S:S,B52) -> 0 | E52: =SUMIFS('AGT TB Apr -25'!J:J,'AGT TB Apr -25'!S:S,B52) -> 0 | F52: =SUMIFS('AGT TB Apr -25'!K:K,'AGT TB Apr -25'!S:S,B52) -> 0 | G52: =SUMIFS('AGT TB Apr -25'!L:L,'AGT TB Apr -25'!S:S,B52) -> 0 | H52: =SUM(C52:G52) -> 0
A53: 18 | B53: Conveyance | C53: =SUMIFS('AGT TB Apr -25'!H:H,'AGT TB Apr -25'!S:S,B53) -> 0 | D53: =SUMIFS('AGT TB Apr -25'!I:I,'AGT TB Apr -25'!S:S,B53) -> 0 | E53: =SUMIFS('AGT TB Apr -25'!J:J,'AGT TB Apr -25'!S:S,B53) -> 0 | F53: =SUMIFS('AGT TB Apr -25'!K:K,'AGT TB Apr -25'!S:S,B53) -> 0 | G53: =SUMIFS('AGT TB Apr -25'!L:L,'AGT TB Apr -25'!S:S,B53) -> 0 | H53: =SUM(C53:G53) -> 0
A54: 38 | B54: ESIC charges | C54: =SUMIFS('AGT TB Apr -25'!H:H,'AGT TB Apr -25'!S:S,B54) -> 0 | D54: =SUMIFS('AGT TB Apr -25'!I:I,'AGT TB Apr -25'!S:S,B54) -> 0 | E54: =SUMIFS('AGT TB Apr -25'!J:J,'AGT TB Apr -25'!S:S,B54) -> 0 | F54: =SUMIFS('AGT TB Apr -25'!K:K,'AGT TB Apr -25'!S:S,B54) -> 0 | G54: =SUMIFS('AGT TB Apr -25'!L:L,'AGT TB Apr -25'!S:S,B54) -> 0 | H54: =SUM(C54:G54) -> 0
A55: 8 | B55: PF Insurance Charges | C55: =SUMIFS('AGT TB Apr -25'!H:H,'AGT TB Apr -25'!S:S,B55) -> 0 | D55: =SUMIFS('AGT TB Apr -25'!I:I,'AGT TB Apr -25'!S:S,B55) -> 0 | E55: =SUMIFS('AGT TB Apr -25'!J:J,'AGT TB Apr -25'!S:S,B55) -> 0 | F55: =SUMIFS('AGT TB Apr -25'!K:K,'AGT TB Apr -25'!S:S,B55) -> 0 | G55: =SUMIFS('AGT TB Apr -25'!L:L,'AGT TB Apr -25'!S:S,B55) -> 0 | H55: =SUM(C55:G55) -> 0
A56: 16 | B56: Gratuity expense | C56: =SUMIFS('AGT TB Apr -25'!H:H,'AGT TB Apr -25'!S:S,B56) -> 0 | D56: =SUMIFS('AGT TB Apr -25'!I:I,'AGT TB Apr -25'!S:S,B56) -> 0 | E56: =SUMIFS('AGT TB Apr -25'!J:J,'AGT TB Apr -25'!S:S,B56) -> 0 | F56: =SUMIFS('AGT TB Apr -25'!K:K,'AGT TB Apr -25'!S:S,B56) -> 0 | G56: =SUMIFS('AGT TB Apr -25'!L:L,'AGT TB Apr -25'!S:S,B56) -> 0 | H56: =SUM(C56:G56) -> 0
A57: 4 | B57: ESOP | C57: =SUMIFS('AGT TB Apr -25'!H:H,'AGT TB Apr -25'!S:S,B57) -> 0 | D57: =SUMIFS('AGT TB Apr -25'!I:I,'AGT TB Apr -25'!S:S,B57) -> 0 | E57: =SUMIFS('AGT TB Apr -25'!J:J,'AGT TB Apr -25'!S:S,B57) -> 0 | F57: =SUMIFS('AGT TB Apr -25'!K:K,'AGT TB Apr -25'!S:S,B57) -> 0 | G57: =SUMIFS('AGT TB Apr -25'!L:L,'AGT TB Apr -25'!S:S,B57) -> 0 | H57: =SUM(C57:G57) -> 0
B58: Bonus | C58: =SUMIFS('AGT TB Apr -25'!H:H,'AGT TB Apr -25'!S:S,B58) -> 0 | D58: =SUMIFS('AGT TB Apr -25'!I:I,'AGT TB Apr -25'!S:S,B58) -> 0 | E58: =SUMIFS('AGT TB Apr -25'!J:J,'AGT TB Apr -25'!S:S,B58) -> 0 | F58: =SUMIFS('AGT TB Apr -25'!K:K,'AGT TB Apr -25'!S:S,B58) -> 0 | G58: =SUMIFS('AGT TB Apr -25'!L:L,'AGT TB Apr -25'!S:S,B58) -> 0 | H58: =SUM(C58:G58) -> 0
B59: Contracted Employee | C59: =SUMIFS('AGT TB Apr -25'!H:H,'AGT TB Apr -25'!S:S,B59) -> 0 | D59: =SUMIFS('AGT TB Apr -25'!I:I,'AGT TB Apr -25'!S:S,B59) -> 0 | E59: =SUMIFS('AGT TB Apr -25'!J:J,'AGT TB Apr -25'!S:S,B59) -> 0 | F59: =SUMIFS('AGT TB Apr -25'!K:K,'AGT TB Apr -25'!S:S,B59) -> 0 | G59: =SUMIFS('AGT TB Apr -25'!L:L,'AGT TB Apr -25'!S:S,B59) -> 0 | H59: =SUM(C59:G59) -> 0
B60: Technical Expenses | C60: =SUM(C61:C61) -> 0 | D60: =SUM(D61:D61) -> 0 | E60: =SUM(E61:E61) -> 0 | F60: =SUM(F61:F61) -> 0 | G60: =SUM(G61:G61) -> 0 | H60: =SUM(C60:G60) -> 0
B61: Software Expenses | C61: =SUMIFS('AGT TB Apr -25'!H:H,'AGT TB Apr -25'!S:S,B61) -> 0 | D61: =SUMIFS('AGT TB Apr -25'!I:I,'AGT TB Apr -25'!S:S,B61) -> 0 | E61: =SUMIFS('AGT TB Apr -25'!J:J,'AGT TB Apr -25'!S:S,B61) -> 0 | F61: =SUMIFS('AGT TB Apr -25'!K:K,'AGT TB Apr -25'!S:S,B61) -> 0 | G61: =SUMIFS('AGT TB Apr -25'!L:L,'AGT TB Apr -25'!S:S,B61) -> 0 | H61: =SUM(C61:G61) -> 0
B62: Selling & Distribution exp | C62: =SUMIFS('AGT TB Apr -25'!H:H,'AGT TB Apr -25'!S:S,B62) -> 0 | D62: =SUMIFS('AGT TB Apr -25'!I:I,'AGT TB Apr -25'!S:S,B62) -> 0 | E62: =SUMIFS('AGT TB Apr -25'!J:J,'AGT TB Apr -25'!S:S,B62) -> 0 | F62: =SUMIFS('AGT TB Apr -25'!K:K,'AGT TB Apr -25'!S:S,B62) -> 0 | G62: =SUMIFS('AGT TB Apr -25'!L:L,'AGT TB Apr -25'!S:S,B62) -> 0 | H62: =SUM(C62:G62) -> 0
B63: Office Expenses | C63: =SUM(C64:C82) -> 0 | D63: =SUM(D64:D82) -> 0 | E63: =SUM(E64:E82) -> 0 | F63: =SUM(F64:F82) -> 0 | G63: =SUM(G64:G82) -> 0 | H63: =SUM(C63:G63) -> 0
B64: Office Rent | C64: =SUMIFS('AGT TB Apr -25'!H:H,'AGT TB Apr -25'!S:S,B64) -> 0 | D64: =SUMIFS('AGT TB Apr -25'!I:I,'AGT TB Apr -25'!S:S,B64) -> 0 | E64: =SUMIFS('AGT TB Apr -25'!J:J,'AGT TB Apr -25'!S:S,B64) -> 0 | F64: =SUMIFS('AGT TB Apr -25'!K:K,'AGT TB Apr -25'!S:S,B64) -> 0 | G64: =SUMIFS('AGT TB Apr -25'!L:L,'AGT TB Apr -25'!S:S,B64) -> 0 | H64: =SUM(C64:G64) -> 0
A65: 575000 | B65: Printer Rent | C65: =SUMIFS('AGT TB Apr -25'!H:H,'AGT TB Apr -25'!S:S,B65) -> 0 | D65: =SUMIFS('AGT TB Apr -25'!I:I,'AGT TB Apr -25'!S:S,B65) -> 0 | E65: =SUMIFS('AGT TB Apr -25'!J:J,'AGT TB Apr -25'!S:S,B65) -> 0 | F65: =SUMIFS('AGT TB Apr -25'!K:K,'AGT TB Apr -25'!S:S,B65) -> 0 | G65: =SUMIFS('AGT TB Apr -25'!L:L,'AGT TB Apr -25'!S:S,B65) -> 0 | H65: =SUM(C65:G65) -> 0
A66: =400000/118% -> 338983.05 | B66: House Rent | C66: =SUMIFS('AGT TB Apr -25'!H:H,'AGT TB Apr -25'!S:S,B66) -> 0 | D66: =SUMIFS('AGT TB Apr -25'!I:I,'AGT TB Apr -25'!S:S,B66) -> 0 | E66: =SUMIFS('AGT TB Apr -25'!J:J,'AGT TB Apr -25'!S:S,B66) -> 0 | F66: =SUMIFS('AGT TB Apr -25'!K:K,'AGT TB Apr -25'!S:S,B66) -> 0 | G66: =SUMIFS('AGT TB Apr -25'!L:L,'AGT TB Apr -25'!S:S,B66) -> 0 | H66: =SUM(C66:G66) -> 0
A67: =A65-A66 -> 236016.95 | B67: Internet Charges | C67: =SUMIFS('AGT TB Apr -25'!H:H,'AGT TB Apr -25'!S:S,B67) -> 0 | D67: =SUMIFS('AGT TB Apr -25'!I:I,'AGT TB Apr -25'!S:S,B67) -> 0 | E67: =SUMIFS('AGT TB Apr -25'!J:J,'AGT TB Apr -25'!S:S,B67) -> 0 | F67: =SUMIFS('AGT TB Apr -25'!K:K,'AGT TB Apr -25'!S:S,B67) -> 0 | G67: =SUMIFS('AGT TB Apr -25'!L:L,'AGT TB Apr -25'!S:S,B67) -> 0 | H67: =SUM(C67:G67) -> 0
B68: Installation charges | C68: =SUMIFS('AGT TB Apr -25'!H:H,'AGT TB Apr -25'!S:S,B68) -> 0 | D68: =SUMIFS('AGT TB Apr -25'!I:I,'AGT TB Apr -25'!S:S,B68) -> 0 | E68: =SUMIFS('AGT TB Apr -25'!J:J,'AGT TB Apr -25'!S:S,B68) -> 0 | F68: =SUMIFS('AGT TB Apr -25'!K:K,'AGT TB Apr -25'!S:S,B68) -> 0 | G68: =SUMIFS('AGT TB Apr -25'!L:L,'AGT TB Apr -25'!S:S,B68) -> 0 | H68: =SUM(C68:G68) -> 0
B69: Repairs & maintainance | C69: =SUMIFS('AGT TB Apr -25'!H:H,'AGT TB Apr -25'!S:S,B69) -> 0 | D69: =SUMIFS('AGT TB Apr -25'!I:I,'AGT TB Apr -25'!S:S,B69) -> 0 | E69: =SUMIFS('AGT TB Apr -25'!J:J,'AGT TB Apr -25'!S:S,B69) -> 0 | F69: =SUMIFS('AGT TB Apr -25'!K:K,'AGT TB Apr -25'!S:S,B69) -> 0 | G69: =SUMIFS('AGT TB Apr -25'!L:L,'AGT TB Apr -25'!S:S,B69) -> 0 | H69: =SUM(C69:G69) -> 0
B70: Telephone Expenses | C70: =SUMIFS('AGT TB Apr -25'!H:H,'AGT TB Apr -25'!S:S,B70) -> 0 | D70: =SUMIFS('AGT TB Apr -25'!I:I,'AGT TB Apr -25'!S:S,B70) -> 0 | E70: =SUMIFS('AGT TB Apr -25'!J:J,'AGT TB Apr -25'!S:S,B70) -> 0 | F70: =SUMIFS('AGT TB Apr -25'!K:K,'AGT TB Apr -25'!S:S,B70) -> 0 | G70: =SUMIFS('AGT TB Apr -25'!L:L,'AGT TB Apr -25'!S:S,B70) -> 0 | H70: =SUM(C70:G70) -> 0
B71: Testing and Inspection Charges | C71: =SUMIFS('AGT TB Apr -25'!H:H,'AGT TB Apr -25'!S:S,B71) -> 0 | D71: =SUMIFS('AGT TB Apr -25'!I:I,'AGT TB Apr -25'!S:S,B71) -> 0 | E71: =SUMIFS('AGT TB Apr -25'!J:J,'AGT TB Apr -25'!S:S,B71) -> 0 | F71: =SUMIFS('AGT TB Apr -25'!K:K,'AGT TB Apr -25'!S:S,B71) -> 0 | G71: =SUMIFS('AGT TB Apr -25'!L:L,'AGT TB Apr -25'!S:S,B71) -> 0 | H71: =SUM(C71:G71) -> 0
B72: Bank charges against Import/MTT Transaction | C72: =SUMIFS('AGT TB Apr -25'!H:H,'AGT TB Apr -25'!S:S,B72) -> 0 | D72: =SUMIFS('AGT TB Apr -25'!I:I,'AGT TB Apr -25'!S:S,B72) -> 0 | E72: =SUMIFS('AGT TB Apr -25'!J:J,'AGT TB Apr -25'!S:S,B72) -> 0 | F72: =SUMIFS('AGT TB Apr -25'!K:K,'AGT TB Apr -25'!S:S,B72) -> 0 | G72: =SUMIFS('AGT TB Apr -25'!L:L,'AGT TB Apr -25'!S:S,B72) -> 0 | H72: =SUM(C72:G72) -> 0
B73: Printing and Stationery | C73: =SUMIFS('AGT TB Apr -25'!H:H,'AGT TB Apr -25'!S:S,B73) -> 0 | D73: =SUMIFS('AGT TB Apr -25'!I:I,'AGT TB Apr -25'!S:S,B73) -> 0 | E73: =SUMIFS('AGT TB Apr -25'!J:J,'AGT TB Apr -25'!S:S,B73) -> 0 | F73: =SUMIFS('AGT TB Apr -25'!K:K,'AGT TB Apr -25'!S:S,B73) -> 0 | G73: =SUMIFS('AGT TB Apr -25'!L:L,'AGT TB Apr -25'!S:S,B73) -> 0 | H73: =SUM(C73:G73) -> 0
B74: Electricity Charges | C74: =SUMIFS('AGT TB Apr -25'!H:H,'AGT TB Apr -25'!S:S,B74) -> 0 | D74: =SUMIFS('AGT TB Apr -25'!I:I,'AGT TB Apr -25'!S:S,B74) -> 0 | E74: =SUMIFS('AGT TB Apr -25'!J:J,'AGT TB Apr -25'!S:S,B74) -> 0 | F74: =SUMIFS('AGT TB Apr -25'!K:K,'AGT TB Apr -25'!S:S,B74) -> 0 | G74: =SUMIFS('AGT TB Apr -25'!L:L,'AGT TB Apr -25'!S:S,B74) -> 0 | H74: =SUM(C74:G74) -> 0
B75: Business Promotion | C75: =SUMIFS('AGT TB Apr -25'!H:H,'AGT TB Apr -25'!S:S,B75) -> 0 | D75: =SUMIFS('AGT TB Apr -25'!I:I,'AGT TB Apr -25'!S:S,B75) -> 0 | E75: =SUMIFS('AGT TB Apr -25'!J:J,'AGT TB Apr -25'!S:S,B75) -> 0 | F75: =SUMIFS('AGT TB Apr -25'!K:K,'AGT TB Apr -25'!S:S,B75) -> 0 | G75: =SUMIFS('AGT TB Apr -25'!L:L,'AGT TB Apr -25'!S:S,B75) -> 0 | H75: =SUM(C75:G75) -> 0
B76: Housekeeping Charges | C76: =SUMIFS('AGT TB Apr -25'!H:H,'AGT TB Apr -25'!S:S,B76) -> 0 | D76: =SUMIFS('AGT TB Apr -25'!I:I,'AGT TB Apr -25'!S:S,B76) -> 0 | E76: =SUMIFS('AGT TB Apr -25'!J:J,'AGT TB Apr -25'!S:S,B76) -> 0 | F76: =SUMIFS('AGT TB Apr -25'!K:K,'AGT TB Apr -25'!S:S,B76) -> 0 | G76: =SUMIFS('AGT TB Apr -25'!L:L,'AGT TB Apr -25'!S:S,B76) -> 0 | H76: =SUM(C76:G76) -> 0
B77: Insurance Charges | C77: =SUMIFS('AGT TB Apr -25'!H:H,'AGT TB Apr -25'!S:S,B77) -> 0 | D77: =SUMIFS('AGT TB Apr -25'!I:I,'AGT TB Apr -25'!S:S,B77) -> 0 | E77: =SUMIFS('AGT TB Apr -25'!J:J,'AGT TB Apr -25'!S:S,B77) -> 0 | F77: =SUMIFS('AGT TB Apr -25'!K:K,'AGT TB Apr -25'!S:S,B77) -> 0 | G77: =SUMIFS('AGT TB Apr -25'!L:L,'AGT TB Apr -25'!S:S,B77) -> 0 | H77: =SUM(C77:G77) -> 0
B78: Diwali Expenses | C78: =SUMIFS('AGT TB Apr -25'!H:H,'AGT TB Apr -25'!S:S,B78) -> 0 | D78: =SUMIFS('AGT TB Apr -25'!I:I,'AGT TB Apr -25'!S:S,B78) -> 0 | E78: =SUMIFS('AGT TB Apr -25'!J:J,'AGT TB Apr -25'!S:S,B78) -> 0 | F78: =SUMIFS('AGT TB Apr -25'!K:K,'AGT TB Apr -25'!S:S,B78) -> 0 | G78: =SUMIFS('AGT TB Apr -25'!L:L,'AGT TB Apr -25'!S:S,B78) -> 0 | H78: =SUM(C78:G78) -> 0
B79: Warehouse Rent | C79: =SUMIFS('AGT TB Apr -25'!H:H,'AGT TB Apr -25'!S:S,B79) -> 0 | D79: =SUMIFS('AGT TB Apr -25'!I:I,'AGT TB Apr -25'!S:S,B79) -> 0 | E79: =SUMIFS('AGT TB Apr -25'!J:J,'AGT TB Apr -25'!S:S,B79) -> 0 | F79: =SUMIFS('AGT TB Apr -25'!K:K,'AGT TB Apr -25'!S:S,B79) -> 0 | G79: =SUMIFS('AGT TB Apr -25'!L:L,'AGT TB Apr -25'!S:S,B79) -> 0 | H79: =SUM(C79:G79) -> 0
... B82: Rates and Taxes | C82: =SUMIFS('AGT TB Apr -25'!H:H,'AGT TB Apr -25'!S:S,B82) -> 0 | D82: =SUMIFS('AGT TB Apr -25'!I:I,'AGT TB Apr -25'!S:S,B82) -> 0 | E82: =SUMIFS('AGT TB Apr -25'!J:J,'AGT TB Apr -25'!S:S,B82) -> 0 | F82: =SUMIFS('AGT TB Apr -25'!K:K,'AGT TB Apr -25'!S:S,B82) -> 0 | G82: =SUMIFS('AGT TB Apr -25'!L:L,'AGT TB Apr -25'!S:S,B82) -> 0 | H82: =SUM(C82:G82) -> 0
B83: Travelling & Conveyance | C83: =SUM(C84:C86) -> 0 | D83: =SUM(D84:D86) -> 0 | E83: =SUM(E84:E86) -> 0 | F83: =SUM(F84:F86) -> 0 | G83: =SUM(G84:G86) -> 0 | H83: =SUM(C83:G83) -> 0
B84: Travelling Expenses | C84: =SUMIFS('AGT TB Apr -25'!H:H,'AGT TB Apr -25'!S:S,B84) -> 0 | D84: =SUMIFS('AGT TB Apr -25'!I:I,'AGT TB Apr -25'!S:S,B84) -> 0 | E84: =SUMIFS('AGT TB Apr -25'!J:J,'AGT TB Apr -25'!S:S,B84) -> 0 | F84: =SUMIFS('AGT TB Apr -25'!K:K,'AGT TB Apr -25'!S:S,B84) -> 0 | G84: =SUMIFS('AGT TB Apr -25'!L:L,'AGT TB Apr -25'!S:S,B84) -> 0 | H84: =SUM(C84:G84) -> 0
B85: Travelling Expenses (Cash & Local) | C85: =SUMIFS('AGT TB Apr -25'!H:H,'AGT TB Apr -25'!S:S,B85) -> 0 | D85: =SUMIFS('AGT TB Apr -25'!I:I,'AGT TB Apr -25'!S:S,B85) -> 0 | E85: =SUMIFS('AGT TB Apr -25'!J:J,'AGT TB Apr -25'!S:S,B85) -> 0 | F85: =SUMIFS('AGT TB Apr -25'!K:K,'AGT TB Apr -25'!S:S,B85) -> 0 | G85: =SUMIFS('AGT TB Apr -25'!L:L,'AGT TB Apr -25'!S:S,B85) -> 0 | H85: =SUM(C85:G85) -> 0
B86: Employee Re-imbursementExpense | C86: =SUMIFS('AGT TB Apr -25'!H:H,'AGT TB Apr -25'!S:S,B86) -> 0 | D86: =SUMIFS('AGT TB Apr -25'!I:I,'AGT TB Apr -25'!S:S,B86) -> 0 | E86: =SUMIFS('AGT TB Apr -25'!J:J,'AGT TB Apr -25'!S:S,B86) -> 0 | F86: =SUMIFS('AGT TB Apr -25'!K:K,'AGT TB Apr -25'!S:S,B86) -> 0 | G86: =SUMIFS('AGT TB Apr -25'!L:L,'AGT TB Apr -25'!S:S,B86) -> 0 | H86: =SUM(C86:G86) -> 0
B87: Legal & Professional Fees | C87: =SUM(C88:C93) -> 0 | D87: =SUM(D88:D93) -> 0 | E87: =SUM(E88:E93) -> 0 | F87: =SUM(F88:F93) -> 0 | G87: =SUM(G88:G93) -> 0 | H87: =SUM(C87:G87) -> 0
B88: Finance Partner | C88: =SUMIFS('AGT TB Apr -25'!H:H,'AGT TB Apr -25'!S:S,B88) -> 0 | D88: =SUMIFS('AGT TB Apr -25'!I:I,'AGT TB Apr -25'!S:S,B88) -> 0 | E88: =SUMIFS('AGT TB Apr -25'!J:J,'AGT TB Apr -25'!S:S,B88) -> 0 | F88: =SUMIFS('AGT TB Apr -25'!K:K,'AGT TB Apr -25'!S:S,B88) -> 0 | G88: =SUMIFS('AGT TB Apr -25'!L:L,'AGT TB Apr -25'!S:S,B88) -> 0 | H88: =SUM(C88:G88) -> 0
B89: Professional Fees | C89: =SUMIFS('AGT TB Apr -25'!H:H,'AGT TB Apr -25'!S:S,B89) -> 0 | D89: =SUMIFS('AGT TB Apr -25'!I:I,'AGT TB Apr -25'!S:S,B89) -> 0 | E89: =SUMIFS('AGT TB Apr -25'!J:J,'AGT TB Apr -25'!S:S,B89) -> 0 | F89: =SUMIFS('AGT TB Apr -25'!K:K,'AGT TB Apr -25'!S:S,B89) -> 0 | G89: =SUMIFS('AGT TB Apr -25'!L:L,'AGT TB Apr -25'!S:S,B89) -> 0 | H89: =SUM(C89:G89) -> 0
B90: Audit Fees | C90: =SUMIFS('AGT TB Apr -25'!H:H,'AGT TB Apr -25'!S:S,B90) -> 0 | D90: =SUMIFS('AGT TB Apr -25'!I:I,'AGT TB Apr -25'!S:S,B90) -> 0 | E90: =SUMIFS('AGT TB Apr -25'!J:J,'AGT TB Apr -25'!S:S,B90) -> 0 | F90: =SUMIFS('AGT TB Apr -25'!K:K,'AGT TB Apr -25'!S:S,B90) -> 0 | G90: =SUMIFS('AGT TB Apr -25'!L:L,'AGT TB Apr -25'!S:S,B90) -> 0 | H90: =SUM(C90:G90) -> 0
B91: Hiring Partner | C91: =SUMIFS('AGT TB Apr -25'!H:H,'AGT TB Apr -25'!S:S,B91) -> 0 | D91: =SUMIFS('AGT TB Apr -25'!I:I,'AGT TB Apr -25'!S:S,B91) -> 0 | E91: =SUMIFS('AGT TB Apr -25'!J:J,'AGT TB Apr -25'!S:S,B91) -> 0 | F91: =SUMIFS('AGT TB Apr -25'!K:K,'AGT TB Apr -25'!S:S,B91) -> 0 | G91: =SUMIFS('AGT TB Apr -25'!L:L,'AGT TB Apr -25'!S:S,B91) -> 0 | H91: =SUM(C91:G91) -> 0
B92: Legal Expenses | C92: =SUMIFS('AGT TB Apr -25'!H:H,'AGT TB Apr -25'!S:S,B92) -> 0 | D92: =SUMIFS('AGT TB Apr -25'!I:I,'AGT TB Apr -25'!S:S,B92) -> 0 | E92: =SUMIFS('AGT TB Apr -25'!J:J,'AGT TB Apr -25'!S:S,B92) -> 0 | F92: =SUMIFS('AGT TB Apr -25'!K:K,'AGT TB Apr -25'!S:S,B92) -> 0 | G92: =SUMIFS('AGT TB Apr -25'!L:L,'AGT TB Apr -25'!S:S,B92) -> 0 | H92: =SUM(C92:G92) -> 0
B93: Branding Expenses | C93: =SUMIFS('AGT TB Apr -25'!H:H,'AGT TB Apr -25'!S:S,B93) -> 0 | D93: =SUMIFS('AGT TB Apr -25'!I:I,'AGT TB Apr -25'!S:S,B93) -> 0 | E93: =SUMIFS('AGT TB Apr -25'!J:J,'AGT TB Apr -25'!S:S,B93) -> 0 | F93: =SUMIFS('AGT TB Apr -25'!K:K,'AGT TB Apr -25'!S:S,B93) -> 0 | G93: =SUMIFS('AGT TB Apr -25'!L:L,'AGT TB Apr -25'!S:S,B93) -> 0 | H93: =SUM(C93:G93) -> 0
B94: Advertisement & Marketing Fees | C94: =SUM(C95:C98) -> 0 | D94: =SUM(D95:D98) -> 0 | E94: =SUM(E95:E98) -> 0 | F94: =SUM(F95:F98) -> 0 | G94: =SUM(G95:G98) -> 0 | H94: =SUM(C94:G94) -> 0
B95: Advertising Expenses | C95: =SUMIFS('AGT TB Apr -25'!H:H,'AGT TB Apr -25'!S:S,B95) -> 0 | D95: =SUMIFS('AGT TB Apr -25'!I:I,'AGT TB Apr -25'!S:S,B95) -> 0 | E95: =SUMIFS('AGT TB Apr -25'!J:J,'AGT TB Apr -25'!S:S,B95) -> 0 | F95: =SUMIFS('AGT TB Apr -25'!K:K,'AGT TB Apr -25'!S:S,B95) -> 0 | G95: =SUMIFS('AGT TB Apr -25'!L:L,'AGT TB Apr -25'!S:S,B95) -> 0 | H95: =SUM(C95:G95) -> 0
B96: Marketing Expenses | C96: =SUMIFS('AGT TB Apr -25'!H:H,'AGT TB Apr -25'!S:S,B96) -> 0 | D96: =SUMIFS('AGT TB Apr -25'!I:I,'AGT TB Apr -25'!S:S,B96) -> 0 | E96: =SUMIFS('AGT TB Apr -25'!J:J,'AGT TB Apr -25'!S:S,B96) -> 0 | F96: =SUMIFS('AGT TB Apr -25'!K:K,'AGT TB Apr -25'!S:S,B96) -> 0 | G96: =SUMIFS('AGT TB Apr -25'!L:L,'AGT TB Apr -25'!S:S,B96) -> 0 | H96: =SUM(C96:G96) -> 0
B97: Gulf-Food Registration fees | C97: =SUMIFS('AGT TB Apr -25'!H:H,'AGT TB Apr -25'!S:S,B97) -> 0 | D97: =SUMIFS('AGT TB Apr -25'!I:I,'AGT TB Apr -25'!S:S,B97) -> 0 | E97: =SUMIFS('AGT TB Apr -25'!J:J,'AGT TB Apr -25'!S:S,B97) -> 0 | F97: =SUMIFS('AGT TB Apr -25'!K:K,'AGT TB Apr -25'!S:S,B97) -> 0 | G97: =SUMIFS('AGT TB Apr -25'!L:L,'AGT TB Apr -25'!S:S,B97) -> 0 | H97: =SUM(C97:G97) -> 0
B98: Other Expenses | C98: =SUMIFS('AGT TB Apr -25'!H:H,'AGT TB Apr -25'!S:S,B98) -> 0 | D98: =SUMIFS('AGT TB Apr -25'!I:I,'AGT TB Apr -25'!S:S,B98) -> 0 | E98: =SUMIFS('AGT TB Apr -25'!J:J,'AGT TB Apr -25'!S:S,B98) -> 0 | F98: =SUMIFS('AGT TB Apr -25'!K:K,'AGT TB Apr -25'!S:S,B98) -> 0 | G98: =SUMIFS('AGT TB Apr -25'!L:L,'AGT TB Apr -25'!S:S,B98) -> 0 | H98: =SUM(C98:G98) -> 0
B99: Rates and Taxes | C99: =SUM(C100:C109) -> 0 | D99: =SUM(D100:D109) -> 0 | E99: =SUM(E100:E109) -> 0 | F99: =SUM(F100:F109) -> 0 | G99: =SUM(G100:G109) -> 0 | H99: =SUM(C99:G99) -> 0
B100: ROC Charges | C100: =SUMIFS('AGT TB Apr -25'!H:H,'AGT TB Apr -25'!S:S,B100) -> 0 | D100: =SUMIFS('AGT TB Apr -25'!I:I,'AGT TB Apr -25'!S:S,B100) -> 0 | E100: =SUMIFS('AGT TB Apr -25'!J:J,'AGT TB Apr -25'!S:S,B100) -> 0 | F100: =SUMIFS('AGT TB Apr -25'!K:K,'AGT TB Apr -25'!S:S,B100) -> 0 | G100: =SUMIFS('AGT TB Apr -25'!L:L,'AGT TB Apr -25'!S:S,B100) -> 0 | H100: =SUM(C100:G100) -> 0
B101: Custodian Charges | C101: =SUMIFS('AGT TB Apr -25'!H:H,'AGT TB Apr -25'!S:S,B101) -> 0 | D101: =SUMIFS('AGT TB Apr -25'!I:I,'AGT TB Apr -25'!S:S,B101) -> 0 | E101: =SUMIFS('AGT TB Apr -25'!J:J,'AGT TB Apr -25'!S:S,B101) -> 0 | F101: =SUMIFS('AGT TB Apr -25'!K:K,'AGT TB Apr -25'!S:S,B101) -> 0 | G101: =SUMIFS('AGT TB Apr -25'!L:L,'AGT TB Apr -25'!S:S,B101) -> 0 | H101: =SUM(C101:G101) -> 0
B102: Stamp Duty Charges | C102: =SUMIFS('AGT TB Apr -25'!H:H,'AGT TB Apr -25'!S:S,B102) -> 0 | D102: =SUMIFS('AGT TB Apr -25'!I:I,'AGT TB Apr -25'!S:S,B102) -> 0 | E102: =SUMIFS('AGT TB Apr -25'!J:J,'AGT TB Apr -25'!S:S,B102) -> 0 | F102: =SUMIFS('AGT TB Apr -25'!K:K,'AGT TB Apr -25'!S:S,B102) -> 0 | G102: =SUMIFS('AGT TB Apr -25'!L:L,'AGT TB Apr -25'!S:S,B102) -> 0 | H102: =SUM(C102:G102) -> 0
B103: IEC Registration | C103: =SUMIFS('AGT TB Apr -25'!H:H,'AGT TB Apr -25'!S:S,B103) -> 0 | D103: =SUMIFS('AGT TB Apr -25'!I:I,'AGT TB Apr -25'!S:S,B103) -> 0 | E103: =SUMIFS('AGT TB Apr -25'!J:J,'AGT TB Apr -25'!S:S,B103) -> 0 | F103: =SUMIFS('AGT TB Apr -25'!K:K,'AGT TB Apr -25'!S:S,B103) -> 0 | G103: =SUMIFS('AGT TB Apr -25'!L:L,'AGT TB Apr -25'!S:S,B103) -> 0 | H103: =SUM(C103:G103) -> 0
B104: Demat Charges | C104: =SUMIFS('AGT TB Apr -25'!H:H,'AGT TB Apr -25'!S:S,B104) -> 0 | D104: =SUMIFS('AGT TB Apr -25'!I:I,'AGT TB Apr -25'!S:S,B104) -> 0 | E104: =SUMIFS('AGT TB Apr -25'!J:J,'AGT TB Apr -25'!S:S,B104) -> 0 | F104: =SUMIFS('AGT TB Apr -25'!K:K,'AGT TB Apr -25'!S:S,B104) -> 0 | G104: =SUMIFS('AGT TB Apr -25'!L:L,'AGT TB Apr -25'!S:S,B104) -> 0 | H104: =SUM(C104:G104) -> 0
B105: Share Issue Expenses | C105: =SUMIFS('AGT TB Apr -25'!H:H,'AGT TB Apr -25'!S:S,B105) -> 0 | D105: =SUMIFS('AGT TB Apr -25'!I:I,'AGT TB Apr -25'!S:S,B105) -> 0 | E105: =SUMIFS('AGT TB Apr -25'!J:J,'AGT TB Apr -25'!S:S,B105) -> 0 | F105: =SUMIFS('AGT TB Apr -25'!K:K,'AGT TB Apr -25'!S:S,B105) -> 0 | G105: =SUMIFS('AGT TB Apr -25'!L:L,'AGT TB Apr -25'!S:S,B105) -> 0 | H105: =SUM(C105:G105) -> 0
B106: Other Rates and taxes | C106: =SUMIFS('AGT TB Apr -25'!H:H,'AGT TB Apr -25'!S:S,B106) -> 0 | D106: =SUMIFS('AGT TB Apr -25'!I:I,'AGT TB Apr -25'!S:S,B106) -> 0 | E106: =SUMIFS('AGT TB Apr -25'!J:J,'AGT TB Apr -25'!S:S,B106) -> 0 | F106: =SUMIFS('AGT TB Apr -25'!K:K,'AGT TB Apr -25'!S:S,B106) -> 0 | G106: =SUMIFS('AGT TB Apr -25'!L:L,'AGT TB Apr -25'!S:S,B106) -> 0 | H106: =SUM(C106:G106) -> 0
B107: GOVT Service | C107: =SUMIFS('AGT TB Apr -25'!H:H,'AGT TB Apr -25'!S:S,B107) -> 0 | D107: =SUMIFS('AGT TB Apr -25'!I:I,'AGT TB Apr -25'!S:S,B107) -> 0 | E107: =SUMIFS('AGT TB Apr -25'!J:J,'AGT TB Apr -25'!S:S,B107) -> 0 | F107: =SUMIFS('AGT TB Apr -25'!K:K,'AGT TB Apr -25'!S:S,B107) -> 0 | G107: =SUMIFS('AGT TB Apr -25'!L:L,'AGT TB Apr -25'!S:S,B107) -> 0 | H107: =SUM(C107:G107) -> 0
B108: Ejari charges | C108: =SUMIFS('AGT TB Apr -25'!H:H,'AGT TB Apr -25'!S:S,B108) -> 0 | D108: =SUMIFS('AGT TB Apr -25'!I:I,'AGT TB Apr -25'!S:S,B108) -> 0 | E108: =SUMIFS('AGT TB Apr -25'!J:J,'AGT TB Apr -25'!S:S,B108) -> 0 | F108: =SUMIFS('AGT TB Apr -25'!K:K,'AGT TB Apr -25'!S:S,B108) -> 0 | G108: =SUMIFS('AGT TB Apr -25'!L:L,'AGT TB Apr -25'!S:S,B108) -> 0 | H108: =SUM(C108:G108) -> 0
...

Sheet PL1_AGT
B1: Arha Platforms General Trading LLC | F1: -22.83 | H1: ='AGT TB Apr -25'!N1 -> 26 | L1: =SUBTOTAL(9,L5:L568) -> 0 | W1: =SUBTOTAL(9,W5:W568) -> 0 | AC1: =SUBTOTAL(9,AC5:AC568) -> 0
B2: Revenue and Margin by Invoice
J3: Purchase | L3: Purchase | O3: Direct Expense | U3: Sales | W3: Sales | AC3: Margin | AD3: Margin
B4: Month | C4: Invoice Number | D4: Month | E4: Segment | F4: Product | G4: Vendor Name | H4: Customer Name | I4: Qty (Measure) | J4: Qty | K4: Rate | L4: Amount (P) | M4: Discount on Purchase | N4: Net Purchase cost | O4: Direct Expense P.U | P4: Direct Expenses Cost (F) | Q4: Total Cost | R4: Customer Country | S4: Partner Name | T4: Direct Expenses | U4: Qty | V4: Rate | W4: Amount | X4: Discount on Sales | Y4: Net Sales | Z4: Adjustment | AA4: Total After Adjustment (S) | AB4: Foreign Exchange Gain/ (Loss) | AC4: Gross Margin 1 | AD4: Gross Margin 2 | AE4: Gross Margin 1 (%) | AF4: Gross Margin 2 (%) | AG4: Remarks
B5: =EOMONTH(A5,0) -> 31 | J5: =U5 -> 0 | K5: =L5/J5 -> #DIV/0! | N5: =L5-M5 -> 0 | O5: =P5/J5 -> #DIV/0! | Q5: =N5+P5 -> 0 | V5: =W5/U5 -> #DIV/0! | Y5: =W5-X5 -> 0 | AA5: =Y5-Z5 -> 0 | AC5: =Y5-N5 -> 0 | AD5: =AA5-Q5 -> 0 | AE5: =AC5/Y5 -> #DIV/0! | AF5: =AD5/AA5 -> #DIV/0!
B6: =EOMONTH(A6,0) -> 31 | J6: =U6 -> 0 | K6: =L6/J6 -> #DIV/0! | N6: =L6-M6 -> 0 | O6: =P6/J6 -> #DIV/0! | Q6: =N6+P6 -> 0 | V6: =W6/U6 -> #DIV/0! | Y6: =W6-X6 -> 0 | AA6: =Y6-Z6 -> 0 | AC6: =Y6-N6 -> 0 | AD6: =AA6-Q6 -> 0 | AE6: =AC6/Y6 -> #DIV/0! | AF6: =AD6/AA6 -> #DIV/0!
B7: =EOMONTH(A7,0) -> 31 | J7: =U7 -> 0 | K7: =L7/J7 -> #DIV/0! | N7: =L7-M7 -> 0 | O7: =P7/J7 -> #DIV/0! | Q7: =N7+P7 -> 0 | V7: =W7/U7 -> #DIV/0! | Y7: =W7-X7 -> 0 | AA7: =Y7-Z7 -> 0 | AC7: =Y7-N7 -> 0 | AD7: =AA7-Q7 -> 0 | AE7: =AC7/Y7 -> #DIV/0! | AF7: =AD7/AA7 -> #DIV/0!
B8: =EOMONTH(A8,0) -> 31 | J8: =U8 -> 0 | K8: =L8/J8 -> #DIV/0! | N8: =L8-M8 -> 0 | O8: =P8/J8 -> #DIV/0! | Q8: =N8+P8 -> 0 | V8: =W8/U8 -> #DIV/0! | Y8: =W8-X8 -> 0 | AA8: =Y8-Z8 -> 0 | AC8: =Y8-N8 -> 0 | AD8: =AA8-Q8 -> 0 | AE8: =AC8/Y8 -> #DIV/0! | AF8: =AD8/AA8 -> #DIV/0!
B9: =EOMONTH(A9,0) -> 31 | J9: =U9 -> 0 | K9: =L9/J9 -> #DIV/0! | N9: =L9-M9 -> 0 | O9: =P9/J9 -> #DIV/0! | Q9: =N9+P9 -> 0 | V9: =W9/U9 -> #DIV/0! | Y9: =W9-X9 -> 0 | AA9: =Y9-Z9 -> 0 | AC9: =Y9-N9 -> 0 | AD9: =AA9-Q9 -> 0 | AE9: =AC9/Y9 -> #DIV/0! | AF9: =AD9/AA9 -> #DIV/0!
B10: =EOMONTH(A10,0) -> 31 | J10: =U10 -> 0 | K10: =L10/J10 -> #DIV/0! | N10: =L10-M10 -> 0 | O10: =P10/J10 -> #DIV/0! | Q10: =N10+P10 -> 0 | V10: =W10/U10 -> #DIV/0! | Y10: =W10-X10 -> 0 | AA10: =Y10-Z10 -> 0 | AC10: =Y10-N10 -> 0 | AD10: =AA10-Q10 -> 0 | AE10: =AC10/Y10 -> #DIV/0! | AF10: =AD10/AA10 -> #DIV/0!
B11: =EOMONTH(A11,0) -> 31 | J11: =U11 -> 0 | K11: =L11/J11 -> #DIV/0! | N11: =L11-M11 -> 0 | O11: =P11/J11 -> #DIV/0! | Q11: =N11+P11 -> 0 | V11: =W11/U11 -> #DIV/0! | Y11: =W11-X11 -> 0 | AA11: =Y11-Z11 -> 0 | AC11: =Y11-N11 -> 0 | AD11: =AA11-Q11 -> 0 | AE11: =AC11/Y11 -> #DIV/0! | AF11: =AD11/AA11 -> #DIV/0!
B12: =EOMONTH(A12,0) -> 31 | J12: =U12 -> 0 | K12: =L12/J12 -> #DIV/0! | N12: =L12-M12 -> 0 | O12: =P12/J12 -> #DIV/0! | Q12: =N12+P12 -> 0 | V12: =W12/U12 -> #DIV/0! | Y12: =W12-X12 -> 0 | AA12: =Y12-Z12 -> 0 | AC12: =Y12-N12 -> 0 | AD12: =AA12-Q12 -> 0 | AE12: =AC12/Y12 -> #DIV/0! | AF12: =AD12/AA12 -> #DIV/0!
B13: =EOMONTH(A13,0) -> 31 | J13: =U13 -> 0 | K13: =L13/J13 -> #DIV/0! | N13: =L13-M13 -> 0 | O13: =P13/J13 -> #DIV/0! | Q13: =N13+P13 -> 0 | V13: =W13/U13 -> #DIV/0! | Y13: =W13-X13 -> 0 | AA13: =Y13-Z13 -> 0 | AC13: =Y13-N13 -> 0 | AD13: =AA13-Q13 -> 0 | AE13: =AC13/Y13 -> #DIV/0! | AF13: =AD13/AA13 -> #DIV/0!
B14: =EOMONTH(A14,0) -> 31 | J14: =U14 -> 0 | K14: =L14/J14 -> #DIV/0! | N14: =L14-M14 -> 0 | O14: =P14/J14 -> #DIV/0! | Q14: =N14+P14 -> 0 | V14: =W14/U14 -> #DIV/0! | Y14: =W14-X14 -> 0 | AA14: =Y14-Z14 -> 0 | AC14: =Y14-N14 -> 0 | AD14: =AA14-Q14 -> 0 | AE14: =AC14/Y14 -> #DIV/0! | AF14: =AD14/AA14 -> #DIV/0!
B15: =EOMONTH(A15,0) -> 31 | J15: =U15 -> 0 | K15: =L15/J15 -> #DIV/0! | N15: =L15-M15 -> 0 | O15: =P15/J15 -> #DIV/0! | Q15: =N15+P15 -> 0 | V15: =W15/U15 -> #DIV/0! | Y15: =W15-X15 -> 0 | AA15: =Y15-Z15 -> 0 | AC15: =Y15-N15 -> 0 | AD15: =AA15-Q15 -> 0 | AE15: =AC15/Y15 -> #DIV/0! | AF15: =AD15/AA15 -> #DIV/0!
B16: =EOMONTH(A16,0) -> 31 | J16: =U16 -> 0 | K16: =L16/J16 -> #DIV/0! | N16: =L16-M16 -> 0 | O16: =P16/J16 -> #DIV/0! | Q16: =N16+P16 -> 0 | V16: =W16/U16 -> #DIV/0! | Y16: =W16-X16 -> 0 | AA16: =Y16-Z16 -> 0 | AC16: =Y16-N16 -> 0 | AD16: =AA16-Q16 -> 0 | AE16: =AC16/Y16 -> #DIV/0! | AF16: =AD16/AA16 -> #DIV/0!
... B26: =EOMONTH(A26,0) -> 31 | J26: =U26 -> 0 | K26: =L26/J26 -> #DIV/0! | N26: =L26-M26 -> 0 | O26: =P26/J26 -> #DIV/0! | Q26: =N26+P26 -> 0 | V26: =W26/U26 -> #DIV/0! | Y26: =W26-X26 -> 0 | AA26: =Y26-Z26 -> 0 | AC26: =Y26-N26 -> 0 | AD26: =AA26-Q26 -> 0 | AE26: =AC26/Y26 -> #DIV/0! | AF26: =AD26/AA26 -> #DIV/0!
B27: =EOMONTH(A27,0) -> 31 | J27: =U27 -> 0 | K27: =L27/J27 -> #DIV/0! | N27: =L27-M27 -> 0 | O27: =P27/J27 -> #N/A | P27: =VLOOKUP(C27,'[1]Profit and Loss agt new'!$D$17:$E$52,2,) -> #N/A | Q27: =N27+P27 -> #N/A | V27: =W27/U27 -> #DIV/0! | Y27: =W27-X27 -> 0 | AA27: =Y27-Z27 -> 0 | AC27: =Y27-N27 -> 0 | AD27: =AA27-Q27 -> #N/A | AE27: =AC27/Y27 -> #DIV/0! | AF27: =AD27/AA27 -> #N/A
B28: =EOMONTH(A28,0) -> 31 | J28: =U28 -> 0 | K28: =L28/J28 -> #DIV/0! | N28: =L28-M28 -> 0 | O28: =P28/J28 -> #DIV/0! | Q28: =N28+P28 -> 0 | V28: =W28/U28 -> #DIV/0! | Y28: =W28-X28 -> 0 | AA28: =Y28-Z28 -> 0 | AC28: =Y28-N28 -> 0 | AD28: =AA28-Q28 -> 0 | AE28: =AC28/Y28 -> #DIV/0! | AF28: =AD28/AA28 -> #DIV/0!
B29: =EOMONTH(A29,0) -> 31 | J29: =U29 -> 0 | K29: =L29/J29 -> #DIV/0! | N29: =L29-M29 -> 0 | O29: =P29/J29 -> #DIV/0! | Q29: =N29+P29 -> 0 | V29: =W29/U29 -> #DIV/0! | Y29: =W29-X29 -> 0 | AA29: =Y29-Z29 -> 0 | AC29: =Y29-N29 -> 0 | AD29: =AA29-Q29 -> 0 | AE29: =AC29/Y29 -> #DIV/0! | AF29: =AD29/AA29 -> #DIV/0!
B30: =EOMONTH(A30,0) -> 31 | J30: =U30 -> 0 | K30: =L30/J30 -> #DIV/0! | N30: =L30-M30 -> 0 | O30: =P30/J30 -> #DIV/0! | Q30: =N30+P30 -> 0 | V30: =W30/U30 -> #DIV/0! | Y30: =W30-X30 -> 0 | AA30: =Y30-Z30 -> 0 | AC30: =Y30-N30 -> 0 | AD30: =AA30-Q30 -> 0 | AE30: =AC30/Y30 -> #DIV/0! | AF30: =AD30/AA30 -> #DIV/0!
B31: =EOMONTH(A31,0) -> 31 | J31: =U31 -> 0 | K31: =L31/J31 -> #DIV/0! | N31: =L31-M31 -> 0 | O31: =P31/J31 -> #DIV/0! | Q31: =N31+P31 -> 0 | V31: =W31/U31 -> #DIV/0! | Y31: =W31-X31 -> 0 | AA31: =Y31-Z31 -> 0 | AC31: =Y31-N31 -> 0 | AD31: =AA31-Q31 -> 0 | AE31: =AC31/Y31 -> #DIV/0! | AF31: =AD31/AA31 -> #DIV/0!
B32: =EOMONTH(A32,0) -> 31 | J32: =U32 -> 0 | K32: =L32/J32 -> #DIV/0! | N32: =L32-M32 -> 0 | O32: =P32/J32 -> #DIV/0! | Q32: =N32+P32 -> 0 | V32: =W32/U32 -> #DIV/0! | Y32: =W32-X32 -> 0 | AA32: =Y32-Z32 -> 0 | AC32: =Y32-N32 -> 0 | AD32: =AA32-Q32 -> 0 | AE32: =AC32/Y32 -> #DIV/0! | AF32: =AD32/AA32 -> #DIV/0!
B33: =EOMONTH(A33,0) -> 31 | J33: =U33 -> 0 | K33: =L33/J33 -> #DIV/0! | N33: =L33-M33 -> 0 | O33: =P33/J33 -> #DIV/0! | Q33: =N33+P33 -> 0 | V33: =W33/U33 -> #DIV/0! | Y33: =W33-X33 -> 0 | AA33: =Y33-Z33 -> 0 | AC33: =Y33-N33 -> 0 | AD33: =AA33-Q33 -> 0 | AE33: =AC33/Y33 -> #DIV/0! | AF33: =AD33/AA33 -> #DIV/0!
B34: =EOMONTH(A34,0) -> 31 | J34: =U34 -> 0 | K34: =L34/J34 -> #DIV/0! | N34: =L34-M34 -> 0 | O34: =P34/J34 -> #DIV/0! | Q34: =N34+P34 -> 0 | V34: =W34/U34 -> #DIV/0! | Y34: =W34-X34 -> 0 | AA34: =Y34-Z34 -> 0 | AC34: =Y34-N34 -> 0 | AD34: =AA34-Q34 -> 0 | AE34: =AC34/Y34 -> #DIV/0! | AF34: =AD34/AA34 -> #DIV/0!
B35: =EOMONTH(A35,0) -> 31 | J35: =U35 -> 0 | K35: =L35/J35 -> #DIV/0! | N35: =L35-M35 -> 0 | O35: =P35/J35 -> #DIV/0! | Q35: =N35+P35 -> 0 | V35: =W35/U35 -> #DIV/0! | Y35: =W35-X35 -> 0 | AA35: =Y35-Z35 -> 0 | AC35: =Y35-N35 -> 0 | AD35: =AA35-Q35 -> 0 | AE35: =AC35/Y35 -> #DIV/0! | AF35: =AD35/AA35 -> #DIV/0!
B36: =EOMONTH(A36,0) -> 31 | J36: =U36 -> 0 | K36: =L36/J36 -> #DIV/0! | N36: =L36-M36 -> 0 | O36: =P36/J36 -> #DIV/0! | Q36: =N36+P36 -> 0 | V36: =W36/U36 -> #DIV/0! | Y36: =W36-X36 -> 0 | AA36: =Y36-Z36 -> 0 | AC36: =Y36-N36 -> 0 | AD36: =AA36-Q36 -> 0 | AE36: =AC36/Y36 -> #DIV/0! | AF36: =AD36/AA36 -> #DIV/0!
B37: =EOMONTH(A37,0) -> 31 | J37: =U37 -> 0 | K37: =L37/J37 -> #DIV/0! | N37: =L37-M37 -> 0 | O37: =P37/J37 -> #DIV/0! | Q37: =N37+P37 -> 0 | V37: =W37/U37 -> #DIV/0! | Y37: =W37-X37 -> 0 | AA37: =Y37-Z37 -> 0 | AC37: =Y37-N37 -> 0 | AD37: =AA37-Q37 -> 0 | AE37: =AC37/Y37 -> #DIV/0! | AF37: =AD37/AA37 -> #DIV/0!
B38: =EOMONTH(A38,0) -> 31 | J38: =U38 -> 0 | K38: =L38/J38 -> #DIV/0! | N38: =L38-M38 -> 0 | O38: =P38/J38 -> #DIV/0! | Q38: =N38+P38 -> 0 | V38: =W38/U38 -> #DIV/0! | Y38: =W38-X38 -> 0 | AA38: =Y38-Z38 -> 0 | AC38: =Y38-N38 -> 0 | AD38: =AA38-Q38 -> 0 | AE38: =AC38/Y38 -> #DIV/0! | AF38: =AD38/AA38 -> #DIV/0!
B39: =EOMONTH(A39,0) -> 31 | J39: =U39 -> 0 | K39: =L39/J39 -> #DIV/0! | N39: =L39-M39 -> 0 | O39: =P39/J39 -> #DIV/0! | Q39: =N39+P39 -> 0 | V39: =W39/U39 -> #DIV/0! | Y39: =W39-X39 -> 0 | AA39: =Y39-Z39 -> 0 | AC39: =Y39-N39 -> 0 | AD39: =AA39-Q39 -> 0 | AE39: =AC39/Y39 -> #DIV/0! | AF39: =AD39/AA39 -> #DIV/0!
... B76: =EOMONTH(A76,0) -> 31 | J76: =U76 -> 0 | K76: =L76/J76 -> #DIV/0! | N76: =L76-M76 -> 0 | O76: =P76/J76 -> #DIV/0! | Q76: =N76+P76 -> 0 | V76: =W76/U76 -> #DIV/0! | Y76: =W76-X76 -> 0 | AA76: =Y76-Z76 -> 0 | AC76: =Y76-N76 -> 0 | AD76: =AA76-Q76 -> 0 | AE76: =AC76/Y76 -> #DIV/0! | AF76: =AD76/AA76 -> #DIV/0!
B77: =EOMONTH(A77,0) -> 31 | J77: =U77 -> 0 | K77: =L77/J77 -> #DIV/0! | N77: =L77-M77 -> 0 | O77: =P77/J77 -> #N/A | P77: =VLOOKUP(C77,'[1]Profit and Loss agt new'!$D$17:$E$52,2,) -> #N/A | Q77: =N77+P77 -> #N/A | V77: =W77/U77 -> #DIV/0! | Y77: =W77-X77 -> 0 | AA77: =Y77-Z77 -> 0 | AC77: =Y77-N77 -> 0 | AD77: =AA77-Q77 -> #N/A | AE77: =AC77/Y77 -> #DIV/0! | AF77: =AD77/AA77 -> #N/A
B78: =EOMONTH(A78,0) -> 31 | J78: =U78 -> 0 | K78: =L78/J78 -> #DIV/0! | N78: =L78-M78 -> 0 | O78: =P78/J78 -> #DIV/0! | Q78: =N78+P78 -> 0 | V78: =W78/U78 -> #DIV/0! | Y78: =W78-X78 -> 0 | AA78: =Y78-Z78 -> 0 | AC78: =Y78-N78 -> 0 | AD78: =AA78-Q78 -> 0 | AE78: =AC78/Y78 -> #DIV/0! | AF78: =AD78/AA78 -> #DIV/0!
B79: =EOMONTH(A79,0) -> 31 | J79: =U79 -> 0 | K79: =L79/J79 -> #DIV/0! | N79: =L79-M79 -> 0 | O79: =P79/J79 -> #DIV/0! | Q79: =N79+P79 -> 0 | V79: =W79/U79 -> #DIV/0! | Y79: =W79-X79 -> 0 | AA79: =Y79-Z79 -> 0 | AC79: =Y79-N79 -> 0 | AD79: =AA79-Q79 -> 0 | AE79: =AC79/Y79 -> #DIV/0! | AF79: =AD79/AA79 -> #DIV/0!
B80: =EOMONTH(A80,0) -> 31 | J80: =U80 -> 0 | K80: =L80/J80 -> #DIV/0! | N80: =L80-M80 -> 0 | O80: =P80/J80 -> #DIV/0! | Q80: =N80+P80 -> 0 | V80: =W80/U80 -> #DIV/0! | Y80: =W80-X80 -> 0 | AA80: =Y80-Z80 -> 0 | AC80: =Y80-N80 -> 0 | AD80: =AA80-Q80 -> 0 | AE80: =AC80/Y80 -> #DIV/0! | AF80: =AD80/AA80 -> #DIV/0!
B81: =EOMONTH(A81,0) -> 31 | J81: =U81 -> 0 | K81: =L81/J81 -> #DIV/0! | N81: =L81-M81 -> 0 | O81: =P81/J81 -> #DIV/0! | Q81: =N81+P81 -> 0 | V81: =W81/U81 -> #DIV/0! | Y81: =W81-X81 -> 0 | AA81: =Y81-Z81 -> 0 | AC81: =Y81-N81 -> 0 | AD81: =AA81-Q81 -> 0 | AE81: =AC81/Y81 -> #DIV/0! | AF81: =AD81/AA81 -> #DIV/0!
B82: =EOMONTH(A82,0) -> 31 | J82: =U82 -> 0 | K82: =L82/J82 -> #DIV/0! | N82: =L82-M82 -> 0 | O82: =P82/J82 -> #DIV/0! | Q82: =N82+P82 -> 0 | V82: =W82/U82 -> #DIV/0! | Y82: =W82-X82 -> 0 | AA82: =Y82-Z82 -> 0 | AC82: =Y82-N82 -> 0 | AD82: =AA82-Q82 -> 0 | AE82: =AC82/Y82 -> #DIV/0! | AF82: =AD82/AA82 -> #DIV/0!
B83: =EOMONTH(A83,0) -> 31 | J83: =U83 -> 0 | K83: =L83/J83 -> #DIV/0! | N83: =L83-M83 -> 0 | O83: =P83/J83 -> #DIV/0! | Q83: =N83+P83 -> 0 | V83: =W83/U83 -> #DIV/0! | Y83: =W83-X83 -> 0 | AA83: =Y83-Z83 -> 0 | AC83: =Y83-N83 -> 0 | AD83: =AA83-Q83 -> 0 | AE83: =AC83/Y83 -> #DIV/0! | AF83: =AD83/AA83 -> #DIV/0!
B84: =EOMONTH(A84,0) -> 31 | J84: =U84 -> 0 | K84: =L84/J84 -> #DIV/0! | N84: =L84-M84 -> 0 | O84: =P84/J84 -> #DIV/0! | Q84: =N84+P84 -> 0 | V84: =W84/U84 -> #DIV/0! | Y84: =W84-X84 -> 0 | AA84: =Y84-Z84 -> 0 | AC84: =Y84-N84 -> 0 | AD84: =AA84-Q84 -> 0 | AE84: =AC84/Y84 -> #DIV/0! | AF84: =AD84/AA84 -> #DIV/0!
B85: =EOMONTH(A85,0) -> 31 | J85: =U85 -> 0 | K85: =L85/J85 -> #DIV/0! | N85: =L85-M85 -> 0 | O85: =P85/J85 -> #DIV/0! | Q85: =N85+P85 -> 0 | V85: =W85/U85 -> #DIV/0! | Y85: =W85-X85 -> 0 | AA85: =Y85-Z85 -> 0 | AC85: =Y85-N85 -> 0 | AD85: =AA85-Q85 -> 0 | AE85: =AC85/Y85 -> #DIV/0! | AF85: =AD85/AA85 -> #DIV/0!
B86: =EOMONTH(A86,0) -> 31 | J86: =U86 -> 0 | K86: =L86/J86 -> #DIV/0! | N86: =L86-M86 -> 0 | O86: =P86/J86 -> #DIV/0! | Q86: =N86+P86 -> 0 | V86: =W86/U86 -> #DIV/0! | Y86: =W86-X86 -> 0 | AA86: =Y86-Z86 -> 0 | AC86: =Y86-N86 -> 0 | AD86: =AA86-Q86 -> 0 | AE86: =AC86/Y86 -> #DIV/0! | AF86: =AD86/AA86 -> #DIV/0!
B87: =EOMONTH(A87,0) -> 31 | J87: =U87 -> 0 | K87: =L87/J87 -> #DIV/0! | N87: =L87-M87 -> 0 | O87: =P87/J87 -> #DIV/0! | Q87: =N87+P87 -> 0 | V87: =W87/U87 -> #DIV/0! | Y87: =W87-X87 -> 0 | AA87: =Y87-Z87 -> 0 | AC87: =Y87-N87 -> 0 | AD87: =AA87-Q87 -> 0 | AE87: =AC87/Y87 -> #DIV/0! | AF87: =AD87/AA87 -> #DIV/0!
B88: =EOMONTH(A88,0) -> 31 | J88: =U88 -> 0 | K88: =L88/J88 -> #DIV/0! | N88: =L88-M88 -> 0 | O88: =P88/J88 -> #DIV/0! | Q88: =N88+P88 -> 0 | V88: =W88/U88 -> #DIV/0! | Y88: =W88-X88 -> 0 | AA88: =Y88-Z88 -> 0 | AC88: =Y88-N88 -> 0 | AD88: =AA88-Q88 -> 0 | AE88: =AC88/Y88 -> #DIV/0! | AF88: =AD88/AA88 -> #DIV/0!
B89: =EOMONTH(A89,0) -> 31 | J89: =U89 -> 0 | K89: =L89/J89 -> #DIV/0! | N89: =L89-M89 -> 0 | O89: =P89/J89 -> #DIV/0! | Q89: =N89+P89 -> 0 | V89: =W89/U89 -> #DIV/0! | Y89: =W89-X89 -> 0 | AA89: =Y89-Z89 -> 0 | AC89: =Y89-N89 -> 0 | AD89: =AA89-Q89 -> 0 | AE89: =AC89/Y89 -> #DIV/0! | AF89: =AD89/AA89 -> #DIV/0!
... B203: =EOMONTH(A203,0) -> 31 | J203: =U203 -> 0 | K203: =L203/J203 -> #DIV/0! | N203: =L203-M203 -> 0 | O203: =P203/J203 -> #DIV/0! | Q203: =N203+P203 -> 0 | V203: =W203/U203 -> #DIV/0! | Y203: =W203-X203 -> 0 | AA203: =Y203-Z203 -> 0 | AC203: =Y203-N203 -> 0 | AD203: =AA203-Q203 -> 0 | AE203: =AC203/Y203 -> #DIV/0! | AF203: =AD203/AA203 -> #DIV/0!
B204: =EOMONTH(A204,0) -> 31 | J204: =U204 -> 0 | K204: =L204/J204 -> #DIV/0! | N204: =L204-M204 -> 0 | O204: =P204/J204 -> #N/A | P204: =VLOOKUP(C204,'[1]Profit and Loss agt new'!$D$17:$E$52,2,) -> #N/A | Q204: =N204+P204 -> #N/A | V204: =W204/U204 -> #DIV/0! | Y204: =W204-X204 -> 0 | AA204: =Y204-Z204 -> 0 | AC204: =Y204-N204 -> 0 | AD204: =AA204-Q204 -> #N/A | AE204: =AC204/Y204 -> #DIV/0! | AF204: =AD204/AA204 -> #N/A
B205: =EOMONTH(A205,0) -> 31 | J205: =U205 -> 0 | K205: =L205/J205 -> #DIV/0! | N205: =L205-M205 -> 0 | O205: =P205/J205 -> #DIV/0! | Q205: =N205+P205 -> 0 | V205: =W205/U205 -> #DIV/0! | Y205: =W205-X205 -> 0 | AA205: =Y205-Z205 -> 0 | AC205: =Y205-N205 -> 0 | AD205: =AA205-Q205 -> 0 | AE205: =AC205/Y205 -> #DIV/0! | AF205: =AD205/AA205 -> #DIV/0!
B206: =EOMONTH(A206,0) -> 31 | J206: =U206 -> 0 | K206: =L206/J206 -> #DIV/0! | N206: =L206-M206 -> 0 | O206: =P206/J206 -> #DIV/0! | Q206: =N206+P206 -> 0 | V206: =W206/U206 -> #DIV/0! | Y206: =W206-X206 -> 0 | AA206: =Y206-Z206 -> 0 | AC206: =Y206-N206 -> 0 | AD206: =AA206-Q206 -> 0 | AE206: =AC206/Y206 -> #DIV/0! | AF206: =AD206/AA206 -> #DIV/0!
B207: =EOMONTH(A207,0) -> 31 | J207: =U207 -> 0 | K207: =L207/J207 -> #DIV/0! | N207: =L207-M207 -> 0 | O207: =P207/J207 -> #DIV/0! | Q207: =N207+P207 -> 0 | V207: =W207/U207 -> #DIV/0! | Y207: =W207-X207 -> 0 | AA207: =Y207-Z207 -> 0 | AC207: =Y207-N207 -> 0 | AD207: =AA207-Q207 -> 0 | AE207: =AC207/Y207 -> #DIV/0! | AF207: =AD207/AA207 -> #DIV/0!
B208: =EOMONTH(A208,0) -> 31 | J208: =U208 -> 0 | K208: =L208/J208 -> #DIV/0! | N208: =L208-M208 -> 0 | O208: =P208/J208 -> #DIV/0! | Q208: =N208+P208 -> 0 | V208: =W208/U208 -> #DIV/0! | Y208: =W208-X208 -> 0 | AA208: =Y208-Z208 -> 0 | AC208: =Y208-N208 -> 0 | AD208: =AA208-Q208 -> 0 | AE208: =AC208/Y208 -> #DIV/0! | AF208: =AD208/AA208 -> #DIV/0!
B209: =EOMONTH(A209,0) -> 31 | J209: =U209 -> 0 | K209: =L209/J209 -> #DIV/0! | N209: =L209-M209 -> 0 | O209: =P209/J209 -> #DIV/0! | Q209: =N209+P209 -> 0 | V209: =W209/U209 -> #DIV/0! | Y209: =W209-X209 -> 0 | AA209: =Y209-Z209 -> 0 | AC209: =Y209-N209 -> 0 | AD209: =AA209-Q209 -> 0 | AE209: =AC209/Y209 -> #DIV/0! | AF209: =AD209/AA209 -> #DIV/0!
B210: =EOMONTH(A210,0) -> 31 | J210: =U210 -> 0 | K210: =L210/J210 -> #DIV/0! | N210: =L210-M210 -> 0 | O210: =P210/J210 -> #DIV/0! | Q210: =N210+P210 -> 0 | V210: =W210/U210 -> #DIV/0! | Y210: =W210-X210 -> 0 | AA210: =Y210-Z210 -> 0 | AC210: =Y210-N210 -> 0 | AD210: =AA210-Q210 -> 0 | AE210: =AC210/Y210 -> #DIV/0! | AF210: =AD210/AA210 -> #DIV/0!
B211: =EOMONTH(A211,0) -> 31 | J211: =U211 -> 0 | K211: =L211/J211 -> #DIV/0! | N211: =L211-M211 -> 0 | O211: =P211/J211 -> #DIV/0! | Q211: =N211+P211 -> 0 | V211: =W211/U211 -> #DIV/0! | Y211: =W211-X211 -> 0 | AA211: =Y211-Z211 -> 0 | AC211: =Y211-N211 -> 0 | AD211: =AA211-Q211 -> 0 | AE211: =AC211/Y211 -> #DIV/0! | AF211: =AD211/AA211 -> #DIV/0!
B212: =EOMONTH(A212,0) -> 31 | J212: =U212 -> 0 | K212: =L212/J212 -> #DIV/0! | N212: =L212-M212 -> 0 | O212: =P212/J212 -> #DIV/0! | Q212: =N212+P212 -> 0 | V212: =W212/U212 -> #DIV/0! | Y212: =W212-X212 -> 0 | AA212: =Y212-Z212 -> 0 | AC212: =Y212-N212 -> 0 | AD212: =AA212-Q212 -> 0 | AE212: =AC212/Y212 -> #DIV/0! | AF212: =AD212/AA212 -> #DIV/0!
B213: =EOMONTH(A213,0) -> 31 | J213: =U213 -> 0 | K213: =L213/J213 -> #DIV/0! | N213: =L213-M213 -> 0 | O213: =P213/J213 -> #DIV/0! | Q213: =N213+P213 -> 0 | V213: =W213/U213 -> #DIV/0! | Y213: =W213-X213 -> 0 | AA213: =Y213-Z213 -> 0 | AC213: =Y213-N213 -> 0 | AD213: =AA213-Q213 -> 0 | AE213: =AC213/Y213 -> #DIV/0! | AF213: =AD213/AA213 -> #DIV/0!
B214: =EOMONTH(A214,0) -> 31 | J214: =U214 -> 0 | K214: =L214/J214 -> #DIV/0! | N214: =L214-M214 -> 0 | O214: =P214/J214 -> #DIV/0! | Q214: =N214+P214 -> 0 | V214: =W214/U214 -> #DIV/0! | Y214: =W214-X214 -> 0 | AA214: =Y214-Z214 -> 0 | AC214: =Y214-N214 -> 0 | AD214: =AA214-Q214 -> 0 | AE214: =AC214/Y214 -> #DIV/0! | AF214: =AD214/AA214 -> #DIV/0!
B215: =EOMONTH(A215,0) -> 31 | J215: =U215 -> 0 | K215: =L215/J215 -> #DIV/0! | N215: =L215-M215 -> 0 | O215: =P215/J215 -> #DIV/0! | Q215: =N215+P215 -> 0 | V215: =W215/U215 -> #DIV/0! | Y215: =W215-X215 -> 0 | AA215: =Y215-Z215 -> 0 | AC215: =Y215-N215 -> 0 | AD215: =AA215-Q215 -> 0 | AE215: =AC215/Y215 -> #DIV/0! | AF215: =AD215/AA215 -> #DIV/0!
B216: =EOMONTH(A216,0) -> 31 | J216: =U216 -> 0 | K216: =L216/J216 -> #DIV/0! | N216: =L216-M216 -> 0 | O216: =P216/J216 -> #DIV/0! | Q216: =N216+P216 -> 0 | V216: =W216/U216 -> #DIV/0! | Y216: =W216-X216 -> 0 | AA216: =Y216-Z216 -> 0 | AC216: =Y216-N216 -> 0 | AD216: =AA216-Q216 -> 0 | AE216: =AC216/Y216 -> #DIV/0! | AF216: =AD216/AA216 -> #DIV/0!
... B266: =EOMONTH(A266,0) -> 31 | J266: =U266 -> 0 | K266: =L266/J266 -> #DIV/0! | N266: =L266-M266 -> 0 | O266: =P266/J266 -> #DIV/0! | Q266: =N266+P266 -> 0 | V266: =W266/U266 -> #DIV/0! | Y266: =W266-X266 -> 0 | AA266: =Y266-Z266 -> 0 | AC266: =Y266-N266 -> 0 | AD266: =AA266-Q266 -> 0 | AE266: =AC266/Y266 -> #DIV/0! | AF266: =AD266/AA266 -> #DIV/0!
B267: =EOMONTH(A267,0) -> 31 | J267: =U267 -> 0 | K267: =L267/J267 -> #DIV/0! | N267: =L267-M267 -> 0 | O267: =P267/J267 -> #N/A | P267: =VLOOKUP(C267,'[1]Profit and Loss agt new'!$D$17:$E$52,2,) -> #N/A | Q267: =N267+P267 -> #N/A | V267: =W267/U267 -> #DIV/0! | Y267: =W267-X267 -> 0 | AA267: =Y267-Z267 -> 0 | AC267: =Y267-N267 -> 0 | AD267: =AA267-Q267 -> #N/A | AE267: =AC267/Y267 -> #DIV/0! | AF267: =AD267/AA267 -> #N/A
B268: =EOMONTH(A268,0) -> 31 | J268: =U268 -> 0 | K268: =L268/J268 -> #DIV/0! | N268: =L268-M268 -> 0 | O268: =P268/J268 -> #DIV/0! | Q268: =N268+P268 -> 0 | V268: =W268/U268 -> #DIV/0! | Y268: =W268-X268 -> 0 | AA268: =Y268-Z268 -> 0 | AC268: =Y268-N268 -> 0 | AD268: =AA268-Q268 -> 0 | AE268: =AC268/Y268 -> #DIV/0! | AF268: =AD268/AA268 -> #DIV/0!
B269: =EOMONTH(A269,0) -> 31 | J269: =U269 -> 0 | K269: =L269/J269 -> #DIV/0! | N269: =L269-M269 -> 0 | O269: =P269/J269 -> #DIV/0! | Q269: =N269+P269 -> 0 | V269: =W269/U269 -> #DIV/0! | Y269: =W269-X269 -> 0 | AA269: =Y269-Z269 -> 0 | AC269: =Y269-N269 -> 0 | AD269: =AA269-Q269 -> 0 | AE269: =AC269/Y269 -> #DIV/0! | AF269: =AD269/AA269 -> #DIV/0!
B270: =EOMONTH(A270,0) -> 31 | J270: =U270 -> 0 | K270: =L270/J270 -> #DIV/0! | N270: =L270-M270 -> 0 | O270: =P270/J270 -> #DIV/0! | Q270: =N270+P270 -> 0 | V270: =W270/U270 -> #DIV/0! | Y270: =W270-X270 -> 0 | AA270: =Y270-Z270 -> 0 | AC270: =Y270-N270 -> 0 | AD270: =AA270-Q270 -> 0 | AE270: =AC270/Y270 -> #DIV/0! | AF270: =AD270/AA270 -> #DIV/0!
B271: =EOMONTH(A271,0) -> 31 | J271: =U271 -> 0 | K271: =L271/J271 -> #DIV/0! | N271: =L271-M271 -> 0 | O271: =P271/J271 -> #DIV/0! | Q271: =N271+P271 -> 0 | V271: =W271/U271 -> #DIV/0! | Y271: =W271-X271 -> 0 | AA271: =Y271-Z271 -> 0 | AC271: =Y271-N271 -> 0 | AD271: =AA271-Q271 -> 0 | AE271: =AC271/Y271 -> #DIV/0! | AF271: =AD271/AA271 -> #DIV/0!
B272: =EOMONTH(A272,0) -> 31 | J272: =U272 -> 0 | K272: =L272/J272 -> #DIV/0! | N272: =L272-M272 -> 0 | O272: =P272/J272 -> #DIV/0! | Q272: =N272+P272 -> 0 | V272: =W272/U272 -> #DIV/0! | Y272: =W272-X272 -> 0 | AA272: =Y272-Z272 -> 0 | AC272: =Y272-N272 -> 0 | AD272: =AA272-Q272 -> 0 | AE272: =AC272/Y272 -> #DIV/0! | AF272: =AD272/AA272 -> #DIV/0!
B273: =EOMONTH(A273,0) -> 31 | J273: =U273 -> 0 | K273: =L273/J273 -> #DIV/0! | N273: =L273-M273 -> 0 | O273: =P273/J273 -> #DIV/0! | Q273: =N273+P273 -> 0 | V273: =W273/U273 -> #DIV/0! | Y273: =W273-X273 -> 0 | AA273: =Y273-Z273 -> 0 | AC273: =Y273-N273 -> 0 | AD273: =AA273-Q273 -> 0 | AE273: =AC273/Y273 -> #DIV/0! | AF273: =AD273/AA273 -> #DIV/0!
B274: =EOMONTH(A274,0) -> 31 | J274: =U274 -> 0 | K274: =L274/J274 -> #DIV/0! | N274: =L274-M274 -> 0 | O274: =P274/J274 -> #DIV/0! | Q274: =N274+P274 -> 0 | V274: =W274/U274 -> #DIV/0! | Y274: =W274-X274 -> 0 | AA274: =Y274-Z274 -> 0 | AC274: =Y274-N274 -> 0 | AD274: =AA274-Q274 -> 0 | AE274: =AC274/Y274 -> #DIV/0! | AF274: =AD274/AA274 -> #DIV/0!
B275: =EOMONTH(A275,0) -> 31 | J275: =U275 -> 0 | K275: =L275/J275 -> #DIV/0! | N275: =L275-M275 -> 0 | O275: =P275/J275 -> #DIV/0! | Q275: =N275+P275 -> 0 | V275: =W275/U275 -> #DIV/0! | Y275: =W275-X275 -> 0 | AA275: =Y275-Z275 -> 0 | AC275: =Y275-N275 -> 0 | AD275: =AA275-Q275 -> 0 | AE275: =AC275/Y275 -> #DIV/0! | AF275: =AD275/AA275 -> #DIV/0!
B276: =EOMONTH(A276,0) -> 31 | J276: =U276 -> 0 | K276: =L276/J276 -> #DIV/0! | N276: =L276-M276 -> 0 | O276: =P276/J276 -> #DIV/0! | Q276: =N276+P276 -> 0 | V276: =W276/U276 -> #DIV/0! | Y276: =W276-X276 -> 0 | AA276: =Y276-Z276 -> 0 | AC276: =Y276-N276 -> 0 | AD276: =AA276-Q276 -> 0 | AE276: =AC276/Y276 -> #DIV/0! | AF276: =AD276/AA276 -> #DIV/0!
B277: =EOMONTH(A277,0) -> 31 | J277: =U277 -> 0 | K277: =L277/J277 -> #DIV/0! | N277: =L277-M277 -> 0 | O277: =P277/J277 -> #DIV/0! | Q277: =N277+P277 -> 0 | V277: =W277/U277 -> #DIV/0! | Y277: =W277-X277 -> 0 | AA277: =Y277-Z277 -> 0 | AC277: =Y277-N277 -> 0 | AD277: =AA277-Q277 -> 0 | AE277: =AC277/Y277 -> #DIV/0! | AF277: =AD277/AA277 -> #DIV/0!
B278: =EOMONTH(A278,0) -> 31 | J278: =U278 -> 0 | K278: =L278/J278 -> #DIV/0! | N278: =L278-M278 -> 0 | O278: =P278/J278 -> #DIV/0! | Q278: =N278+P278 -> 0 | V278: =W278/U278 -> #DIV/0! | Y278: =W278-X278 -> 0 | AA278: =Y278-Z278 -> 0 | AC278: =Y278-N278 -> 0 | AD278: =AA278-Q278 -> 0 | AE278: =AC278/Y278 -> #DIV/0! | AF278: =AD278/AA278 -> #DIV/0!
B279: =EOMONTH(A279,0) -> 31 | J279: =U279 -> 0 | K279: =L279/J279 -> #DIV/0! | N279: =L279-M279 -> 0 | O279: =P279/J279 -> #DIV/0! | Q279: =N279+P279 -> 0 | V279: =W279/U279 -> #DIV/0! | Y279: =W279-X279 -> 0 | AA279: =Y279-Z279 -> 0 | AC279: =Y279-N279 -> 0 | AD279: =AA279-Q279 -> 0 | AE279: =AC279/Y279 -> #DIV/0! | AF279: =AD279/AA279 -> #DIV/0!
... B283: =EOMONTH(A283,0) -> 31 | J283: =U283 -> 0 | K283: =L283/J283 -> #DIV/0! | N283: =L283-M283 -> 0 | O283: =P283/J283 -> #DIV/0! | Q283: =N283+P283 -> 0 | V283: =W283/U283 -> #DIV/0! | Y283: =W283-X283 -> 0 | AA283: =Y283-Z283 -> 0 | AC283: =Y283-N283 -> 0 | AD283: =AA283-Q283 -> 0 | AE283: =AC283/Y283 -> #DIV/0! | AF283: =AD283/AA283 -> #DIV/0!
B284: =EOMONTH(A284,0) -> 31 | J284: =U284 -> 0 | K284: =L284/J284 -> #DIV/0! | N284: =L284-M284 -> 0 | O284: =P284/J284 -> #N/A | P284: =VLOOKUP(C284,'[1]Profit and Loss agt new'!$D$17:$E$52,2,) -> #N/A | Q284: =N284+P284 -> #N/A | V284: =W284/U284 -> #DIV/0! | Y284: =W284-X284 -> 0 | AA284: =Y284-Z284 -> 0 | AC284: =Y284-N284 -> 0 | AD284: =AA284-Q284 -> #N/A | AE284: =AC284/Y284 -> #DIV/0! | AF284: =AD284/AA284 -> #N/A
B285: =EOMONTH(A285,0) -> 31 | J285: =U285 -> 0 | K285: =L285/J285 -> #DIV/0! | N285: =L285-M285 -> 0 | O285: =P285/J285 -> #DIV/0! | Q285: =N285+P285 -> 0 | V285: =W285/U285 -> #DIV/0! | Y285: =W285-X285 -> 0 | AA285: =Y285-Z285 -> 0 | AC285: =Y285-N285 -> 0 | AD285: =AA285-Q285 -> 0 | AE285: =AC285/Y285 -> #DIV/0! | AF285: =AD285/AA285 -> #DIV/0!
B286: =EOMONTH(A286,0) -> 31 | J286: =U286 -> 0 | K286: =L286/J286 -> #DIV/0! | N286: =L286-M286 -> 0 | O286: =P286/J286 -> #DIV/0! | Q286: =N286+P286 -> 0 | V286: =W286/U286 -> #DIV/0! | Y286: =W286-X286 -> 0 | AA286: =Y286-Z286 -> 0 | AC286: =Y286-N286 -> 0 | AD286: =AA286-Q286 -> 0 | AE286: =AC286/Y286 -> #DIV/0! | AF286: =AD286/AA286 -> #DIV/0!
B287: =EOMONTH(A287,0) -> 31 | J287: =U287 -> 0 | K287: =L287/J287 -> #DIV/0! | N287: =L287-M287 -> 0 | O287: =P287/J287 -> #DIV/0! | Q287: =N287+P287 -> 0 | V287: =W287/U287 -> #DIV/0! | Y287: =W287-X287 -> 0 | AA287: =Y287-Z287 -> 0 | AC287: =Y287-N287 -> 0 | AD287: =AA287-Q287 -> 0 | AE287: =AC287/Y287 -> #DIV/0! | AF287: =AD287/AA287 -> #DIV/0!
B288: =EOMONTH(A288,0) -> 31 | J288: =U288 -> 0 | K288: =L288/J288 -> #DIV/0! | N288: =L288-M288 -> 0 | O288: =P288/J288 -> #DIV/0! | Q288: =N288+P288 -> 0 | V288: =W288/U288 -> #DIV/0! | Y288: =W288-X288 -> 0 | AA288: =Y288-Z288 -> 0 | AC288: =Y288-N288 -> 0 | AD288: =AA288-Q288 -> 0 | AE288: =AC288/Y288 -> #DIV/0! | AF288: =AD288/AA288 -> #DIV/0!
B289: =EOMONTH(A289,0) -> 31 | J289: =U289 -> 0 | K289: =L289/J289 -> #DIV/0! | N289: =L289-M289 -> 0 | O289: =P289/J289 -> #DIV/0! | Q289: =N289+P289 -> 0 | V289: =W289/U289 -> #DIV/0! | Y289: =W289-X289 -> 0 | AA289: =Y289-Z289 -> 0 | AC289: =Y289-N289 -> 0 | AD289: =AA289-Q289 -> 0 | AE289: =AC289/Y289 -> #DIV/0! | AF289: =AD289/AA289 -> #DIV/0!
B290: =EOMONTH(A290,0) -> 31 | J290: =U290 -> 0 | K290: =L290/J290 -> #DIV/0! | N290: =L290-M290 -> 0 | O290: =P290/J290 -> #DIV/0! | Q290: =N290+P290 -> 0 | V290: =W290/U290 -> #DIV/0! | Y290: =W290-X290 -> 0 | AA290: =Y290-Z290 -> 0 | AC290: =Y290-N290 -> 0 | AD290: =AA290-Q290 -> 0 | AE290: =AC290/Y290 -> #DIV/0! | AF290: =AD290/AA290 -> #DIV/0!
B291: =EOMONTH(A291,0) -> 31 | J291: =U291 -> 0 | K291: =L291/J291 -> #DIV/0! | N291: =L291-M291 -> 0 | O291: =P291/J291 -> #DIV/0! | Q291: =N291+P291 -> 0 | V291: =W291/U291 -> #DIV/0! | Y291: =W291-X291 -> 0 | AA291: =Y291-Z291 -> 0 | AC291: =Y291-N291 -> 0 | AD291: =AA291-Q291 -> 0 | AE291: =AC291/Y291 -> #DIV/0! | AF291: =AD291/AA291 -> #DIV/0!
B292: =EOMONTH(A292,0) -> 31 | J292: =U292 -> 0 | K292: =L292/J292 -> #DIV/0! | N292: =L292-M292 -> 0 | O292: =P292/J292 -> #DIV/0! | Q292: =N292+P292 -> 0 | V292: =W292/U292 -> #DIV/0! | Y292: =W292-X292 -> 0 | AA292: =Y292-Z292 -> 0 | AC292: =Y292-N292 -> 0 | AD292: =AA292-Q292 -> 0 | AE292: =AC292/Y292 -> #DIV/0! | AF292: =AD292/AA292 -> #DIV/0!
B293: =EOMONTH(A293,0) -> 31 | J293: =U293 -> 0 | K293: =L293/J293 -> #DIV/0! | N293: =L293-M293 -> 0 | O293: =P293/J293 -> #DIV/0! | Q293: =N293+P293 -> 0 | V293: =W293/U293 -> #DIV/0! | Y293: =W293-X293 -> 0 | AA293: =Y293-Z293 -> 0 | AC293: =Y293-N293 -> 0 | AD293: =AA293-Q293 -> 0 | AE293: =AC293/Y293 -> #DIV/0! | AF293: =AD293/AA293 -> #DIV/0!
B294: =EOMONTH(A294,0) -> 31 | J294: =U294 -> 0 | K294: =L294/J294 -> #DIV/0! | N294: =L294-M294 -> 0 | O294: =P294/J294 -> #N/A | P294: =VLOOKUP(C294,'[1]Profit and Loss agt new'!$D$17:$E$52,2,) -> #N/A | Q294: =N294+P294 -> #N/A | V294: =W294/U294 -> #DIV/0! | Y294: =W294-X294 -> 0 | AA294: =Y294-Z294 -> 0 | AC294: =Y294-N294 -> 0 | AD294: =AA294-Q294 -> #N/A | AE294: =AC294/Y294 -> #DIV/0! | AF294: =AD294/AA294 -> #N/A
B295: =EOMONTH(A295,0) -> 31 | J295: =U295 -> 0 | K295: =L295/J295 -> #DIV/0! | N295: =L295-M295 -> 0 | O295: =P295/J295 -> #DIV/0! | Q295: =N295+P295 -> 0 | V295: =W295/U295 -> #DIV/0! | Y295: =W295-X295 -> 0 | AA295: =Y295-Z295 -> 0 | AC295: =Y295-N295 -> 0 | AD295: =AA295-Q295 -> 0 | AE295: =AC295/Y295 -> #DIV/0! | AF295: =AD295/AA295 -> #DIV/0!
B296: =EOMONTH(A296,0) -> 31 | J296: =U296 -> 0 | K296: =L296/J296 -> #DIV/0! | N296: =L296-M296 -> 0 | O296: =P296/J296 -> #DIV/0! | Q296: =N296+P296 -> 0 | V296: =W296/U296 -> #DIV/0! | Y296: =W296-X296 -> 0 | AA296: =Y296-Z296 -> 0 | AC296: =Y296-N296 -> 0 | AD296: =AA296-Q296 -> 0 | AE296: =AC296/Y296 -> #DIV/0! | AF296: =AD296/AA296 -> #DIV/0!
B297: =EOMONTH(A297,0) -> 31 | J297: =U297 -> 0 | K297: =L297/J297 -> #DIV/0! | N297: =L297-M297 -> 0 | O297: =P297/J297 -> #DIV/0! | Q297: =N297+P297 -> 0 | V297: =W297/U297 -> #DIV/0! | Y297: =W297-X297 -> 0 | AA297: =Y297-Z297 -> 0 | AC297: =Y297-N297 -> 0 | AD297: =AA297-Q297 -> 0 | AE297: =AC297/Y297 -> #DIV/0! | AF297: =AD297/AA297 -> #DIV/0!
B298: =EOMONTH(A298,0) -> 31 | J298: =U298 -> 0 | K298: =L298/J298 -> #DIV/0! | N298: =L298-M298 -> 0 | O298: =P298/J298 -> #DIV/0! | Q298: =N298+P298 -> 0 | V298: =W298/U298 -> #DIV/0! | Y298: =W298-X298 -> 0 | AA298: =Y298-Z298 -> 0 | AC298: =Y298-N298 -> 0 | AD298: =AA298-Q298 -> 0 | AE298: =AC298/Y298 -> #DIV/0! | AF298: =AD298/AA298 -> #DIV/0!
B299: =EOMONTH(A299,0) -> 31 | J299: =U299 -> 0 | K299: =L299/J299 -> #DIV/0! | N299: =L299-M299 -> 0 | O299: =P299/J299 -> #DIV/0! | Q299: =N299+P299 -> 0 | V299: =W299/U299 -> #DIV/0! | Y299: =W299-X299 -> 0 | AA299: =Y299-Z299 -> 0 | AC299: =Y299-N299 -> 0 | AD299: =AA299-Q299 -> 0 | AE299: =AC299/Y299 -> #DIV/0! | AF299: =AD299/AA299 -> #DIV/0!
B300: =EOMONTH(A300,0) -> 31 | J300: =U300 -> 0 | K300: =L300/J300 -> #DIV/0! | N300: =L300-M300 -> 0 | O300: =P300/J300 -> #DIV/0! | Q300: =N300+P300 -> 0 | V300: =W300/U300 -> #DIV/0! | Y300: =W300-X300 -> 0 | AA300: =Y300-Z300 -> 0 | AC300: =Y300-N300 -> 0 | AD300: =AA300-Q300 -> 0 | AE300: =AC300/Y300 -> #DIV/0! | AF300: =AD300/AA300 -> #DIV/0!
B301: =EOMONTH(A301,0) -> 31 | J301: =U301 -> 0 | K301: =L301/J301 -> #DIV/0! | N301: =L301-M301 -> 0 | O301: =P301/J301 -> #DIV/0! | Q301: =N301+P301 -> 0 | V301: =W301/U301 -> #DIV/0! | Y301: =W301-X301 -> 0 | AA301: =Y301-Z301 -> 0 | AC301: =Y301-N301 -> 0 | AD301: =AA301-Q301 -> 0 | AE301: =AC301/Y301 -> #DIV/0! | AF301: =AD301/AA301 -> #DIV/0!
B302: =EOMONTH(A302,0) -> 31 | J302: =U302 -> 0 | K302: =L302/J302 -> #DIV/0! | N302: =L302-M302 -> 0 | O302: =P302/J302 -> #DIV/0! | Q302: =N302+P302 -> 0 | V302: =W302/U302 -> #DIV/0! | Y302: =W302-X302 -> 0 | AA302: =Y302-Z302 -> 0 | AC302: =Y302-N302 -> 0 | AD302: =AA302-Q302 -> 0 | AE302: =AC302/Y302 -> #DIV/0! | AF302: =AD302/AA302 -> #DIV/0!
B303: =EOMONTH(A303,0) -> 31 | J303: =U303 -> 0 | K303: =L303/J303 -> #DIV/0! | N303: =L303-M303 -> 0 | O303: =P303/J303 -> #DIV/0! | Q303: =N303+P303 -> 0 | V303: =W303/U303 -> #DIV/0! | Y303: =W303-X303 -> 0 | AA303: =Y303-Z303 -> 0 | AC303: =Y303-N303 -> 0 | AD303: =AA303-Q303 -> 0 | AE303: =AC303/Y303 -> #DIV/0! | AF303: =AD303/AA303 -> #DIV/0!
B304: =EOMONTH(A304,0) -> 31 | J304: =U304 -> 0 | K304: =L304/J304 -> #DIV/0! | N304: =L304-M304 -> 0 | O304: =P304/J304 -> #DIV/0! | Q304: =N304+P304 -> 0 | V304: =W304/U304 -> #DIV/0! | Y304: =W304-X304 -> 0 | AA304: =Y304-Z304 -> 0 | AC304: =Y304-N304 -> 0 | AD304: =AA304-Q304 -> 0 | AE304: =AC304/Y304 -> #DIV/0! | AF304: =AD304/AA304 -> #DIV/0!
B305: =EOMONTH(A305,0) -> 31 | J305: =U305 -> 0 | K305: =L305/J305 -> #DIV/0! | N305: =L305-M305 -> 0 | O305: =P305/J305 -> #N/A | P305: =VLOOKUP(C305,'[1]Profit and Loss agt new'!$D$17:$E$52,2,) -> #N/A | Q305: =N305+P305 -> #N/A | V305: =W305/U305 -> #DIV/0! | Y305: =W305-X305 -> 0 | AA305: =Y305-Z305 -> 0 | AC305: =Y305-N305 -> 0 | AD305: =AA305-Q305 -> #N/A | AE305: =AC305/Y305 -> #DIV/0! | AF305: =AD305/AA305 -> #N/A
B306: =EOMONTH(A306,0) -> 31 | J306: =U306 -> 0 | K306: =L306/J306 -> #DIV/0! | N306: =L306-M306 -> 0 | O306: =P306/J306 -> #DIV/0! | Q306: =N306+P306 -> 0 | V306: =W306/U306 -> #DIV/0! | Y306: =W306-X306 -> 0 | AA306: =Y306-Z306 -> 0 | AC306: =Y306-N306 -> 0 | AD306: =AA306-Q306 -> 0 | AE306: =AC306/Y306 -> #DIV/0! | AF306: =AD306/AA306 -> #DIV/0!
B307: =EOMONTH(A307,0) -> 31 | J307: =U307 -> 0 | K307: =L307/J307 -> #DIV/0! | N307: =L307-M307 -> 0 | O307: =P307/J307 -> #DIV/0! | Q307: =N307+P307 -> 0 | V307: =W307/U307 -> #DIV/0! | Y307: =W307-X307 -> 0 | AA307: =Y307-Z307 -> 0 | AC307: =Y307-N307 -> 0 | AD307: =AA307-Q307 -> 0 | AE307: =AC307/Y307 -> #DIV/0! | AF307: =AD307/AA307 -> #DIV/0!
B308: =EOMONTH(A308,0) -> 31 | J308: =U308 -> 0 | K308: =L308/J308 -> #DIV/0! | N308: =L308-M308 -> 0 | O308: =P308/J308 -> #DIV/0! | Q308: =N308+P308 -> 0 | V308: =W308/U308 -> #DIV/0! | Y308: =W308-X308 -> 0 | AA308: =Y308-Z308 -> 0 | AC308: =Y308-N308 -> 0 | AD308: =AA308-Q308 -> 0 | AE308: =AC308/Y308 -> #DIV/0! | AF308: =AD308/AA308 -> #DIV/0!
B309: =EOMONTH(A309,0) -> 31 | J309: =U309 -> 0 | K309: =L309/J309 -> #DIV/0! | N309: =L309-M309 -> 0 | O309: =P309/J309 -> #DIV/0! | Q309: =N309+P309 -> 0 | V309: =W309/U309 -> #DIV/0! | Y309: =W309-X309 -> 0 | AA309: =Y309-Z309 -> 0 | AC309: =Y309-N309 -> 0 | AD309: =AA309-Q309 -> 0 | AE309: =AC309/Y309 -> #DIV/0! | AF309: =AD309/AA309 -> #DIV/0!
B310: =EOMONTH(A310,0) -> 31 | J310: =U310 -> 0 | K310: =L310/J310 -> #DIV/0! | N310: =L310-M310 -> 0 | O310: =P310/J310 -> #DIV/0! | Q310: =N310+P310 -> 0 | V310: =W310/U310 -> #DIV/0! | Y310: =W310-X310 -> 0 | AA310: =Y310-Z310 -> 0 | AC310: =Y310-N310 -> 0 | AD310: =AA310-Q310 -> 0 | AE310: =AC310/Y310 -> #DIV/0! | AF310: =AD310/AA310 -> #DIV/0!
...

Sheet BS
B1: Aspirarch Market Platforms Private Limited | AG1: AGT | AH1: 42897872
B2: Balance Sheet | J2: 1 | Q2: 1 | AG2: AL | AH2: 38110854
B3: As on 31st October 2024 | C3: Expora | D3: Expora | E3: Expora | F3: Expora | G3: Expora | H3: Expora | I3: Expora | J3: AGT | K3: AGT | L3: AGT | M3: AGT | N3: AGT | O3: AGT | P3: AGT | Q3: Lanka | R3: Lanka | S3: Lanka | T3: Lanka | U3: Lanka | V3: Lanka | W3: Lanka | X3: Conso | Y3: Conso | Z3: Conso | AA3: Conso | AB3: Conso | AC3: Conso | AD3: Conso
B4: Currency (Rs) | C4: Apr-25 | D4: 45778 | E4: 45809 | F4: 45839 | G4: 45870 | H4: 45901 | I4: 45931 | J4: Apr-25 | K4: 45778 | L4: 45809 | M4: 45839 | N4: 45870 | O4: 45901 | P4: 45931 | Q4: Apr-25 | R4: 45778 | S4: 45809 | T4: 45839 | U4: 45870 | V4: 45901 | W4: 45931 | X4: Apr-25 | Y4: 45778 | Z4: 45809 | AA4: 45839 | AB4: 45870 | AC4: 45901 | AD4: 45931 | AE4: Elimination | AF4: YTD Console Net | AH4: Remarks
B5: Fixed assets -Tangible | C5: =SUMIFS(#REF!,#REF!,B5) -> #REF! | D5: =SUMIFS(#REF!,#REF!,B5) -> #REF! | E5: =SUMIFS(#REF!,#REF!,B5) -> #REF! | F5: =SUMIFS(#REF!,#REF!,B5) -> #REF! | G5: =SUMIFS(#REF!,#REF!,B5) -> #REF! | H5: =SUMIFS(#REF!,#REF!,B5) -> #REF! | I5: =SUMIFS(#REF!,#REF!,B5) -> #REF! | J5: =SUMIFS('AGT TB Apr -25'!M:M,'AGT TB Apr -25'!S:S,BS!B5)*$J$2 -> 0 | Q5: =SUMIFS(#REF!,#REF!,BS!B5)*$Q$2 -> #REF! | X5: =C5+J5+Q5 -> #REF! | Y5: =D5+K5+R5 -> #REF! | Z5: =E5+L5+S5 -> #REF! | AA5: =F5+M5+T5 -> #REF! | AB5: =G5+N5+U5 -> #REF! | AC5: =H5+O5+V5 -> #REF! | AD5: =I5+P5+W5 -> #REF! | AF5: =X5-AE5 -> #REF! | AH5: Refer BS Annexure- BS4
B6: Fixed assets -Intangible | C6: =SUMIFS(#REF!,#REF!,B6) -> #REF! | D6: =SUMIFS(#REF!,#REF!,B6) -> #REF! | E6: =SUMIFS(#REF!,#REF!,B6) -> #REF! | F6: =SUMIFS(#REF!,#REF!,B6) -> #REF! | G6: =SUMIFS(#REF!,#REF!,B6) -> #REF! | H6: =SUMIFS(#REF!,#REF!,B6) -> #REF! | I6: =SUMIFS(#REF!,#REF!,B6) -> #REF! | J6: =SUMIFS('AGT TB Apr -25'!M:M,'AGT TB Apr -25'!S:S,BS!B6)*$J$2 -> 0 | K6: 0 | L6: 0 | M6: 0 | N6: 0 | O6: 0 | P6: =SUMIF(#REF!,B6,#REF!) -> #REF! | Q6: =SUMIFS(#REF!,#REF!,BS!B6)*$Q$2 -> #REF! | X6: =C6+J6+Q6 -> #REF! | Y6: =D6+K6+R6 -> #REF! | Z6: =E6+L6+S6 -> #REF! | AA6: =F6+M6+T6 -> #REF! | AB6: =G6+N6+U6 -> #REF! | AC6: =H6+O6+V6 -> #REF! | AD6: =I6+P6+W6 -> #REF! | AF6: =X6-AE6 -> #REF!
B7: Investments in Subsidiary | C7: =SUM(C8:C11) -> #REF! | D7: =SUM(D8:D11) -> #REF! | E7: =SUM(E8:E11) -> #REF! | F7: =SUM(F8:F11) -> #REF! | G7: =SUM(G8:G11) -> #REF! | H7: =SUM(H8:H11) -> #REF! | I7: =SUM(I8:I11) -> #REF! | J7: =SUM(J8:J11) -> 0 | ... Q7: =SUM(Q8:Q11) -> #REF! | X7: =SUM(X8:X11) -> #REF! | Y7: =SUM(Y8:Y11) -> #REF! | Z7: =SUM(Z8:Z11) -> #REF! | AA7: =SUM(AA8:AA11) -> #REF! | AB7: =SUM(AB8:AB11) -> #REF! | AC7: =SUM(AC8:AC11) -> #REF! | AD7: =SUM(AD8:AD11) -> #REF! | AF7: =SUM(AF8:AF11) -> #REF! | AH7: Refer BS Annexure- BS4
B8: Investment in Parnia Expora Pvt Ltd | C8: =SUMIFS(#REF!,#REF!,B8) -> #REF! | D8: =SUMIFS(#REF!,#REF!,B8) -> #REF! | E8: =SUMIFS(#REF!,#REF!,B8) -> #REF! | F8: =SUMIFS(#REF!,#REF!,B8) -> #REF! | G8: =SUMIFS(#REF!,#REF!,B8) -> #REF! | H8: =SUMIFS(#REF!,#REF!,B8) -> #REF! | I8: =SUMIFS(#REF!,#REF!,B8) -> #REF! | J8: =SUMIFS('AGT TB Apr -25'!M:M,'AGT TB Apr -25'!S:S,BS!B8)*$J$2 -> 0 | K8: =SUMIF(#REF!,B:B,#REF!) -> #REF! | L8: =SUMIF(#REF!,B:B,#REF!) -> #REF! | M8: =SUMIF(#REF!,BS!B:B,#REF!) -> #REF! | N8: =SUMIF(#REF!,B8,#REF!) -> #REF! | O8: =SUMIF(#REF!,B:B,#REF!) -> #REF! | P8: =SUMIF(#REF!,B8,#REF!) -> #REF! | Q8: =SUMIFS(#REF!,#REF!,BS!B8)*$Q$2 -> #REF! | X8: =C8+J8+Q8 -> #REF! | Y8: =D8+K8+R8 -> #REF! | Z8: =E8+L8+S8 -> #REF! | AA8: =F8+M8+T8 -> #REF! | AB8: =G8+N8+U8 -> #REF! | AC8: =H8+O8+V8 -> #REF! | AD8: =I8+P8+W8 -> #REF! | AF8: =X8-AE8 -> #REF! | AH8: 100% Investment in Parnia Expora Pvt Ltd. Share Certificate Received.
B9: Investment in Arha Platforms Genral Trading LLC | C9: =SUMIFS(#REF!,#REF!,B9) -> #REF! | D9: =SUMIFS(#REF!,#REF!,B9) -> #REF! | E9: =SUMIFS(#REF!,#REF!,B9) -> #REF! | F9: =SUMIFS(#REF!,#REF!,B9) -> #REF! | G9: =SUMIFS(#REF!,#REF!,B9) -> #REF! | H9: =SUMIFS(#REF!,#REF!,B9) -> #REF! | I9: =SUMIFS(#REF!,#REF!,B9) -> #REF! | J9: =SUMIFS('AGT TB Apr -25'!M:M,'AGT TB Apr -25'!S:S,BS!B9)*$J$2 -> 0 | K9: =SUMIF(#REF!,B:B,#REF!) -> #REF! | L9: =SUMIF(#REF!,B:B,#REF!) -> #REF! | M9: =SUMIF(#REF!,BS!B:B,#REF!) -> #REF! | N9: =SUMIF(#REF!,B9,#REF!) -> #REF! | O9: =SUMIF(#REF!,B:B,#REF!) -> #REF! | P9: =SUMIF(#REF!,B9,#REF!) -> #REF! | Q9: =SUMIFS(#REF!,#REF!,BS!B9)*$Q$2 -> #REF! | X9: =C9+J9+Q9 -> #REF! | Y9: =D9+K9+R9 -> #REF! | Z9: =E9+L9+S9 -> #REF! | AA9: =F9+M9+T9 -> #REF! | AB9: =G9+N9+U9 -> #REF! | AC9: =H9+O9+V9 -> #REF! | AD9: =I9+P9+W9 -> #REF! | AE9: =C9 -> #REF! | AF9: =X9-AE9 -> #REF! | AH9: 100% Investment in Arha General Trading LLC
B10: Investment in AMI AGRO | C10: =SUMIFS(#REF!,#REF!,B10) -> #REF! | D10: =SUMIFS(#REF!,#REF!,B10) -> #REF! | E10: =SUMIFS(#REF!,#REF!,B10) -> #REF! | F10: =SUMIFS(#REF!,#REF!,B10) -> #REF! | G10: =SUMIFS(#REF!,#REF!,B10) -> #REF! | H10: =SUMIFS(#REF!,#REF!,B10) -> #REF! | I10: =SUMIFS(#REF!,#REF!,B10) -> #REF! | J10: =SUMIFS('AGT TB Apr -25'!M:M,'AGT TB Apr -25'!S:S,BS!B10)*$J$2 -> 0 | K10: =SUMIF(#REF!,B:B,#REF!) -> #REF! | L10: =SUMIF(#REF!,B:B,#REF!) -> #REF! | M10: =SUMIF(#REF!,BS!B:B,#REF!) -> #REF! | N10: =SUMIF(#REF!,B10,#REF!) -> #REF! | O10: =SUMIF(#REF!,B:B,#REF!) -> #REF! | P10: =SUMIF(#REF!,B10,#REF!) -> #REF! | Q10: =SUMIFS(#REF!,#REF!,BS!B10)*$Q$2 -> #REF! | X10: =C10+J10+Q10 -> #REF! | Y10: =D10+K10+R10 -> #REF! | Z10: =E10+L10+S10 -> #REF! | AA10: =F10+M10+T10 -> #REF! | AB10: =G10+N10+U10 -> #REF! | AC10: =H10+O10+V10 -> #REF! | AD10: =I10+P10+W10 -> #REF! | AE10: =C10 -> #REF! | AF10: =X10-AE10 -> #REF!
B11: Investment in Arha Platforms Jewellery Trading LLC | C11: =SUMIFS(#REF!,#REF!,B11) -> #REF! | D11: =SUMIFS(#REF!,#REF!,B11) -> #REF! | E11: =SUMIFS(#REF!,#REF!,B11) -> #REF! | F11: =SUMIFS(#REF!,#REF!,B11) -> #REF! | G11: =SUMIFS(#REF!,#REF!,B11) -> #REF! | H11: =SUMIFS(#REF!,#REF!,B11) -> #REF! | I11: =SUMIFS(#REF!,#REF!,B11) -> #REF! | J11: =SUMIFS('AGT TB Apr -25'!M:M,'AGT TB Apr -25'!S:S,BS!B11)*$J$2 -> 0 | K11: =SUMIF(#REF!,B:B,#REF!) -> #REF! | L11: =SUMIF(#REF!,B:B,#REF!) -> #REF! | M11: =SUMIF(#REF!,BS!B:B,#REF!) -> #REF! | N11: =SUMIF(#REF!,B11,#REF!) -> #REF! | O11: =SUMIF(#REF!,B:B,#REF!) -> #REF! | P11: =SUMIF(#REF!,B11,#REF!) -> #REF! | Q11: =SUMIFS(#REF!,#REF!,BS!B11)*$Q$2 -> #REF! | X11: =C11+J11+Q11 -> #REF! | Y11: =D11+K11+R11 -> #REF! | Z11: =E11+L11+S11 -> #REF! | AA11: =F11+M11+T11 -> #REF! | AB11: =G11+N11+U11 -> #REF! | AC11: =H11+O11+V11 -> #REF! | AD11: =I11+P11+W11 -> #REF! | AF11: =X11-AE11 -> #REF! | AH11: 100% Investment in Arha Jewellery Trading LLC
B12: Bank Balance | C12: =SUMIFS(#REF!,#REF!,B12) -> #REF! | D12: =SUMIFS(#REF!,#REF!,B12) -> #REF! | E12: =SUMIFS(#REF!,#REF!,B12) -> #REF! | F12: =SUMIFS(#REF!,#REF!,B12) -> #REF! | G12: =SUMIFS(#REF!,#REF!,B12) -> #REF! | H12: =SUMIFS(#REF!,#REF!,B12) -> #REF! | I12: =SUMIFS(#REF!,#REF!,B12) -> #REF! | J12: =SUMIFS('AGT TB Apr -25'!M:M,'AGT TB Apr -25'!S:S,BS!B12)*$J$2 -> 0 | Q12: =SUMIFS(#REF!,#REF!,BS!B12)*$Q$2 -> #REF! | X12: =C12+J12+Q12 -> #REF! | Y12: =D12+K12+R12 -> #REF! | Z12: =E12+L12+S12 -> #REF! | AA12: =F12+M12+T12 -> #REF! | AB12: =G12+N12+U12 -> #REF! | AC12: =H12+O12+V12 -> #REF! | AD12: =I12+P12+W12 -> #REF! | AF12: =X12-AE12 -> #REF!
B13: Cash Balance | C13: =SUMIFS(#REF!,#REF!,B13) -> #REF! | D13: =SUMIFS(#REF!,#REF!,B13) -> #REF! | E13: =SUMIFS(#REF!,#REF!,B13) -> #REF! | F13: =SUMIFS(#REF!,#REF!,B13) -> #REF! | G13: =SUMIFS(#REF!,#REF!,B13) -> #REF! | H13: =SUMIFS(#REF!,#REF!,B13) -> #REF! | I13: =SUMIFS(#REF!,#REF!,B13) -> #REF! | J13: =SUMIFS('AGT TB Apr -25'!M:M,'AGT TB Apr -25'!S:S,BS!B13)*$J$2 -> 0 | Q13: =SUMIFS(#REF!,#REF!,BS!B13)*$Q$2 -> #REF! | X13: =C13+J13+Q13 -> #REF! | Y13: =D13+K13+R13 -> #REF! | Z13: =E13+L13+S13 -> #REF! | AA13: =F13+M13+T13 -> #REF! | AB13: =G13+N13+U13 -> #REF! | AC13: =H13+O13+V13 -> #REF! | AD13: =I13+P13+W13 -> #REF! | AF13: =X13-AE13 -> #REF!
B14: Closing Stock | C14: =SUMIFS(#REF!,#REF!,B14) -> #REF! | D14: =SUMIFS(#REF!,#REF!,B14) -> #REF! | E14: =SUMIFS(#REF!,#REF!,B14) -> #REF! | F14: =SUMIFS(#REF!,#REF!,B14) -> #REF! | G14: =SUMIFS(#REF!,#REF!,B14) -> #REF! | H14: =SUMIFS(#REF!,#REF!,B14) -> #REF! | I14: =SUMIFS(#REF!,#REF!,B14) -> #REF! | J14: =SUMIFS('AGT TB Apr -25'!M:M,'AGT TB Apr -25'!S:S,BS!B14)*$J$2 -> 0 | Q14: =SUMIFS(#REF!,#REF!,BS!B14)*$Q$2 -> #REF! | X14: =C14+J14+Q14 -> #REF! | Y14: =D14+K14+R14 -> #REF! | Z14: =E14+L14+S14 -> #REF! | AA14: =F14+M14+T14 -> #REF! | AB14: =G14+N14+U14 -> #REF! | AC14: =H14+O14+V14 -> #REF! | AD14: =I14+P14+W14 -> #REF! | AF14: =X14-AE14 -> #REF! | AH14: Refer BS Annexure- BS2
B15: Trade Receivables | C15: =SUMIFS(#REF!,#REF!,B15) -> #REF! | D15: =SUMIFS(#REF!,#REF!,B15) -> #REF! | E15: =SUMIFS(#REF!,#REF!,B15) -> #REF! | F15: =SUMIFS(#REF!,#REF!,B15) -> #REF! | G15: =SUMIFS(#REF!,#REF!,B15) -> #REF! | H15: =SUMIFS(#REF!,#REF!,B15) -> #REF! | I15: =SUMIFS(#REF!,#REF!,B15) -> #REF! | J15: =SUMIFS('AGT TB Apr -25'!M:M,'AGT TB Apr -25'!S:S,BS!B15)*$J$2 -> 0 | Q15: =SUMIFS(#REF!,#REF!,BS!B15)*$Q$2 -> #REF! | X15: =C15+J15+Q15 -> #REF! | Y15: =D15+K15+R15 -> #REF! | Z15: =E15+L15+S15 -> #REF! | AA15: =F15+M15+T15 -> #REF! | AB15: =G15+N15+U15 -> #REF! | AC15: =H15+O15+V15 -> #REF! | AD15: =I15+P15+W15 -> #REF! | AE15: =AH2+AH1 -> 81008725 | AF15: =X15-AE15 -> #REF! | AH15: Refer Trade Receivable Annexure- BS1
B16: Other Current Asset | C16: =SUM(C17:C32) -> #REF! | D16: =SUM(D17:D32) -> #REF! | E16: =SUM(E17:E32) -> #REF! | F16: =SUM(F17:F32) -> #REF! | G16: =SUM(G17:G32) -> #REF! | H16: =SUM(H17:H32) -> #REF! | I16: =SUM(I17:I32) -> #REF! | J16: =SUM(J17:J32) -> 0 | Q16: =SUM(Q17:Q32) -> #REF! | X16: =SUM(X17:X32) -> #REF! | Y16: =SUM(Y17:Y32) -> #REF! | Z16: =SUM(Z17:Z32) -> #REF! | AA16: =SUM(AA17:AA32) -> #REF! | AB16: =SUM(AB17:AB32) -> #REF! | AC16: =SUM(AC17:AC32) -> #REF! | AD16: =SUM(AD17:AD32) -> #REF! | AF16: =SUM(AF17:AF32) -> #REF! | AH16: Refer BS Annexure - BS1
B17: Term Deposits | C17: =SUMIFS(#REF!,#REF!,B17) -> #REF! | D17: =SUMIFS(#REF!,#REF!,B17) -> #REF! | E17: =SUMIFS(#REF!,#REF!,B17) -> #REF! | F17: =SUMIFS(#REF!,#REF!,B17) -> #REF! | G17: =SUMIFS(#REF!,#REF!,B17) -> #REF! | H17: =SUMIFS(#REF!,#REF!,B17) -> #REF! | I17: =SUMIFS(#REF!,#REF!,B17) -> #REF! | J17: =SUMIFS('AGT TB Apr -25'!M:M,'AGT TB Apr -25'!S:S,BS!B17)*$J$2 -> 0 | Q17: =SUMIFS(#REF!,#REF!,BS!B17)*$Q$2 -> #REF! | X17: =C17+J17+Q17 -> #REF! | Y17: =D17+K17+R17 -> #REF! | Z17: =E17+L17+S17 -> #REF! | AA17: =F17+M17+T17 -> #REF! | AB17: =G17+N17+U17 -> #REF! | AC17: =H17+O17+V17 -> #REF! | AD17: =I17+P17+W17 -> #REF! | AF17: =X17-AE17 -> #REF!
B18: Interest on FD Receivable | C18: =SUMIFS(#REF!,#REF!,B18) -> #REF! | D18: =SUMIFS(#REF!,#REF!,B18) -> #REF! | E18: =SUMIFS(#REF!,#REF!,B18) -> #REF! | F18: =SUMIFS(#REF!,#REF!,B18) -> #REF! | G18: =SUMIFS(#REF!,#REF!,B18) -> #REF! | H18: =SUMIFS(#REF!,#REF!,B18) -> #REF! | I18: =SUMIFS(#REF!,#REF!,B18) -> #REF! | J18: =SUMIFS('AGT TB Apr -25'!M:M,'AGT TB Apr -25'!S:S,BS!B18)*$J$2 -> 0 | Q18: =SUMIFS(#REF!,#REF!,BS!B18)*$Q$2 -> #REF! | X18: =C18+J18+Q18 -> #REF! | Y18: =D18+K18+R18 -> #REF! | Z18: =E18+L18+S18 -> #REF! | AA18: =F18+M18+T18 -> #REF! | AB18: =G18+N18+U18 -> #REF! | AC18: =H18+O18+V18 -> #REF! | AD18: =I18+P18+W18 -> #REF! | AF18: =X18-AE18 -> #REF!
B19: TCS Receivable | C19: =SUMIFS(#REF!,#REF!,B19) -> #REF! | D19: =SUMIFS(#REF!,#REF!,B19) -> #REF! | E19: =SUMIFS(#REF!,#REF!,B19) -> #REF! | F19: =SUMIFS(#REF!,#REF!,B19) -> #REF! | G19: =SUMIFS(#REF!,#REF!,B19) -> #REF! | H19: =SUMIFS(#REF!,#REF!,B19) -> #REF! | I19: =SUMIFS(#REF!,#REF!,B19) -> #REF! | J19: =SUMIFS('AGT TB Apr -25'!M:M,'AGT TB Apr -25'!S:S,BS!B19)*$J$2 -> 0 | Q19: =SUMIFS(#REF!,#REF!,BS!B19)*$Q$2 -> #REF! | X19: =C19+J19+Q19 -> #REF! | Y19: =D19+K19+R19 -> #REF! | Z19: =E19+L19+S19 -> #REF! | AA19: =F19+M19+T19 -> #REF! | AB19: =G19+N19+U19 -> #REF! | AC19: =H19+O19+V19 -> #REF! | AD19: =I19+P19+W19 -> #REF! | AF19: =X19-AE19 -> #REF!
B20: TDS Receivable | C20: =SUMIFS(#REF!,#REF!,B20) -> #REF! | D20: =SUMIFS(#REF!,#REF!,B20) -> #REF! | E20: =SUMIFS(#REF!,#REF!,B20) -> #REF! | F20: =SUMIFS(#REF!,#REF!,B20) -> #REF! | G20: =SUMIFS(#REF!,#REF!,B20) -> #REF! | H20: =SUMIFS(#REF!,#REF!,B20) -> #REF! | I20: =SUMIFS(#REF!,#REF!,B20) -> #REF! | J20: =SUMIFS('AGT TB Apr -25'!M:M,'AGT TB Apr -25'!S:S,BS!B20)*$J$2 -> 0 | Q20: =SUMIFS(#REF!,#REF!,BS!B20)*$Q$2 -> #REF! | X20: =C20+J20+Q20 -> #REF! | Y20: =D20+K20+R20 -> #REF! | Z20: =E20+L20+S20 -> #REF! | AA20: =F20+M20+T20 -> #REF! | AB20: =G20+N20+U20 -> #REF! | AC20: =H20+O20+V20 -> #REF! | AD20: =I20+P20+W20 -> #REF! | AF20: =X20-AE20 -> #REF!
B21: Security Deposit | C21: =SUMIFS(#REF!,#REF!,B21) -> #REF! | D21: =SUMIFS(#REF!,#REF!,B21) -> #REF! | E21: =SUMIFS(#REF!,#REF!,B21) -> #REF! | F21: =SUMIFS(#REF!,#REF!,B21) -> #REF! | G21: =SUMIFS(#REF!,#REF!,B21) -> #REF! | H21: =SUMIFS(#REF!,#REF!,B21) -> #REF! | I21: =SUMIFS(#REF!,#REF!,B21) -> #REF! | J21: =SUMIFS('AGT TB Apr -25'!M:M,'AGT TB Apr -25'!S:S,BS!B21)*$J$2 -> 0 | Q21: =SUMIFS(#REF!,#REF!,BS!B21)*$Q$2 -> #REF! | X21: =C21+J21+Q21 -> #REF! | Y21: =D21+K21+R21 -> #REF! | Z21: =E21+L21+S21 -> #REF! | AA21: =F21+M21+T21 -> #REF! | AB21: =G21+N21+U21 -> #REF! | AC21: =H21+O21+V21 -> #REF! | AD21: =I21+P21+W21 -> #REF! | AF21: =X21-AE21 -> #REF!
B22: Rodtep Receivable | C22: =SUMIFS(#REF!,#REF!,B22) -> #REF! | D22: =SUMIFS(#REF!,#REF!,B22) -> #REF! | E22: =SUMIFS(#REF!,#REF!,B22) -> #REF! | F22: =SUMIFS(#REF!,#REF!,B22) -> #REF! | G22: =SUMIFS(#REF!,#REF!,B22) -> #REF! | H22: =SUMIFS(#REF!,#REF!,B22) -> #REF! | I22: =SUMIFS(#REF!,#REF!,B22) -> #REF! | J22: =SUMIFS('AGT TB Apr -25'!M:M,'AGT TB Apr -25'!S:S,BS!B22)*$J$2 -> 0 | Q22: =SUMIFS(#REF!,#REF!,BS!B22)*$Q$2 -> #REF! | X22: =C22+J22+Q22 -> #REF! | Y22: =D22+K22+R22 -> #REF! | Z22: =E22+L22+S22 -> #REF! | AA22: =F22+M22+T22 -> #REF! | AB22: =G22+N22+U22 -> #REF! | AC22: =H22+O22+V22 -> #REF! | AD22: =I22+P22+W22 -> #REF! | AF22: =X22-AE22 -> #REF!
B23: GST Input tax Assets | C23: =SUMIFS(#REF!,#REF!,B23) -> #REF! | D23: =SUMIFS(#REF!,#REF!,B23) -> #REF! | E23: =SUMIFS(#REF!,#REF!,B23) -> #REF! | F23: =SUMIFS(#REF!,#REF!,B23) -> #REF! | G23: =SUMIFS(#REF!,#REF!,B23) -> #REF! | H23: =SUMIFS(#REF!,#REF!,B23) -> #REF! | I23: =SUMIFS(#REF!,#REF!,B23) -> #REF! | J23: =SUMIFS('AGT TB Apr -25'!M:M,'AGT TB Apr -25'!S:S,BS!B23)*$J$2 -> 0 | Q23: =SUMIFS(#REF!,#REF!,BS!B23)*$Q$2 -> #REF! | X23: =C23+J23+Q23 -> #REF! | Y23: =D23+K23+R23 -> #REF! | Z23: =E23+L23+S23 -> #REF! | AA23: =F23+M23+T23 -> #REF! | AB23: =G23+N23+U23 -> #REF! | AC23: =H23+O23+V23 -> #REF! | AD23: =I23+P23+W23 -> #REF! | AF23: =X23-AE23 -> #REF!
B24: Prepaid Expenses | C24: =SUMIFS(#REF!,#REF!,B24) -> #REF! | D24: =SUMIFS(#REF!,#REF!,B24) -> #REF! | E24: =SUMIFS(#REF!,#REF!,B24) -> #REF! | F24: =SUMIFS(#REF!,#REF!,B24) -> #REF! | G24: =SUMIFS(#REF!,#REF!,B24) -> #REF! | H24: =SUMIFS(#REF!,#REF!,B24) -> #REF! | I24: =SUMIFS(#REF!,#REF!,B24) -> #REF! | J24: =SUMIFS('AGT TB Apr -25'!M:M,'AGT TB Apr -25'!S:S,BS!B24)*$J$2 -> 0 | Q24: =SUMIFS(#REF!,#REF!,BS!B24)*$Q$2 -> #REF! | X24: =C24+J24+Q24 -> #REF! | Y24: =D24+K24+R24 -> #REF! | Z24: =E24+L24+S24 -> #REF! | AA24: =F24+M24+T24 -> #REF! | AB24: =G24+N24+U24 -> #REF! | AC24: =H24+O24+V24 -> #REF! | AD24: =I24+P24+W24 -> #REF! | AF24: =X24-AE24 -> #REF!
B25: Advance to Vendor | C25: =SUMIFS(#REF!,#REF!,B25) -> #REF! | D25: =SUMIFS(#REF!,#REF!,B25) -> #REF! | E25: =SUMIFS(#REF!,#REF!,B25) -> #REF! | F25: =SUMIFS(#REF!,#REF!,B25) -> #REF! | G25: =SUMIFS(#REF!,#REF!,B25) -> #REF! | H25: =SUMIFS(#REF!,#REF!,B25) -> #REF! | I25: =SUMIFS(#REF!,#REF!,B25) -> #REF! | J25: =SUMIFS('AGT TB Apr -25'!M:M,'AGT TB Apr -25'!S:S,BS!B25)*$J$2 -> 0 | Q25: =SUMIFS(#REF!,#REF!,BS!B25)*$Q$2 -> #REF! | X25: =C25+J25+Q25 -> #REF! | Y25: =D25+K25+R25 -> #REF! | Z25: =E25+L25+S25 -> #REF! | AA25: =F25+M25+T25 -> #REF! | AB25: =G25+N25+U25 -> #REF! | AC25: =H25+O25+V25 -> #REF! | AD25: =I25+P25+W25 -> #REF! | AF25: =X25-AE25 -> #REF!
B26: LOAN TO SUBSIDIARIES | C26: =SUMIFS(#REF!,#REF!,B26) -> #REF! | D26: =SUMIFS(#REF!,#REF!,B26) -> #REF! | E26: =SUMIFS(#REF!,#REF!,B26) -> #REF! | F26: =SUMIFS(#REF!,#REF!,B26) -> #REF! | G26: =SUMIFS(#REF!,#REF!,B26) -> #REF! | H26: =SUMIFS(#REF!,#REF!,B26) -> #REF! | I26: =SUMIFS(#REF!,#REF!,B26) -> #REF! | J26: =SUMIFS('AGT TB Apr -25'!M:M,'AGT TB Apr -25'!S:S,BS!B26)*$J$2 -> 0 | Q26: =SUMIFS(#REF!,#REF!,BS!B26)*$Q$2 -> #REF! | X26: =C26+J26+Q26 -> #REF! | Y26: =D26+K26+R26 -> #REF! | Z26: =E26+L26+S26 -> #REF! | AA26: =F26+M26+T26 -> #REF! | AB26: =G26+N26+U26 -> #REF! | AC26: =H26+O26+V26 -> #REF! | AD26: =I26+P26+W26 -> #REF! | AE26: =AE51 -> #REF! | AF26: =X26-AE26 -> #REF!
B27: Other Current Asset | C27: =SUMIFS(#REF!,#REF!,B27) -> #REF! | D27: =SUMIFS(#REF!,#REF!,B27) -> #REF! | E27: =SUMIFS(#REF!,#REF!,B27) -> #REF! | F27: =SUMIFS(#REF!,#REF!,B27) -> #REF! | G27: =SUMIFS(#REF!,#REF!,B27) -> #REF! | H27: =SUMIFS(#REF!,#REF!,B27) -> #REF! | I27: =SUMIFS(#REF!,#REF!,B27) -> #REF! | J27: =SUMIFS('AGT TB Apr -25'!M:M,'AGT TB Apr -25'!S:S,BS!B27)*$J$2 -> 0 | Q27: =SUMIFS(#REF!,#REF!,BS!B27)*$Q$2 -> #REF! | X27: =C27+J27+Q27 -> #REF! | Y27: =D27+K27+R27 -> #REF! | Z27: =E27+L27+S27 -> #REF! | AA27: =F27+M27+T27 -> #REF! | AB27: =G27+N27+U27 -> #REF! | AC27: =H27+O27+V27 -> #REF! | AD27: =I27+P27+W27 -> #REF! | AF27: =X27-AE27 -> #REF!
B28: Other Miscelenious Assets | C28: =SUMIFS(#REF!,#REF!,B28) -> #REF! | D28: =SUMIFS(#REF!,#REF!,B28) -> #REF! | E28: =SUMIFS(#REF!,#REF!,B28) -> #REF! | F28: =SUMIFS(#REF!,#REF!,B28) -> #REF! | G28: =SUMIFS(#REF!,#REF!,B28) -> #REF! | H28: =SUMIFS(#REF!,#REF!,B28) -> #REF! | I28: =SUMIFS(#REF!,#REF!,B28) -> #REF! | J28: =SUMIFS('AGT TB Apr -25'!M:M,'AGT TB Apr -25'!S:S,BS!B28)*$J$2 -> 0 | Q28: =SUMIFS(#REF!,#REF!,BS!B28)*$Q$2 -> #REF! | X28: =C28+J28+Q28 -> #REF! | Y28: =D28+K28+R28 -> #REF! | Z28: =E28+L28+S28 -> #REF! | AA28: =F28+M28+T28 -> #REF! | AB28: =G28+N28+U28 -> #REF! | AC28: =H28+O28+V28 -> #REF! | AD28: =I28+P28+W28 -> #REF! | AF28: =X28-AE28 -> #REF!
B29: Employee Advance | C29: =SUMIFS(#REF!,#REF!,B29) -> #REF! | D29: =SUMIFS(#REF!,#REF!,B29) -> #REF! | E29: =SUMIFS(#REF!,#REF!,B29) -> #REF! | F29: =SUMIFS(#REF!,#REF!,B29) -> #REF! | G29: =SUMIFS(#REF!,#REF!,B29) -> #REF! | H29: =SUMIFS(#REF!,#REF!,B29) -> #REF! | I29: =SUMIFS(#REF!,#REF!,B29) -> #REF! | J29: =SUMIFS('AGT TB Apr -25'!M:M,'AGT TB Apr -25'!S:S,BS!B29)*$J$2 -> 0 | Q29: =SUMIFS(#REF!,#REF!,BS!B29)*$Q$2 -> #REF! | X29: =C29+J29+Q29 -> #REF! | Y29: =D29+K29+R29 -> #REF! | Z29: =E29+L29+S29 -> #REF! | AA29: =F29+M29+T29 -> #REF! | AB29: =G29+N29+U29 -> #REF! | AC29: =H29+O29+V29 -> #REF! | AD29: =I29+P29+W29 -> #REF! | AF29: =X29-AE29 -> #REF!
B30: Foreign Exchange | C30: =SUMIFS(#REF!,#REF!,B30) -> #REF! | D30: =SUMIFS(#REF!,#REF!,B30) -> #REF! | E30: =SUMIFS(#REF!,#REF!,B30) -> #REF! | F30: =SUMIFS(#REF!,#REF!,B30) -> #REF! | G30: =SUMIFS(#REF!,#REF!,B30) -> #REF! | H30: =SUMIFS(#REF!,#REF!,B30) -> #REF! | I30: =SUMIFS(#REF!,#REF!,B30) -> #REF! | J30: =SUMIFS('AGT TB Apr -25'!M:M,'AGT TB Apr -25'!S:S,BS!B30)*$J$2 -> 0 | Q30: =SUMIFS(#REF!,#REF!,BS!B30)*$Q$2 -> #REF! | X30: =C30+J30+Q30 -> #REF! | Y30: =D30+K30+R30 -> #REF! | Z30: =E30+L30+S30 -> #REF! | AA30: =F30+M30+T30 -> #REF! | AB30: =G30+N30+U30 -> #REF! | AC30: =H30+O30+V30 -> #REF! | AD30: =I30+P30+W30 -> #REF! | AF30: =X30-AE30 -> #REF!
B31: Duty Drawback Receivable | C31: =SUMIFS(#REF!,#REF!,B31) -> #REF! | D31: =SUMIFS(#REF!,#REF!,B31) -> #REF! | E31: =SUMIFS(#REF!,#REF!,B31) -> #REF! | F31: =SUMIFS(#REF!,#REF!,B31) -> #REF! | G31: =SUMIFS(#REF!,#REF!,B31) -> #REF! | H31: =SUMIFS(#REF!,#REF!,B31) -> #REF! | I31: =SUMIFS(#REF!,#REF!,B31) -> #REF! | J31: =SUMIFS('AGT TB Apr -25'!M:M,'AGT TB Apr -25'!S:S,BS!B31)*$J$2 -> 0 | Q31: =SUMIFS(#REF!,#REF!,BS!B31)*$Q$2 -> #REF! | X31: =C31+J31+Q31 -> #REF! | Y31: =D31+K31+R31 -> #REF! | Z31: =E31+L31+S31 -> #REF! | AA31: =F31+M31+T31 -> #REF! | AB31: =G31+N31+U31 -> #REF! | AC31: =H31+O31+V31 -> #REF! | AD31: =I31+P31+W31 -> #REF! | AF31: =X31-AE31 -> #REF!
B32: ECL GST | C32: =SUMIFS(#REF!,#REF!,B32) -> #REF! | D32: =SUMIFS(#REF!,#REF!,B32) -> #REF! | E32: =SUMIFS(#REF!,#REF!,B32) -> #REF! | F32: =SUMIFS(#REF!,#REF!,B32) -> #REF! | G32: =SUMIFS(#REF!,#REF!,B32) -> #REF! | H32: =SUMIFS(#REF!,#REF!,B32) -> #REF! | I32: =SUMIFS(#REF!,#REF!,B32) -> #REF! | J32: =SUMIFS('AGT TB Apr -25'!M:M,'AGT TB Apr -25'!S:S,BS!B32)*$J$2 -> 0 | Q32: =SUMIFS(#REF!,#REF!,BS!B32)*$Q$2 -> #REF! | X32: =C32+J32+Q32 -> #REF! | Y32: =D32+K32+R32 -> #REF! | Z32: =E32+L32+S32 -> #REF! | AA32: =F32+M32+T32 -> #REF! | AB32: =G32+N32+U32 -> #REF! | AC32: =H32+O32+V32 -> #REF! | AD32: =I32+P32+W32 -> #REF! | AF32: =X32-AE32 -> #REF!
X33: =C33+J33+Q33 -> 0 | Y33: =D33+K33+R33 -> 0 | Z33: =E33+L33+S33 -> 0 | AA33: =F33+M33+T33 -> 0 | AB33: =G33+N33+U33 -> 0 | AC33: =H33+O33+V33 -> 0 | AD33: =I33+P33+W33 -> 0 | AF33: =X33-AE33 -> 0
X34: =C34+J34+Q34 -> 0 | Y34: =D34+K34+R34 -> 0 | Z34: =E34+L34+S34 -> 0 | AA34: =F34+M34+T34 -> 0 | AB34: =G34+N34+U34 -> 0 | AC34: =H34+O34+V34 -> 0 | AD34: =I34+P34+W34 -> 0 | AF34: =X34-AE34 -> 0
B35: Total Assets | C35: =C5+C6+C7+C12+C13+C14+C15+C16 -> #REF! | D35: =D5+D6+D7+D12+D13+D14+D15+D16 -> #REF! | E35: =E5+E6+E7+E12+E13+E14+E15+E16 -> #REF! | F35: =F5+F6+F7+F12+F13+F14+F15+F16 -> #REF! | G35: =G5+G6+G7+G12+G13+G14+G15+G16 -> #REF! | H35: =H5+H6+H7+H12+H13+H14+H15+H16 -> #REF! | I35: =I5+I6+I7+I12+I13+I14+I15+I16 -> #REF! | J35: =J5+J6+J7+J12+J13+J14+J15+J16 -> 0 | Q35: =Q5+Q6+Q7+Q12+Q13+Q14+Q15+Q16 -> #REF! | X35: =X5+X6+X7+X12+X13+X14+X15+X16 -> #REF! | Y35: =Y5+Y6+Y7+Y12+Y13+Y14+Y15+Y16 -> #REF! | Z35: =Z5+Z6+Z7+Z12+Z13+Z14+Z15+Z16 -> #REF! | AA35: =AA5+AA6+AA7+AA12+AA13+AA14+AA15+AA16 -> #REF! | AB35: =AB5+AB6+AB7+AB12+AB13+AB14+AB15+AB16 -> #REF! | AC35: =AC5+AC6+AC7+AC12+AC13+AC14+AC15+AC16 -> #REF! | AD35: =AD5+AD6+AD7+AD12+AD13+AD14+AD15+AD16 -> #REF! | AE35: =SUM(AE5:AE33) -> #REF! | AF35: =AF5+AF6+AF7+AF12+AF13+AF14+AF15+AF16 -> #REF!
X36: =C36+J36+Q36 -> 0 | Y36: =D36+K36+R36 -> 0 | Z36: =E36+L36+S36 -> 0 | AA36: =F36+M36+T36 -> 0 | AB36: =G36+N36+U36 -> 0 | AC36: =H36+O36+V36 -> 0 | AD36: =I36+P36+W36 -> 0 | AF36: =X36-AE36 -> 0
B37: Provision Payable | C37: =SUM(C38:C41) -> #REF! | D37: =SUM(D38:D41) -> #REF! | E37: =SUM(E38:E41) -> #REF! | F37: =SUM(F38:F41) -> #REF! | G37: =SUM(G38:G41) -> #REF! | H37: =SUM(H38:H41) -> #REF! | I37: =SUM(I38:I41) -> #REF! | J37: =SUM(J38:J41) -> 0 | Q37: =SUM(Q38:Q41) -> #REF! | X37: =SUM(X38:X41) -> #REF! | Y37: =SUM(Y38:Y41) -> #REF! | Z37: =SUM(Z38:Z41) -> #REF! | AA37: =SUM(AA38:AA41) -> #REF! | AB37: =SUM(AB38:AB41) -> #REF! | AC37: =SUM(AC38:AC41) -> #REF! | AD37: =SUM(AD38:AD41) -> #REF! | AF37: =SUM(AF38:AF41) -> #REF!
B38: Audit Fees Payable | C38: =-SUMIFS(#REF!,#REF!,B38) -> #REF! | D38: =-SUMIFS(#REF!,#REF!,B38) -> #REF! | E38: =-SUMIFS(#REF!,#REF!,B38) -> #REF! | F38: =-SUMIFS(#REF!,#REF!,B38) -> #REF! | G38: =-SUMIFS(#REF!,#REF!,B38) -> #REF! | H38: =-SUMIFS(#REF!,#REF!,B38) -> #REF! | I38: =-SUMIFS(#REF!,#REF!,B38) -> #REF! | J38: =-SUMIFS('AGT TB Apr -25'!M:M,'AGT TB Apr -25'!S:S,BS!B38)*$J$2 -> 0 | Q38: =-SUMIFS(#REF!,#REF!,BS!B38)*$Q$2 -> #REF! | X38: =C38+J38+Q38 -> #REF! | Y38: =D38+K38+R38 -> #REF! | Z38: =E38+L38+S38 -> #REF! | AA38: =F38+M38+T38 -> #REF! | AB38: =G38+N38+U38 -> #REF! | AC38: =H38+O38+V38 -> #REF! | AD38: =I38+P38+W38 -> #REF! | AF38: =X38-AE38 -> #REF!
B39: Provision for doubtful debts | C39: =-SUMIFS(#REF!,#REF!,B39) -> #REF! | D39: =-SUMIFS(#REF!,#REF!,B39) -> #REF! | E39: =-SUMIFS(#REF!,#REF!,B39) -> #REF! | F39: =-SUMIFS(#REF!,#REF!,B39) -> #REF! | G39: =-SUMIFS(#REF!,#REF!,B39) -> #REF! | H39: =-SUMIFS(#REF!,#REF!,B39) -> #REF! | I39: =-SUMIFS(#REF!,#REF!,B39) -> #REF! | J39: =-SUMIFS('AGT TB Apr -25'!M:M,'AGT TB Apr -25'!S:S,BS!B39)*$J$2 -> 0 | Q39: =-SUMIFS(#REF!,#REF!,BS!B39)*$Q$2 -> #REF! | X39: =C39+J39+Q39 -> #REF! | Y39: =D39+K39+R39 -> #REF! | Z39: =E39+L39+S39 -> #REF! | AA39: =F39+M39+T39 -> #REF! | AB39: =G39+N39+U39 -> #REF! | AC39: =H39+O39+V39 -> #REF! | AD39: =I39+P39+W39 -> #REF! | AF39: =X39-AE39 -> #REF!
B40: Gratuity Payable | C40: =-SUMIFS(#REF!,#REF!,B40) -> #REF! | D40: =-SUMIFS(#REF!,#REF!,B40) -> #REF! | E40: =-SUMIFS(#REF!,#REF!,B40) -> #REF! | F40: =-SUMIFS(#REF!,#REF!,B40) -> #REF! | G40: =-SUMIFS(#REF!,#REF!,B40) -> #REF! | H40: =-SUMIFS(#REF!,#REF!,B40) -> #REF! | I40: =-SUMIFS(#REF!,#REF!,B40) -> #REF! | J40: =-SUMIFS('AGT TB Apr -25'!M:M,'AGT TB Apr -25'!S:S,BS!B40)*$J$2 -> 0 | Q40: =-SUMIFS(#REF!,#REF!,BS!B40)*$Q$2 -> #REF! | X40: =C40+J40+Q40 -> #REF! | Y40: =D40+K40+R40 -> #REF! | Z40: =E40+L40+S40 -> #REF! | AA40: =F40+M40+T40 -> #REF! | AB40: =G40+N40+U40 -> #REF! | AC40: =H40+O40+V40 -> #REF! | AD40: =I40+P40+W40 -> #REF! | AF40: =X40-AE40 -> #REF!
B41: Other Provision Payable | C41: =-SUMIFS(#REF!,#REF!,B41) -> #REF! | D41: =-SUMIFS(#REF!,#REF!,B41) -> #REF! | E41: =-SUMIFS(#REF!,#REF!,B41) -> #REF! | F41: =-SUMIFS(#REF!,#REF!,B41) -> #REF! | G41: =-SUMIFS(#REF!,#REF!,B41) -> #REF! | H41: =-SUMIFS(#REF!,#REF!,B41) -> #REF! | I41: =-SUMIFS(#REF!,#REF!,B41) -> #REF! | J41: =-SUMIFS('AGT TB Apr -25'!M:M,'AGT TB Apr -25'!S:S,BS!B41)*$J$2 -> 0 | K41: =SUMIF(#REF!,B:B,#REF!) -> #REF! | L41: =SUMIF(#REF!,B:B,#REF!) -> #REF! | M41: =-SUMIF(#REF!,BS!B:B,#REF!) -> #REF! | N41: =-SUMIF(#REF!,B41,#REF!) -> #REF! | O41: =SUMIF(#REF!,B:B,#REF!) -> #REF! | P41: =SUMIF(#REF!,B41,#REF!) -> #REF! | Q41: =-SUMIFS(#REF!,#REF!,BS!B41)*$Q$2 -> #REF! | X41: =C41+J41+Q41 -> #REF! | Y41: =D41+K41+R41 -> #REF! | Z41: =E41+L41+S41 -> #REF! | AA41: =F41+M41+T41 -> #REF! | AB41: =G41+N41+U41 -> #REF! | AC41: =H41+O41+V41 -> #REF! | AD41: =I41+P41+W41 -> #REF! | AF41: =X41-AE41 -> #REF! | AH41: Refer BS Annexure - BS1
B42: Trade payables | C42: =-SUMIFS(#REF!,#REF!,B42) -> #REF! | D42: =-SUMIFS(#REF!,#REF!,B42) -> #REF! | E42: =-SUMIFS(#REF!,#REF!,B42) -> #REF! | F42: =-SUMIFS(#REF!,#REF!,B42) -> #REF! | G42: =-SUMIFS(#REF!,#REF!,B42) -> #REF! | H42: =-SUMIFS(#REF!,#REF!,B42) -> #REF! | I42: =-SUMIFS(#REF!,#REF!,B42) -> #REF! | J42: =-SUMIFS('AGT TB Apr -25'!M:M,'AGT TB Apr -25'!S:S,BS!B42)*$J$2 -> 0 | Q42: =-SUMIFS(#REF!,#REF!,BS!B42)*$Q$2 -> #REF! | X42: =C42+J42+Q42 -> #REF! | Y42: =D42+K42+R42 -> #REF! | Z42: =E42+L42+S42 -> #REF! | AA42: =F42+M42+T42 -> #REF! | AB42: =G42+N42+U42 -> #REF! | AC42: =H42+O42+V42 -> #REF! | AD42: =I42+P42+W42 -> #REF! | AE42: =AE15 -> 81008725 | AF42: =X42-AE42 -> #REF! | AH42: Refer BS Annexure
B43: Advance from customer | C43: =-SUMIFS(#REF!,#REF!,B43) -> #REF! | D43: =-SUMIFS(#REF!,#REF!,B43) -> #REF! | E43: =-SUMIFS(#REF!,#REF!,B43) -> #REF! | F43: =-SUMIFS(#REF!,#REF!,B43) -> #REF! | G43: =-SUMIFS(#REF!,#REF!,B43) -> #REF! | H43: =-SUMIFS(#REF!,#REF!,B43) -> #REF! | I43: =-SUMIFS(#REF!,#REF!,B43) -> #REF! | J43: =-SUMIFS('AGT TB Apr -25'!M:M,'AGT TB Apr -25'!S:S,BS!B43)*$J$2 -> 0 | K43: 0 | L43: 0 | M43: =-SUMIF(#REF!,BS!B:B,#REF!) -> #REF! | N43: =-SUMIF(#REF!,B43,#REF!) -> #REF! | O43: =SUMIF(#REF!,B:B,#REF!) -> #REF! | P43: =SUMIF(#REF!,B43,#REF!) -> #REF! | Q43: =-SUMIFS(#REF!,#REF!,BS!B43)*$Q$2 -> #REF! | X43: =C43+J43+Q43 -> #REF! | Y43: =D43+K43+R43 -> #REF! | Z43: =E43+L43+S43 -> #REF! | AA43: =F43+M43+T43 -> #REF! | AB43: =G43+N43+U43 -> #REF! | AC43: =H43+O43+V43 -> #REF! | AD43: =I43+P43+W43 -> #REF! | AF43: =X43-AE43 -> #REF!
B44: Interest on unsecured loan payable | C44: =-SUMIFS(#REF!,#REF!,B44) -> #REF! | D44: =-SUMIFS(#REF!,#REF!,B44) -> #REF! | E44: =-SUMIFS(#REF!,#REF!,B44) -> #REF! | F44: =-SUMIFS(#REF!,#REF!,B44) -> #REF! | G44: =-SUMIFS(#REF!,#REF!,B44) -> #REF! | H44: =-SUMIFS(#REF!,#REF!,B44) -> #REF! | I44: =-SUMIFS(#REF!,#REF!,B44) -> #REF! | J44: =-SUMIFS('AGT TB Apr -25'!M:M,'AGT TB Apr -25'!S:S,BS!B44)*$J$2 -> 0 | K44: =SUMIF(#REF!,B:B,#REF!) -> #REF! | L44: =SUMIF(#REF!,B:B,#REF!) -> #REF! | M44: =-SUMIF(#REF!,BS!B:B,#REF!) -> #REF! | N44: =-SUMIF(#REF!,B44,#REF!) -> #REF! | O44: =SUMIF(#REF!,B:B,#REF!) -> #REF! | P44: =SUMIF(#REF!,B44,#REF!) -> #REF! | Q44: =-SUMIFS(#REF!,#REF!,BS!B44)*$Q$2 -> #REF! | X44: =C44+J44+Q44 -> #REF! | Y44: =D44+K44+R44 -> #REF! | Z44: =E44+L44+S44 -> #REF! | AA44: =F44+M44+T44 -> #REF! | AB44: =G44+N44+U44 -> #REF! | AC44: =H44+O44+V44 -> #REF! | AD44: =I44+P44+W44 -> #REF! | AF44: =X44-AE44 -> #REF! | AH44: Refer PL5
B45: Interest on ICD payable | C45: =-SUMIFS(#REF!,#REF!,B45) -> #REF! | D45: =-SUMIFS(#REF!,#REF!,B45) -> #REF! | E45: =-SUMIFS(#REF!,#REF!,B45) -> #REF! | F45: =-SUMIFS(#REF!,#REF!,B45) -> #REF! | G45: =-SUMIFS(#REF!,#REF!,B45) -> #REF! | H45: =-SUMIFS(#REF!,#REF!,B45) -> #REF! | I45: =-SUMIFS(#REF!,#REF!,B45) -> #REF! | J45: =-SUMIFS('AGT TB Apr -25'!M:M,'AGT TB Apr -25'!S:S,BS!B45)*$J$2 -> 0 | Q45: =-SUMIFS(#REF!,#REF!,BS!B45)*$Q$2 -> #REF! | X45: =C45+J45+Q45 -> #REF! | Y45: =D45+K45+R45 -> #REF! | Z45: =E45+L45+S45 -> #REF! | AA45: =F45+M45+T45 -> #REF! | AB45: =G45+N45+U45 -> #REF! | AC45: =H45+O45+V45 -> #REF! | AD45: =I45+P45+W45 -> #REF! | AF45: =X45-AE45 -> #REF!
B46: Salary Payable | C46: =-SUMIFS(#REF!,#REF!,B46) -> #REF! | D46: =-SUMIFS(#REF!,#REF!,B46) -> #REF! | E46: =-SUMIFS(#REF!,#REF!,B46) -> #REF! | F46: =-SUMIFS(#REF!,#REF!,B46) -> #REF! | G46: =-SUMIFS(#REF!,#REF!,B46) -> #REF! | H46: =-SUMIFS(#REF!,#REF!,B46) -> #REF! | I46: =-SUMIFS(#REF!,#REF!,B46) -> #REF! | J46: =-SUMIFS('AGT TB Apr -25'!M:M,'AGT TB Apr -25'!S:S,BS!B46)*$J$2 -> 0 | K46: =SUMIF(#REF!,B:B,#REF!) -> #REF! | L46: =SUMIF(#REF!,B:B,#REF!) -> #REF! | M46: =-SUMIF(#REF!,BS!B:B,#REF!) -> #REF! | N46: =-SUMIF(#REF!,B46,#REF!) -> #REF! | O46: =SUMIF(#REF!,B:B,#REF!) -> #REF! | P46: =SUMIF(#REF!,B46,#REF!) -> #REF! | Q46: =-SUMIFS(#REF!,#REF!,BS!B46)*$Q$2 -> #REF! | X46: =C46+J46+Q46 -> #REF! | Y46: =D46+K46+R46 -> #REF! | Z46: =E46+L46+S46 -> #REF! | AA46: =F46+M46+T46 -> #REF! | AB46: =G46+N46+U46 -> #REF! | AC46: =H46+O46+V46 -> #REF! | AD46: =I46+P46+W46 -> #REF! | AF46: =X46-AE46 -> #REF!
B47: Employee Reimbursements | C47: =-SUMIFS(#REF!,#REF!,B47) -> #REF! | D47: =-SUMIFS(#REF!,#REF!,B47) -> #REF! | E47: =-SUMIFS(#REF!,#REF!,B47) -> #REF! | F47: =-SUMIFS(#REF!,#REF!,B47) -> #REF! | G47: =-SUMIFS(#REF!,#REF!,B47) -> #REF! | H47: =-SUMIFS(#REF!,#REF!,B47) -> #REF! | I47: =-SUMIFS(#REF!,#REF!,B47) -> #REF! | J47: =-SUMIFS('AGT TB Apr -25'!M:M,'AGT TB Apr -25'!S:S,BS!B47)*$J$2 -> 0 | Q47: =-SUMIFS(#REF!,#REF!,BS!B47)*$Q$2 -> #REF! | X47: =C47+J47+Q47 -> #REF! | Y47: =D47+K47+R47 -> #REF! | Z47: =E47+L47+S47 -> #REF! | AA47: =F47+M47+T47 -> #REF! | AB47: =G47+N47+U47 -> #REF! | AC47: =H47+O47+V47 -> #REF! | AD47: =I47+P47+W47 -> #REF! | AF47: =X47-AE47 -> #REF!
B48: Employee Flexi Reimbursements | C48: =-SUMIFS(#REF!,#REF!,B48) -> #REF! | D48: =-SUMIFS(#REF!,#REF!,B48) -> #REF! | E48: =-SUMIFS(#REF!,#REF!,B48) -> #REF! | F48: =-SUMIFS(#REF!,#REF!,B48) -> #REF! | G48: =-SUMIFS(#REF!,#REF!,B48) -> #REF! | H48: =-SUMIFS(#REF!,#REF!,B48) -> #REF! | I48: =-SUMIFS(#REF!,#REF!,B48) -> #REF! | J48: =-SUMIFS('AGT TB Apr -25'!M:M,'AGT TB Apr -25'!S:S,BS!B48)*$J$2 -> 0 | Q48: =-SUMIFS(#REF!,#REF!,BS!B48)*$Q$2 -> #REF! | X48: =C48+J48+Q48 -> #REF! | Y48: =D48+K48+R48 -> #REF! | Z48: =E48+L48+S48 -> #REF! | AA48: =F48+M48+T48 -> #REF! | AB48: =G48+N48+U48 -> #REF! | AC48: =H48+O48+V48 -> #REF! | AD48: =I48+P48+W48 -> #REF! | AF48: =X48-AE48 -> #REF!
B49: GST Payable | C49: =-SUMIFS(#REF!,#REF!,B49) -> #REF! | D49: =-SUMIFS(#REF!,#REF!,B49) -> #REF! | E49: =-SUMIFS(#REF!,#REF!,B49) -> #REF! | F49: =-SUMIFS(#REF!,#REF!,B49) -> #REF! | G49: =-SUMIFS(#REF!,#REF!,B49) -> #REF! | H49: =-SUMIFS(#REF!,#REF!,B49) -> #REF! | I49: =-SUMIFS(#REF!,#REF!,B49) -> #REF! | J49: =-SUMIFS('AGT TB Apr -25'!M:M,'AGT TB Apr -25'!S:S,BS!B49)*$J$2 -> 0 | Q49: =-SUMIFS(#REF!,#REF!,BS!B49)*$Q$2 -> #REF! | X49: =C49+J49+Q49 -> #REF! | Y49: =D49+K49+R49 -> #REF! | Z49: =E49+L49+S49 -> #REF! | AA49: =F49+M49+T49 -> #REF! | AB49: =G49+N49+U49 -> #REF! | AC49: =H49+O49+V49 -> #REF! | AD49: =I49+P49+W49 -> #REF! | AF49: =X49-AE49 -> #REF!
B50: Statutory Dues | C50: =-SUMIFS(#REF!,#REF!,B50) -> #REF! | D50: =-SUMIFS(#REF!,#REF!,B50) -> #REF! | E50: =-SUMIFS(#REF!,#REF!,B50) -> #REF! | F50: =-SUMIFS(#REF!,#REF!,B50) -> #REF! | G50: =-SUMIFS(#REF!,#REF!,B50) -> #REF! | H50: =-SUMIFS(#REF!,#REF!,B50) -> #REF! | I50: =-SUMIFS(#REF!,#REF!,B50) -> #REF! | J50: =-SUMIFS('AGT TB Apr -25'!M:M,'AGT TB Apr -25'!S:S,BS!B50)*$J$2 -> 0 | K50: =SUMIF(#REF!,B:B,#REF!) -> #REF! | L50: =SUMIF(#REF!,B:B,#REF!) -> #REF! | M50: =-SUMIF(#REF!,BS!B:B,#REF!) -> #REF! | N50: =-SUMIF(#REF!,B50,#REF!) -> #REF! | O50: =SUMIF(#REF!,B:B,#REF!) -> #REF! | P50: =SUMIF(#REF!,B50,#REF!) -> #REF! | Q50: =-SUMIFS(#REF!,#REF!,BS!B50)*$Q$2 -> #REF! | X50: =C50+J50+Q50 -> #REF! | Y50: =D50+K50+R50 -> #REF! | Z50: =E50+L50+S50 -> #REF! | AA50: =F50+M50+T50 -> #REF! | AB50: =G50+N50+U50 -> #REF! | AC50: =H50+O50+V50 -> #REF! | AD50: =I50+P50+W50 -> #REF! | AF50: =X50-AE50 -> #REF! | AH50: Refer BS Annexure
B51: Related Party Loan | C51: =-SUMIFS(#REF!,#REF!,B51) -> #REF! | D51: =-SUMIFS(#REF!,#REF!,B51) -> #REF! | E51: =-SUMIFS(#REF!,#REF!,B51) -> #REF! | F51: =-SUMIFS(#REF!,#REF!,B51) -> #REF! | G51: =-SUMIFS(#REF!,#REF!,B51) -> #REF! | H51: =-SUMIFS(#REF!,#REF!,B51) -> #REF! | I51: =-SUMIFS(#REF!,#REF!,B51) -> #REF! | J51: =-SUMIFS('AGT TB Apr -25'!M:M,'AGT TB Apr -25'!S:S,BS!B51)*$J$2 -> 0 | K51: =SUMIF(#REF!,B:B,#REF!) -> #REF! | L51: =SUMIF(#REF!,B:B,#REF!) -> #REF! | M51: =SUMIF(#REF!,BS!B:B,#REF!) -> #REF! | N51: =SUMIF(#REF!,B51,#REF!) -> #REF! | O51: =SUMIF(#REF!,B:B,#REF!) -> #REF! | P51: =SUMIF(#REF!,B51,#REF!) -> #REF! | Q51: =-SUMIFS(#REF!,#REF!,BS!B51)*$Q$2 -> #REF! | X51: =C51+J51+Q51 -> #REF! | Y51: =D51+K51+R51 -> #REF! | Z51: =E51+L51+S51 -> #REF! | AA51: =F51+M51+T51 -> #REF! | AB51: =G51+N51+U51 -> #REF! | AC51: =H51+O51+V51 -> #REF! | AD51: =I51+P51+W51 -> #REF! | AE51: =J51+Q51 -> #REF! | AF51: =X51-AE51 -> #REF! | AH51: Refer BS Annexure
B52: Vehicle Loan | C52: =-SUMIFS(#REF!,#REF!,B52) -> #REF! | D52: =-SUMIFS(#REF!,#REF!,B52) -> #REF! | E52: =-SUMIFS(#REF!,#REF!,B52) -> #REF! | F52: =-SUMIFS(#REF!,#REF!,B52) -> #REF! | G52: =-SUMIFS(#REF!,#REF!,B52) -> #REF! | H52: =-SUMIFS(#REF!,#REF!,B52) -> #REF! | I52: =-SUMIFS(#REF!,#REF!,B52) -> #REF! | J52: =-SUMIFS('AGT TB Apr -25'!M:M,'AGT TB Apr -25'!S:S,BS!B52)*$J$2 -> 0 | K52: =SUMIF(#REF!,B:B,#REF!) -> #REF! | L52: =SUMIF(#REF!,B:B,#REF!) -> #REF! | M52: =SUMIF(#REF!,BS!B:B,#REF!) -> #REF! | N52: =SUMIF(#REF!,B52,#REF!) -> #REF! | O52: =SUMIF(#REF!,B:B,#REF!) -> #REF! | P52: =SUMIF(#REF!,B52,#REF!) -> #REF! | Q52: =-SUMIFS(#REF!,#REF!,BS!B52)*$Q$2 -> #REF! | X52: =C52+J52+Q52 -> #REF! | Y52: =D52+K52+R52 -> #REF! | Z52: =E52+L52+S52 -> #REF! | AA52: =F52+M52+T52 -> #REF! | AB52: =G52+N52+U52 -> #REF! | AC52: =H52+O52+V52 -> #REF! | AD52: =I52+P52+W52 -> #REF! | AE52: =J52+Q52 -> #REF! | AF52: =X52-AE52 -> #REF!
B53: Unsecured Loan | C53: =-SUMIFS(#REF!,#REF!,B53) -> #REF! | D53: =-SUMIFS(#REF!,#REF!,B53) -> #REF! | E53: =-SUMIFS(#REF!,#REF!,B53) -> #REF! | F53: =-SUMIFS(#REF!,#REF!,B53) -> #REF! | G53: =-SUMIFS(#REF!,#REF!,B53) -> #REF! | H53: =-SUMIFS(#REF!,#REF!,B53) -> #REF! | I53: =-SUMIFS(#REF!,#REF!,B53) -> #REF! | J53: =-SUMIFS('AGT TB Apr -25'!M:M,'AGT TB Apr -25'!S:S,BS!B53)*$J$2 -> 0 | K53: =SUMIF(#REF!,B:B,#REF!) -> #REF! | L53: =SUMIF(#REF!,B:B,#REF!) -> #REF! | M53: =SUMIF(#REF!,BS!B:B,#REF!) -> #REF! | N53: =SUMIF(#REF!,B53,#REF!) -> #REF! | O53: =SUMIF(#REF!,B:B,#REF!) -> #REF! | P53: =SUMIF(#REF!,B53,#REF!) -> #REF! | Q53: =-SUMIFS(#REF!,#REF!,BS!B53)*$Q$2 -> #REF! | X53: =C53+J53+Q53 -> #REF! | Y53: =D53+K53+R53 -> #REF! | Z53: =E53+L53+S53 -> #REF! | AA53: =F53+M53+T53 -> #REF! | AB53: =G53+N53+U53 -> #REF! | AC53: =H53+O53+V53 -> #REF! | AD53: =I53+P53+W53 -> #REF! | AF53: =X53-AE53 -> #REF!
B54: Bank anf NBFC Borrowings | C54: =SUM(C55:C61) -> #REF! | D54: =SUM(D55:D61) -> #REF! | E54: =SUM(E55:E61) -> #REF! | F54: =SUM(F55:F61) -> #REF! | G54: =SUM(G55:G61) -> #REF! | H54: =SUM(H55:H61) -> #REF! | I54: =SUM(I55:I61) -> #REF! | J54: =SUM(J55:J61) -> 0 | P54: =SUMIF(#REF!,B54,#REF!) -> #REF! | Q54: =SUM(Q55:Q61) -> #REF! | X54: =SUM(X55:X61) -> #REF! | Y54: =SUM(Y55:Y61) -> #REF! | Z54: =SUM(Z55:Z61) -> #REF! | AA54: =SUM(AA55:AA61) -> #REF! | AB54: =SUM(AB55:AB61) -> #REF! | AC54: =SUM(AC55:AC61) -> #REF! | AD54: =SUM(AD55:AD61) -> #REF! | AF54: =SUM(AF55:AF61) -> #REF!
B55: PCFC Loan | C55: =-SUMIFS(#REF!,#REF!,B55) -> #REF! | D55: =-SUMIFS(#REF!,#REF!,B55) -> #REF! | E55: =-SUMIFS(#REF!,#REF!,B55) -> #REF! | F55: =-SUMIFS(#REF!,#REF!,B55) -> #REF! | G55: =-SUMIFS(#REF!,#REF!,B55) -> #REF! | H55: =-SUMIFS(#REF!,#REF!,B55) -> #REF! | I55: =-SUMIFS(#REF!,#REF!,B55) -> #REF! | J55: =-SUMIFS('AGT TB Apr -25'!M:M,'AGT TB Apr -25'!S:S,BS!B55)*$J$2 -> 0 | Q55: =-SUMIFS(#REF!,#REF!,BS!B55)*$Q$2 -> #REF! | X55: =C55+J55+Q55 -> #REF! | Y55: =D55+K55+R55 -> #REF! | Z55: =E55+L55+S55 -> #REF! | AA55: =F55+M55+T55 -> #REF! | AB55: =G55+N55+U55 -> #REF! | AC55: =H55+O55+V55 -> #REF! | AD55: =I55+P55+W55 -> #REF! | AF55: =X55-AE55 -> #REF!
B56: Warehouse Finance | C56: =-SUMIFS(#REF!,#REF!,B56) -> #REF! | D56: =-SUMIFS(#REF!,#REF!,B56) -> #REF! | E56: =-SUMIFS(#REF!,#REF!,B56) -> #REF! | F56: =-SUMIFS(#REF!,#REF!,B56) -> #REF! | G56: =-SUMIFS(#REF!,#REF!,B56) -> #REF! | H56: =-SUMIFS(#REF!,#REF!,B56) -> #REF! | I56: =-SUMIFS(#REF!,#REF!,B56) -> #REF! | J56: =-SUMIFS('AGT TB Apr -25'!M:M,'AGT TB Apr -25'!S:S,BS!B56)*$J$2 -> 0 | Q56: =-SUMIFS(#REF!,#REF!,BS!B56)*$Q$2 -> #REF! | X56: =C56+J56+Q56 -> #REF! | Y56: =D56+K56+R56 -> #REF! | Z56: =E56+L56+S56 -> #REF! | AA56: =F56+M56+T56 -> #REF! | AB56: =G56+N56+U56 -> #REF! | AC56: =H56+O56+V56 -> #REF! | AD56: =I56+P56+W56 -> #REF! | AF56: =X56-AE56 -> #REF!
B57: ICD | C57: =-SUMIFS(#REF!,#REF!,B57) -> #REF! | D57: =-SUMIFS(#REF!,#REF!,B57) -> #REF! | E57: =-SUMIFS(#REF!,#REF!,B57) -> #REF! | F57: =-SUMIFS(#REF!,#REF!,B57) -> #REF! | G57: =-SUMIFS(#REF!,#REF!,B57) -> #REF! | H57: =-SUMIFS(#REF!,#REF!,B57) -> #REF! | I57: =-SUMIFS(#REF!,#REF!,B57) -> #REF! | J57: =-SUMIFS('AGT TB Apr -25'!M:M,'AGT TB Apr -25'!S:S,BS!B57)*$J$2 -> 0 | Q57: =-SUMIFS(#REF!,#REF!,BS!B57)*$Q$2 -> #REF! | X57: =C57+J57+Q57 -> #REF! | Y57: =D57+K57+R57 -> #REF! | Z57: =E57+L57+S57 -> #REF! | AA57: =F57+M57+T57 -> #REF! | AB57: =G57+N57+U57 -> #REF! | AC57: =H57+O57+V57 -> #REF! | AD57: =I57+P57+W57 -> #REF! | AF57: =X57-AE57 -> #REF!
B58: Bill Discounting | C58: =-SUMIFS(#REF!,#REF!,B58) -> #REF! | D58: =-SUMIFS(#REF!,#REF!,B58) -> #REF! | E58: =-SUMIFS(#REF!,#REF!,B58) -> #REF! | F58: =-SUMIFS(#REF!,#REF!,B58) -> #REF! | G58: =-SUMIFS(#REF!,#REF!,B58) -> #REF! | H58: =-SUMIFS(#REF!,#REF!,B58) -> #REF! | I58: =-SUMIFS(#REF!,#REF!,B58) -> #REF! | J58: =-SUMIFS('AGT TB Apr -25'!M:M,'AGT TB Apr -25'!S:S,BS!B58)*$J$2 -> 0 | Q58: =-SUMIFS(#REF!,#REF!,BS!B58)*$Q$2 -> #REF! | X58: =C58+J58+Q58 -> #REF! | Y58: =D58+K58+R58 -> #REF! | Z58: =E58+L58+S58 -> #REF! | AA58: =F58+M58+T58 -> #REF! | AB58: =G58+N58+U58 -> #REF! | AC58: =H58+O58+V58 -> #REF! | AD58: =I58+P58+W58 -> #REF! | AF58: =X58-AE58 -> #REF!
B59: ECGC Premium Payable | C59: =-SUMIFS(#REF!,#REF!,B59) -> #REF! | D59: =-SUMIFS(#REF!,#REF!,B59) -> #REF! | E59: =-SUMIFS(#REF!,#REF!,B59) -> #REF! | F59: =-SUMIFS(#REF!,#REF!,B59) -> #REF! | G59: =-SUMIFS(#REF!,#REF!,B59) -> #REF! | H59: =-SUMIFS(#REF!,#REF!,B59) -> #REF! | I59: =-SUMIFS(#REF!,#REF!,B59) -> #REF! | J59: =-SUMIFS('AGT TB Apr -25'!M:M,'AGT TB Apr -25'!S:S,BS!B59)*$J$2 -> 0 | Q59: =-SUMIFS(#REF!,#REF!,BS!B59)*$Q$2 -> #REF! | X59: =C59+J59+Q59 -> #REF! | Y59: =D59+K59+R59 -> #REF! | Z59: =E59+L59+S59 -> #REF! | AA59: =F59+M59+T59 -> #REF! | AB59: =G59+N59+U59 -> #REF! | AC59: =H59+O59+V59 -> #REF! | AD59: =I59+P59+W59 -> #REF! | AF59: =X59-AE59 -> #REF!
B60: Credit Card Balance | C60: =-SUMIFS(#REF!,#REF!,B60) -> #REF! | D60: =-SUMIFS(#REF!,#REF!,B60) -> #REF! | E60: =-SUMIFS(#REF!,#REF!,B60) -> #REF! | F60: =-SUMIFS(#REF!,#REF!,B60) -> #REF! | G60: =-SUMIFS(#REF!,#REF!,B60) -> #REF! | H60: =-SUMIFS(#REF!,#REF!,B60) -> #REF! | I60: =-SUMIFS(#REF!,#REF!,B60) -> #REF! | J60: =-SUMIFS('AGT TB Apr -25'!M:M,'AGT TB Apr -25'!S:S,BS!B60)*$J$2 -> 0 | Q60: =-SUMIFS(#REF!,#REF!,BS!B60)*$Q$2 -> #REF! | X60: =C60+J60+Q60 -> #REF! | Y60: =D60+K60+R60 -> #REF! | Z60: =E60+L60+S60 -> #REF! | AA60: =F60+M60+T60 -> #REF! | AB60: =G60+N60+U60 -> #REF! | AC60: =H60+O60+V60 -> #REF! | AD60: =I60+P60+W60 -> #REF! | AF60: =X60-AE60 -> #REF!
B61: Bank OD | C61: =-SUMIFS(#REF!,#REF!,B61) -> #REF! | D61: =-SUMIFS(#REF!,#REF!,B61) -> #REF! | E61: =-SUMIFS(#REF!,#REF!,B61) -> #REF! | F61: =-SUMIFS(#REF!,#REF!,B61) -> #REF! | G61: =-SUMIFS(#REF!,#REF!,B61) -> #REF! | H61: =-SUMIFS(#REF!,#REF!,B61) -> #REF! | I61: =-SUMIFS(#REF!,#REF!,B61) -> #REF! | J61: =-SUMIFS('AGT TB Apr -25'!M:M,'AGT TB Apr -25'!S:S,BS!B61)*$J$2 -> 0 | K61: =SUMIF(#REF!,B:B,#REF!) -> #REF! | L61: =SUMIF(#REF!,B:B,#REF!) -> #REF! | M61: =SUMIF(#REF!,BS!B:B,#REF!) -> #REF! | N61: =-SUMIF(#REF!,B61,#REF!) -> #REF! | O61: =-SUMIF(#REF!,B:B,#REF!) -> #REF! | P61: =SUMIF(#REF!,B61,#REF!) -> #REF! | Q61: =-SUMIFS(#REF!,#REF!,BS!B61)*$Q$2 -> #REF! | X61: =C61+J61+Q61 -> #REF! | Y61: =D61+K61+R61 -> #REF! | Z61: =E61+L61+S61 -> #REF! | AA61: =F61+M61+T61 -> #REF! | AB61: =G61+N61+U61 -> #REF! | AC61: =H61+O61+V61 -> #REF! | AD61: =I61+P61+W61 -> #REF! | AF61: =X61-AE61 -> #REF!
B62: Represented by | Q62: =-SUMIFS(#REF!,#REF!,BS!B62)*$Q$2 -> #REF! | X62: =C62+J62+Q62 -> #REF! | Y62: =D62+K62+R62 -> 0 | Z62: =E62+L62+S62 -> 0 | AA62: =F62+M62+T62 -> 0 | AB62: =G62+N62+U62 -> 0 | AC62: =H62+O62+V62 -> 0 | AD62: =I62+P62+W62 -> 0 | AF62: =X62-AE62 -> #REF!
B63: Share Capital | C63: =SUM(C64:C65) -> #REF! | D63: =SUM(D64:D65) -> #REF! | E63: =SUM(E64:E65) -> #REF! | F63: =SUM(F64:F65) -> #REF! | G63: =SUM(G64:G65) -> #REF! | H63: =SUM(H64:H65) -> #REF! | I63: =SUM(I64:I65) -> #REF! | J63: =SUM(J64:J65) -> 0 | Q63: =SUM(Q64:Q65) -> #REF! | X63: =SUM(X64:X65) -> #REF! | Y63: =SUM(Y64:Y65) -> #REF! | Z63: =SUM(Z64:Z65) -> #REF! | AA63: =SUM(AA64:AA65) -> #REF! | AB63: =SUM(AB64:AB65) -> #REF! | AC63: =SUM(AC64:AC65) -> #REF! | AD63: =SUM(AD64:AD65) -> #REF! | AF63: =SUM(AF64:AF65) -> #REF! | AH63: Refer BS3
B64: Equity Sahare Capital | C64: =-SUMIFS(#REF!,#REF!,B64) -> #REF! | D64: =-SUMIFS(#REF!,#REF!,B64) -> #REF! | E64: =-SUMIFS(#REF!,#REF!,B64) -> #REF! | F64: =-SUMIFS(#REF!,#REF!,B64) -> #REF! | G64: =-SUMIFS(#REF!,#REF!,B64) -> #REF! | H64: =-SUMIFS(#REF!,#REF!,B64) -> #REF! | I64: =-SUMIFS(#REF!,#REF!,B64) -> #REF! | J64: =-SUMIFS('AGT TB Apr -25'!M:M,'AGT TB Apr -25'!S:S,BS!B64)*$J$2 -> 0 | Q64: =-SUMIFS(#REF!,#REF!,BS!B64)*$Q$2 -> #REF! | X64: =C64+J64+Q64 -> #REF! | Y64: =D64+K64+R64 -> #REF! | Z64: =E64+L64+S64 -> #REF! | AA64: =F64+M64+T64 -> #REF! | AB64: =G64+N64+U64 -> #REF! | AC64: =H64+O64+V64 -> #REF! | AD64: =I64+P64+W64 -> #REF! | AE64: =J64 -> 0 | AF64: =X64-AE64 -> #REF!
B65: Preference Share Capital | C65: =-SUMIFS(#REF!,#REF!,B65) -> #REF! | D65: =-SUMIFS(#REF!,#REF!,B65) -> #REF! | E65: =-SUMIFS(#REF!,#REF!,B65) -> #REF! | F65: =-SUMIFS(#REF!,#REF!,B65) -> #REF! | G65: =-SUMIFS(#REF!,#REF!,B65) -> #REF! | H65: =-SUMIFS(#REF!,#REF!,B65) -> #REF! | I65: =-SUMIFS(#REF!,#REF!,B65) -> #REF! | J65: =-SUMIFS('AGT TB Apr -25'!M:M,'AGT TB Apr -25'!S:S,BS!B65)*$J$2 -> 0 | Q65: =-SUMIFS(#REF!,#REF!,BS!B65)*$Q$2 -> #REF! | X65: =C65+J65+Q65 -> #REF! | Y65: =D65+K65+R65 -> #REF! | Z65: =E65+L65+S65 -> #REF! | AA65: =F65+M65+T65 -> #REF! | AB65: =G65+N65+U65 -> #REF! | AC65: =H65+O65+V65 -> #REF! | AD65: =I65+P65+W65 -> #REF! | AF65: =X65-AE65 -> #REF!
X66: =C66+J66+Q66 -> 0 | Y66: =D66+K66+R66 -> 0 | Z66: =E66+L66+S66 -> 0 | AA66: =F66+M66+T66 -> 0 | AB66: =G66+N66+U66 -> 0 | AC66: =H66+O66+V66 -> 0 | AD66: =I66+P66+W66 -> 0 | AF66: =X66-AE66 -> 0
B67: Reserves and surplus | C67: =SUM(C68:C71) -> #REF! | D67: =SUM(D68:D71) -> #REF! | E67: =SUM(E68:E71) -> #REF! | F67: =SUM(F68:F71) -> #REF! | G67: =SUM(G68:G71) -> #REF! | H67: =SUM(H68:H71) -> #REF! | I67: =SUM(I68:I71) -> #REF! | J67: =SUM(J68:J71) -> 0 | ... Q67: =SUM(Q68:Q71) -> #REF! | X67: =SUM(X68:X71) -> #REF! | Y67: =SUM(Y68:Y71) -> #REF! | Z67: =SUM(Z68:Z71) -> #REF! | AA67: =SUM(AA68:AA71) -> #REF! | AB67: =SUM(AB68:AB71) -> #REF! | AC67: =SUM(AC68:AC71) -> #REF! | AD67: =SUM(AD68:AD71) -> #REF! | AF67: =SUM(AF68:AF71) -> #REF!
B68: Retained earning | C68: =-SUMIFS(#REF!,#REF!,B68) -> #REF! | D68: =-SUMIFS(#REF!,#REF!,B68) -> #REF! | E68: =-SUMIFS(#REF!,#REF!,B68) -> #REF! | F68: =-SUMIFS(#REF!,#REF!,B68) -> #REF! | G68: =-SUMIFS(#REF!,#REF!,B68) -> #REF! | H68: =-SUMIFS(#REF!,#REF!,B68) -> #REF! | I68: =-SUMIFS(#REF!,#REF!,B68) -> #REF! | J68: =-SUMIFS('AGT TB Apr -25'!M:M,'AGT TB Apr -25'!S:S,BS!B68)*$J$2 -> 0 | K68: =PL!#REF! -> #REF! | L68: =PL!#REF!+K68 -> #REF! | M68: =PL!#REF!+L68 -> #REF! | N68: =PL!#REF!+M68 -> #REF! | O68: =PL!#REF!+N68 -> #REF! | P68: =PL!#REF!+O68 -> #REF! | Q68: =-SUMIFS(#REF!,#REF!,BS!B68)*$Q$2 -> #REF! | X68: =C68+J68+Q68 -> #REF! | Y68: =D68+K68+R68 -> #REF! | Z68: =E68+L68+S68 -> #REF! | AA68: =F68+M68+T68 -> #REF! | AB68: =G68+N68+U68 -> #REF! | AC68: =H68+O68+V68 -> #REF! | AD68: =I68+P68+W68 -> #REF! | AF68: =X68-AE68 -> #REF! | AN68: =#REF!/#REF! -> #REF!
B69: Current Year Earnings | C69: =PL!#REF! -> #REF! | D69: =PL!#REF!+C69 -> #REF! | E69: =PL!#REF!+D69 -> #REF! | F69: =PL!#REF!+E69 -> #REF! | G69: =PL!#REF!+F69 -> #REF! | H69: =PL!#REF!+G69 -> #REF! | I69: =PL!#REF!+H69 -> #REF! | J69: =PL!C171 -> 0 | Q69: =PL!#REF! -> #REF! | X69: =C69+J69+Q69 -> #REF! | Y69: =D69+K69+R69 -> #REF! | Z69: =E69+L69+S69 -> #REF! | AA69: =F69+M69+T69 -> #REF! | AB69: =G69+N69+U69 -> #REF! | AC69: =H69+O69+V69 -> #REF! | AD69: =I69+P69+W69 -> #REF! | AF69: =X69-AE69 -> #REF!
B70: ESOP Reserve | C70: =-SUMIFS(#REF!,#REF!,B70) -> #REF! | D70: =-SUMIFS(#REF!,#REF!,B70) -> #REF! | E70: =-SUMIFS(#REF!,#REF!,B70) -> #REF! | F70: =-SUMIFS(#REF!,#REF!,B70) -> #REF! | G70: =-SUMIFS(#REF!,#REF!,B70) -> #REF! | H70: =-SUMIFS(#REF!,#REF!,B70) -> #REF! | I70: =-SUMIFS(#REF!,#REF!,B70) -> #REF! | J70: =-SUMIFS('AGT TB Apr -25'!M:M,'AGT TB Apr -25'!S:S,BS!B70)*$J$2 -> 0 | Q70: =-SUMIFS(#REF!,#REF!,BS!B70)*$Q$2 -> #REF! | X70: =C70+J70+Q70 -> #REF! | Y70: =D70+K70+R70 -> #REF! | Z70: =E70+L70+S70 -> #REF! | AA70: =F70+M70+T70 -> #REF! | AB70: =G70+N70+U70 -> #REF! | AC70: =H70+O70+V70 -> #REF! | AD70: =I70+P70+W70 -> #REF! | AF70: =X70-AE70 -> #REF!
B71: Security Premium | C71: =-SUMIFS(#REF!,#REF!,B71) -> #REF! | D71: =-SUMIFS(#REF!,#REF!,B71) -> #REF! | E71: =-SUMIFS(#REF!,#REF!,B71) -> #REF! | F71: =-SUMIFS(#REF!,#REF!,B71) -> #REF! | G71: =-SUMIFS(#REF!,#REF!,B71) -> #REF! | H71: =-SUMIFS(#REF!,#REF!,B71) -> #REF! | I71: =-SUMIFS(#REF!,#REF!,B71) -> #REF! | J71: =-SUMIFS('AGT TB Apr -25'!M:M,'AGT TB Apr -25'!S:S,BS!B71)*$J$2 -> 0 | K71: 0 | L71: 0 | M71: 0 | N71: 0 | O71: 0 | P71: 0 | Q71: =-SUMIFS(#REF!,#REF!,BS!B71)*$Q$2 -> #REF! | X71: =C71+J71+Q71 -> #REF! | Y71: =D71+K71+R71 -> #REF! | Z71: =E71+L71+S71 -> #REF! | AA71: =F71+M71+T71 -> #REF! | AB71: =G71+N71+U71 -> #REF! | AC71: =H71+O71+V71 -> #REF! | AD71: =I71+P71+W71 -> #REF! | AF71: =X71-AE71 -> #REF!
B72: Net worth | C72: =C67+C63 -> #REF! | D72: =D67+D63 -> #REF! | E72: =E67+E63 -> #REF! | F72: =F67+F63 -> #REF! | G72: =G67+G63 -> #REF! | H72: =H67+H63 -> #REF! | I72: =I67+I63 -> #REF! | J72: =J67+J63 -> 0 | K72: =SUM(K63:K67) -> #REF! | L72: =SUM(L63:L67) -> #REF! | M72: =SUM(M63:M67) -> #REF! | N72: =SUM(N63:N67) -> #REF! | O72: =SUM(O63:O67) -> #REF! | P72: =SUM(P63:P67) -> #REF! | Q72: =Q67+Q63 -> #REF! | X72: =X67+X63 -> #REF! | Y72: =Y67+Y63 -> #REF! | Z72: =Z67+Z63 -> #REF! | AA72: =AA67+AA63 -> #REF! | AB72: =AB67+AB63 -> #REF! | AC72: =AC67+AC63 -> #REF! | AD72: =AD67+AD63 -> #REF! | AE72: =SUM(AE37:AE71) -> #REF! | AF72: =X72-AE72 -> #REF!
B73: Total Capital & Liabilities | C73: =C37+SUM(C42:C54)+C72 -> #REF! | D73: =D37+SUM(D42:D54)+D72 -> #REF! | E73: =E37+SUM(E42:E54)+E72 -> #REF! | F73: =F37+SUM(F42:F54)+F72 -> #REF! | G73: =G37+SUM(G42:G54)+G72 -> #REF! | H73: =H37+SUM(H42:H54)+H72 -> #REF! | I73: =I37+SUM(I42:I54)+I72 -> #REF! | J73: =J37+SUM(J42:J54)+J72 -> 0 | Q73: =Q37+SUM(Q42:Q54)+Q72 -> #REF! | X73: =X37+SUM(X42:X54)+X72 -> #REF! | Y73: =Y37+SUM(Y42:Y54)+Y72 -> #REF! | Z73: =Z37+SUM(Z42:Z54)+Z72 -> #REF! | AA73: =AA37+SUM(AA42:AA54)+AA72 -> #REF! | AB73: =AB37+SUM(AB42:AB54)+AB72 -> #REF! | AC73: =AC37+SUM(AC42:AC54)+AC72 -> #REF! | AD73: =AD37+SUM(AD42:AD54)+AD72 -> #REF! | AE73: =AE35-AE72 -> #REF! | AF73: =AF37+SUM(AF42:AF54)+AF72 -> #REF!
B74: Diff | C74: =C35-C73 -> #REF! | D74: =D35-D73 -> #REF! | E74: =E35-E73 -> #REF! | F74: =F35-F73 -> #REF! | G74: =G35-G73 -> #REF! | H74: =H35-H73 -> #REF! | I74: =I35-I73 -> #REF! | J74: =J35-J73 -> 0 | Q74: =Q35-Q73 -> #REF! | X74: =X35-X73 -> #REF! | Y74: =Y35-Y73 -> #REF! | Z74: =Z35-Z73 -> #REF! | AA74: =AA35-AA73 -> #REF! | AB74: =AB35-AB73 -> #REF! | AC74: =AC35-AC73 -> #REF! | AD74: =AD35-AD73 -> #REF! | AF74: =AF35-AF73 -> #REF!
B78: Funds infused till date | X78: =#REF!+#REF!+#REF!+#REF!+#REF! -> #REF!
B79: Loss YTD | X79: =PL!#REF!+PL!#REF!+PL!#REF!+PL!#REF!+PL!#REF!+PL!#REF!+PL!#REF!+PL!#REF!+PL!#REF!+PL!#REF!+PL!#REF!-13800-24040+5707500+X69+X70 -> #REF!
B80: Net Negative | X80: =SUM(X78:X79)-X72 -> #REF!
B81: Actual Loss | X81: =X79-X6 -> #REF!
B82: Provisions not considered
B83: ALKAHEST ENTERPRISE SDN.BHD | X83: =SUMIFS(#REF!,#REF!,BS!B83) -> #REF!
B84: Aadi International SDN BHD | X84: =SUMIFS(#REF!,#REF!,BS!B84) -> #REF!
B85: Golden Rise Trading LLC | X85: =SUMIFS(#REF!,#REF!,BS!B85) -> #REF!
B86: JK International | X86: 8676238
B87: Golden Rice Trading L.L.C. ( USD ) | X87: =#REF! -> #REF!
B88: Indo Baltic Pte. Ltd | X88: =SUMIFS(#REF!,#REF!,BS!B88) -> #REF!
B89: Peppermint Fashion LLC | X89: =SUMIFS(#REF!,#REF!,BS!B89) -> #REF!
B90: Provision taken in Mar-24 Financials | X90: =-#REF! -> #REF!
B92: Final Loss | X92: =X81-SUM(X83:X91) -> #REF!
H93: =H68/22.83 -> #REF! | I93: =I68/22.83 -> #REF!
I94: =(I93-$H$93) -> #REF!
I95: 24074.88
H522: =SUM(H463:H521) -> 0

Sheet Category Master
A1: Ledger Name | B1: Entity Name | C1: Concate | D1: Group/Legder | E1: PL/BS | F1: Category | G1: Sub Category
A2: Assets | B2: Expora | C2: =_xlfn.CONCAT(Table4[[#This Row],[Ledger Name]],Table4[[#This Row],[Entity Name]]) -> AssetsExpora | D2: Group | E2: 0 | F2: 0 | G2: 0
A3: Account | B3: Expora | C3: =_xlfn.CONCAT(Table4[[#This Row],[Ledger Name]],Table4[[#This Row],[Entity Name]]) -> AccountExpora | D3: Group | E3: 0 | F3: 0 | G3: 0
A4: Accounts Receivable | B4: Expora | C4: =_xlfn.CONCAT(Table4[[#This Row],[Ledger Name]],Table4[[#This Row],[Entity Name]]) -> Accounts ReceivableExpora | D4: Ledger | E4: BS | F4: Trade Receivables | G4: Trade Receivables
A5: Advance TDS (FY21-22) | B5: Expora | C5: =_xlfn.CONCAT(Table4[[#This Row],[Ledger Name]],Table4[[#This Row],[Entity Name]]) -> Advance TDS (FY21-22)Expora | D5: Ledger | E5: BS | F5: Other Current Asset | G5: TDS Receivable
A6: Advance to Vendor | B6: Expora | C6: =_xlfn.CONCAT(Table4[[#This Row],[Ledger Name]],Table4[[#This Row],[Entity Name]]) -> Advance to VendorExpora | D6: Ledger | E6: BS | F6: Other Current Asset | G6: Advance to Vendor
A7: ASPIRARCH MARKET PLATFORMS PRIVATE LIMITED - AXIS BANK | B7: Expora | C7: =_xlfn.CONCAT(Table4[[#This Row],[Ledger Name]],Table4[[#This Row],[Entity Name]]) -> ASPIRARCH MARKET PLATFORMS PRIVATE LIMITED - AXIS BANKExpora | D7: Ledger | E7: BS | F7: Cash and bank balances | G7: Bank Balance
A8: ASPIRARCH MARKET PLATFORMS PVT LTD - CANARA BANK | B8: Expora | C8: =_xlfn.CONCAT(Table4[[#This Row],[Ledger Name]],Table4[[#This Row],[Entity Name]]) -> ASPIRARCH MARKET PLATFORMS PVT LTD - CANARA BANKExpora | D8: Ledger | E8: BS | F8: Cash and bank balances | G8: Bank Balance
A9: ASPIRARCH MARKET PLATFORMS PVT LTD- OD ACCOUNT CANARA | B9: Expora | C9: =_xlfn.CONCAT(Table4[[#This Row],[Ledger Name]],Table4[[#This Row],[Entity Name]]) -> ASPIRARCH MARKET PLATFORMS PVT LTD- OD ACCOUNT CANARAExpora | D9: Ledger | E9: BS | F9: Short-term borrowings | G9: Bank OD
A10: AXIS BANK CC OD | B10: Expora | C10: =_xlfn.CONCAT(Table4[[#This Row],[Ledger Name]],Table4[[#This Row],[Entity Name]]) -> AXIS BANK CC ODExpora | D10: Ledger | E10: BS | F10: Short-term borrowings | G10: Bank OD
A11: Citi Bank | B11: Expora | C11: =_xlfn.CONCAT(Table4[[#This Row],[Ledger Name]],Table4[[#This Row],[Entity Name]]) -> Citi BankExpora | D11: Ledger | E11: BS | F11: Cash and bank balances | G11: Bank Balance
A12: Clearing GL | B12: Expora | C12: =_xlfn.CONCAT(Table4[[#This Row],[Ledger Name]],Table4[[#This Row],[Entity Name]]) -> Clearing GLExpora | D12: Ledger | E12: BS | F12: Other Current Asset | G12: Bank Balance
A13: Computers and Laptops | B13: Expora | C13: =_xlfn.CONCAT(Table4[[#This Row],[Ledger Name]],Table4[[#This Row],[Entity Name]]) -> Computers and LaptopsExpora | D13: Ledger | E13: BS | F13: Fixed assets -Tangible | G13: Fixed assets -Tangible
A14: Apple Mb Air 13.6 M3 8c 8GB 256gb | B14: Expora | C14: =_xlfn.CONCAT(Table4[[#This Row],[Ledger Name]],Table4[[#This Row],[Entity Name]]) -> Apple Mb Air 13.6 M3 8c 8GB 256gbExpora | D14: Ledger | E14: BS | F14: Fixed assets -Tangible | G14: Fixed assets -Tangible
A15: Apple Mb Pro 14 M3 11c 512GB | B15: Expora | C15: =_xlfn.CONCAT(Table4[[#This Row],[Ledger Name]],Table4[[#This Row],[Entity Name]]) -> Apple Mb Pro 14 M3 11c 512GBExpora | D15: Ledger | E15: BS | F15: Fixed assets -Tangible | G15: Fixed assets -Tangible
... A22: Lenovo ThinkPad E14 21E3S06C00 | B22: Expora | C22: =_xlfn.CONCAT(Table4[[#This Row],[Ledger Name]],Table4[[#This Row],[Entity Name]]) -> Lenovo ThinkPad E14 21E3S06C00Expora | D22: Ledger | E22: BS | F22: Fixed assets -Tangible | G22: Fixed assets -Tangible
A23: Total for Computers and Laptops | B23: Expora | C23: =_xlfn.CONCAT(Table4[[#This Row],[Ledger Name]],Table4[[#This Row],[Entity Name]]) -> Total for Computers and LaptopsExpora | D23: Group | E23: 0 | F23: 0 | G23: 0
A24: Duty Drawback Receivable | B24: Expora | C24: =_xlfn.CONCAT(Table4[[#This Row],[Ledger Name]],Table4[[#This Row],[Entity Name]]) -> Duty Drawback ReceivableExpora | D24: Ledger | E24: BS | F24: Other Current Asset | G24: Other Miscelenious Assets
A25: ECGC Premium Advance | B25: Expora | C25: =_xlfn.CONCAT(Table4[[#This Row],[Ledger Name]],Table4[[#This Row],[Entity Name]]) -> ECGC Premium AdvanceExpora | D25: Ledger | E25: BS | F25: Other Current Asset | G25: Other Miscelenious Assets
A26: Employee Advance | B26: Expora | C26: =_xlfn.CONCAT(Table4[[#This Row],[Ledger Name]],Table4[[#This Row],[Entity Name]]) -> Employee AdvanceExpora | D26: Group | E26: 0 | F26: 0 | G26: 0
A27: Advance Salary | B27: Expora | C27: =_xlfn.CONCAT(Table4[[#This Row],[Ledger Name]],Table4[[#This Row],[Entity Name]]) -> Advance SalaryExpora | D27: Ledger | E27: BS | F27: Other Current Asset | G27: Employee Advance
A28: Advance Salary to Prakash Chaudhary | B28: Expora | C28: =_xlfn.CONCAT(Table4[[#This Row],[Ledger Name]],Table4[[#This Row],[Entity Name]]) -> Advance Salary to Prakash ChaudharyExpora | D28: Ledger | E28: BS | F28: Other Current Asset | G28: Employee Advance
A29: Advance Salary to Pravin Arora | B29: Expora | C29: =_xlfn.CONCAT(Table4[[#This Row],[Ledger Name]],Table4[[#This Row],[Entity Name]]) -> Advance Salary to Pravin AroraExpora | D29: Ledger | E29: BS | F29: Other Current Asset | G29: Employee Advance
A30: Total for Advance Salary | B30: Expora | C30: =_xlfn.CONCAT(Table4[[#This Row],[Ledger Name]],Table4[[#This Row],[Entity Name]]) -> Total for Advance SalaryExpora | D30: Group | E30: 0 | F30: 0 | G30: 0
A31: Total for Employee Advance | B31: Expora | C31: =_xlfn.CONCAT(Table4[[#This Row],[Ledger Name]],Table4[[#This Row],[Entity Name]]) -> Total for Employee AdvanceExpora | D31: Group | E31: 0 | F31: 0 | G31: 0
A32: Foreign Exchange | B32: Expora | C32: =_xlfn.CONCAT(Table4[[#This Row],[Ledger Name]],Table4[[#This Row],[Entity Name]]) -> Foreign ExchangeExpora | D32: Group | E32: 0 | F32: 0 | G32: 0
A33: Foreign Exchange - Krushang Boria | B33: Expora | C33: =_xlfn.CONCAT(Table4[[#This Row],[Ledger Name]],Table4[[#This Row],[Entity Name]]) -> Foreign Exchange - Krushang BoriaExpora | D33: Ledger | E33: BS | F33: Other Current Asset | G33: Employee Reimbursements
A34: Foreign Exchange - Manish Khiyani | B34: Expora | C34: =_xlfn.CONCAT(Table4[[#This Row],[Ledger Name]],Table4[[#This Row],[Entity Name]]) -> Foreign Exchange - Manish KhiyaniExpora | D34: Ledger | E34: BS | F34: Other Current Asset | G34: Manish Khiyani
A35: Foreign Exchange - Prakash Chaudhary | B35: Expora | C35: =_xlfn.CONCAT(Table4[[#This Row],[Ledger Name]],Table4[[#This Row],[Entity Name]]) -> Foreign Exchange - Prakash ChaudharyExpora | D35: Ledger | E35: BS | F35: Other Current Asset | G35: Prakash Choudhary
A36: Foreign Exchange - Priyanka Shah | B36: Expora | C36: =_xlfn.CONCAT(Table4[[#This Row],[Ledger Name]],Table4[[#This Row],[Entity Name]]) -> Foreign Exchange - Priyanka ShahExpora | D36: Ledger | E36: BS | F36: Other Current Asset | G36: Bank Balance
A37: Foreign Exchange - Saranya Ravikumar | B37: Expora | C37: =_xlfn.CONCAT(Table4[[#This Row],[Ledger Name]],Table4[[#This Row],[Entity Name]]) -> Foreign Exchange - Saranya RavikumarExpora | D37: Ledger | E37: BS | F37: Other Current Asset | G37: Bank Balance
A38: Foreign Exchange - Ved Shah | B38: Expora | C38: =_xlfn.CONCAT(Table4[[#This Row],[Ledger Name]],Table4[[#This Row],[Entity Name]]) -> Foreign Exchange - Ved ShahExpora | D38: Ledger | E38: BS | F38: Other Current Asset | G38: Bank Balance
A39: Foreign Exchange - Viral Trivedi | B39: Expora | C39: =_xlfn.CONCAT(Table4[[#This Row],[Ledger Name]],Table4[[#This Row],[Entity Name]]) -> Foreign Exchange - Viral TrivediExpora | D39: Ledger | E39: BS | F39: Other Current Asset | G39: Bank Balance
A40: Foreign Exchange- Abhinav Boria | B40: Expora | C40: =_xlfn.CONCAT(Table4[[#This Row],[Ledger Name]],Table4[[#This Row],[Entity Name]]) -> Foreign Exchange- Abhinav BoriaExpora | D40: Ledger | E40: BS | F40: Other Current Asset | G40: Bank Balance
A41: Foreign Exchange- Aditya Kaushal | B41: Expora | C41: =_xlfn.CONCAT(Table4[[#This Row],[Ledger Name]],Table4[[#This Row],[Entity Name]]) -> Foreign Exchange- Aditya KaushalExpora | D41: Ledger | E41: BS | F41: Other Current Asset | G41: Bank Balance
A42: Foreign Exchange- Ajit Shah | B42: Expora | C42: =_xlfn.CONCAT(Table4[[#This Row],[Ledger Name]],Table4[[#This Row],[Entity Name]]) -> Foreign Exchange- Ajit ShahExpora | D42: Ledger | E42: BS | F42: Other Current Asset | G42: Bank Balance
A43: Foreign Exchange- Ashay Shah | B43: Expora | C43: =_xlfn.CONCAT(Table4[[#This Row],[Ledger Name]],Table4[[#This Row],[Entity Name]]) -> Foreign Exchange- Ashay ShahExpora | D43: Ledger | E43: BS | F43: Other Current Asset | G43: Bank Balance
A44: Foreign Exchange- Prakash Choudhary | B44: Expora | C44: =_xlfn.CONCAT(Table4[[#This Row],[Ledger Name]],Table4[[#This Row],[Entity Name]]) -> Foreign Exchange- Prakash ChoudharyExpora | D44: Ledger | E44: BS | F44: Other Current Asset | G44: Bank Balance
... A46: Foreign Exchange-Sanjith | B46: Expora | C46: =_xlfn.CONCAT(Table4[[#This Row],[Ledger Name]],Table4[[#This Row],[Entity Name]]) -> Foreign Exchange-SanjithExpora | D46: Ledger | E46: BS | F46: Other Current Asset | G46: Bank Balance
A47: Total for Foreign Exchange | B47: Expora | C47: =_xlfn.CONCAT(Table4[[#This Row],[Ledger Name]],Table4[[#This Row],[Entity Name]]) -> Total for Foreign ExchangeExpora | D47: Group | E47: 0 | F47: 0 | G47: 0
A48: ICE Gate E- Wallet ( Custom Duty ) | B48: Expora | C48: =_xlfn.CONCAT(Table4[[#This Row],[Ledger Name]],Table4[[#This Row],[Entity Name]]) -> ICE Gate E- Wallet ( Custom Duty )Expora | D48: Ledger | E48: BS | F48: Cash and bank balances | G48: Bank Balance
A49: IDBI Bank | B49: Expora | C49: =_xlfn.CONCAT(Table4[[#This Row],[Ledger Name]],Table4[[#This Row],[Entity Name]]) -> IDBI BankExpora | D49: Ledger | E49: BS | F49: Cash and bank balances | G49: Bank Balance
A50: IGST Receivable | B50: Expora | C50: =_xlfn.CONCAT(Table4[[#This Row],[Ledger Name]],Table4[[#This Row],[Entity Name]]) -> IGST ReceivableExpora | D50: Ledger | E50: BS | F50: Other Current Asset | G50: GST Input tax Assets
A51: Input Tax Credits | B51: Expora | C51: =_xlfn.CONCAT(Table4[[#This Row],[Ledger Name]],Table4[[#This Row],[Entity Name]]) -> Input Tax CreditsExpora | D51: Group | E51: 0 | F51: 0 | G51: 0
A52: Input CGST | B52: Expora | C52: =_xlfn.CONCAT(Table4[[#This Row],[Ledger Name]],Table4[[#This Row],[Entity Name]]) -> Input CGSTExpora | D52: Ledger | E52: BS | F52: Other Current Asset | G52: GST Input tax Assets
A53: Input IGST | B53: Expora | C53: =_xlfn.CONCAT(Table4[[#This Row],[Ledger Name]],Table4[[#This Row],[Entity Name]]) -> Input IGSTExpora | D53: Ledger | E53: BS | F53: Other Current Asset | G53: GST Input tax Assets
A54: Input SGST | B54: Expora | C54: =_xlfn.CONCAT(Table4[[#This Row],[Ledger Name]],Table4[[#This Row],[Entity Name]]) -> Input SGSTExpora | D54: Ledger | E54: BS | F54: Other Current Asset | G54: GST Input tax Assets
A55: Total for Input Tax Credits | B55: Expora | C55: =_xlfn.CONCAT(Table4[[#This Row],[Ledger Name]],Table4[[#This Row],[Entity Name]]) -> Total for Input Tax CreditsExpora | D55: Group | E55: 0 | F55: 0 | G55: 0
A56: Intangible Asset | B56: Expora | C56: =_xlfn.CONCAT(Table4[[#This Row],[Ledger Name]],Table4[[#This Row],[Entity Name]]) -> Intangible AssetExpora | D56: Group | E56: 0 | F56: 0 | G56: 0
A57: Expora OS | B57: Expora | C57: =_xlfn.CONCAT(Table4[[#This Row],[Ledger Name]],Table4[[#This Row],[Entity Name]]) -> Expora OSExpora | D57: Ledger | E57: BS | F57: Fixed assets -Intangible | G57: Fixed assets -Intangible
A58: Total for Intangible Asset | B58: Expora | C58: =_xlfn.CONCAT(Table4[[#This Row],[Ledger Name]],Table4[[#This Row],[Entity Name]]) -> Total for Intangible AssetExpora | D58: Group | E58: 0 | F58: 0 | G58: 0
A59: Interest Receivable | B59: Expora | C59: =_xlfn.CONCAT(Table4[[#This Row],[Ledger Name]],Table4[[#This Row],[Entity Name]]) -> Interest ReceivableExpora | D59: Ledger | E59: BS | F59: Other Current Asset | G59: LOAN TO SUBSIDIARIES
A60: Inventory Asset | B60: Expora | C60: =_xlfn.CONCAT(Table4[[#This Row],[Ledger Name]],Table4[[#This Row],[Entity Name]]) -> Inventory AssetExpora | D60: Ledger | E60: BS | F60: Closing Stock | G60: Closing Stock
A61: Loans & Advances (Asset) | B61: Expora | C61: =_xlfn.CONCAT(Table4[[#This Row],[Ledger Name]],Table4[[#This Row],[Entity Name]]) -> Loans & Advances (Asset)Expora | D61: Group | E61: 0 | F61: 0 | G61: 0
A62: Arha Platform General Trading LLC (L) | B62: Expora | C62: =_xlfn.CONCAT(Table4[[#This Row],[Ledger Name]],Table4[[#This Row],[Entity Name]]) -> Arha Platform General Trading LLC (L)Expora | D62: Ledger | E62: BS | F62: Other Current Asset | G62: LOAN TO SUBSIDIARIES
A63: Arha Platform Jewellery Trading LLC (L) | B63: Expora | C63: =_xlfn.CONCAT(Table4[[#This Row],[Ledger Name]],Table4[[#This Row],[Entity Name]]) -> Arha Platform Jewellery Trading LLC (L)Expora | D63: Ledger | E63: BS | F63: Other Current Asset | G63: Loans to Arha Platforms Jewellery Trading LLC (UAE Subs)
A64: Loan to Arha Benin | B64: Expora | C64: =_xlfn.CONCAT(Table4[[#This Row],[Ledger Name]],Table4[[#This Row],[Entity Name]]) -> Loan to Arha BeninExpora | D64: Ledger | E64: BS | F64: Other Current Asset | G64: LOAN TO SUBSIDIARIES
A65: Loan to Aspirarch Lanka (Pvt) Ltd | B65: Expora | C65: =_xlfn.CONCAT(Table4[[#This Row],[Ledger Name]],Table4[[#This Row],[Entity Name]]) -> Loan to Aspirarch Lanka (Pvt) LtdExpora | D65: Ledger | E65: BS | F65: Other Current Asset | G65: LOAN TO SUBSIDIARIES
A66: Loan to Aspirarch Market Platforms Limited (US Sub) | B66: Expora | C66: =_xlfn.CONCAT(Table4[[#This Row],[Ledger Name]],Table4[[#This Row],[Entity Name]]) -> Loan to Aspirarch Market Platforms Limited (US Sub)Expora | D66: Ledger | E66: BS | F66: Other Current Asset | G66: LOAN TO SUBSIDIARIES
A67: Loan to MKS EXPORA | B67: Expora | C67: =_xlfn.CONCAT(Table4[[#This Row],[Ledger Name]],Table4[[#This Row],[Entity Name]]) -> Loan to MKS EXPORAExpora | D67: Ledger | E67: BS | F67: Other Current Asset | G67: LOAN TO SUBSIDIARIES
A68: Loans to Arha Platforms General Trading LLC | B68: Expora | C68: =_xlfn.CONCAT(Table4[[#This Row],[Ledger Name]],Table4[[#This Row],[Entity Name]]) -> Loans to Arha Platforms General Trading LLCExpora | D68: Ledger | E68: BS | F68: Other Current Asset | G68: LOAN TO SUBSIDIARIES
A69: Loans to Arha Platforms Jewellery Trading LLC | B69: Expora | C69: =_xlfn.CONCAT(Table4[[#This Row],[Ledger Name]],Table4[[#This Row],[Entity Name]]) -> Loans to Arha Platforms Jewellery Trading LLCExpora | D69: Ledger | E69: BS | F69: Other Current Asset | G69: Loans to Arha Platforms Jewellery Trading LLC (UAE Subs)
A70: Total for Loans & Advances (Asset) | B70: Expora | C70: =_xlfn.CONCAT(Table4[[#This Row],[Ledger Name]],Table4[[#This Row],[Entity Name]]) -> Total for Loans & Advances (Asset)Expora | D70: Group | E70: 0 | F70: 0 | G70: 0
A71: Non Current Investment | B71: Expora | C71: =_xlfn.CONCAT(Table4[[#This Row],[Ledger Name]],Table4[[#This Row],[Entity Name]]) -> Non Current InvestmentExpora | D71: Group | E71: 0 | F71: 0 | G71: 0
A72: Arha Platform General Trading LLC (SC) | B72: Expora | C72: =_xlfn.CONCAT(Table4[[#This Row],[Ledger Name]],Table4[[#This Row],[Entity Name]]) -> Arha Platform General Trading LLC (SC)Expora | D72: Ledger | E72: BS | F72: Investment in Arha Platforms Genral Trading LLC | G72: Investment in Arha Platforms Genral Trading LLC
A73: Parnia Expora | B73: Expora | C73: =_xlfn.CONCAT(Table4[[#This Row],[Ledger Name]],Table4[[#This Row],[Entity Name]]) -> Parnia ExporaExpora | D73: Ledger | E73: BS | F73: Investment in Parnia Expora Pvt Ltd | G73: Investment in Parnia Expora Pvt Ltd
A74: Term Deposit | B74: Expora | C74: =_xlfn.CONCAT(Table4[[#This Row],[Ledger Name]],Table4[[#This Row],[Entity Name]]) -> Term DepositExpora | D74: Ledger | E74: BS | F74: Term Deposits | G74: Term Deposits
A75: Total for Non Current Investment | B75: Expora | C75: =_xlfn.CONCAT(Table4[[#This Row],[Ledger Name]],Table4[[#This Row],[Entity Name]]) -> Total for Non Current InvestmentExpora | D75: Group | E75: 0 | F75: 0 | G75: 0
B76: Expora | C76: =_xlfn.CONCAT(Table4[[#This Row],[Ledger Name]],Table4[[#This Row],[Entity Name]]) -> Expora | D76: Group | E76: 0 | F76: 0 | G76: 0
A77: Alfa water purifier | B77: Expora | C77: =_xlfn.CONCAT(Table4[[#This Row],[Ledger Name]],Table4[[#This Row],[Entity Name]]) -> Alfa water purifierExpora | D77: Ledger | E77: BS | F77: Fixed assets -Tangible | G77: Fixed assets -Tangible
A78: Face Reader Attendance Device | B78: Expora | C78: =_xlfn.CONCAT(Table4[[#This Row],[Ledger Name]],Table4[[#This Row],[Entity Name]]) -> Face Reader Attendance DeviceExpora | D78: Ledger | E78: BS | F78: Fixed assets -Tangible | G78: Fixed assets -Tangible
A79: kelvinator refrigerator | B79: Expora | C79: =_xlfn.CONCAT(Table4[[#This Row],[Ledger Name]],Table4[[#This Row],[Entity Name]]) -> kelvinator refrigeratorExpora | D79: Ledger | E79: BS | F79: Fixed assets -Tangible | G79: Fixed assets -Tangible
A80: LG Oven | B80: Expora | C80: =_xlfn.CONCAT(Table4[[#This Row],[Ledger Name]],Table4[[#This Row],[Entity Name]]) -> LG OvenExpora | D80: Ledger | E80: BS | F80: Fixed assets -Tangible | G80: Fixed assets -Tangible
A81: Nokia | B81: Expora | C81: =_xlfn.CONCAT(Table4[[#This Row],[Ledger Name]],Table4[[#This Row],[Entity Name]]) -> NokiaExpora | D81: Ledger | E81: BS | F81: Fixed assets -Tangible | G81: Fixed assets -Tangible
A82: OPPO A31 | B82: Expora | C82: =_xlfn.CONCAT(Table4[[#This Row],[Ledger Name]],Table4[[#This Row],[Entity Name]]) -> OPPO A31Expora | D82: Ledger | E82: BS | F82: Fixed assets -Tangible | G82: Fixed assets -Tangible
A83: Redmi 10 Prime | B83: Expora | C83: =_xlfn.CONCAT(Table4[[#This Row],[Ledger Name]],Table4[[#This Row],[Entity Name]]) -> Redmi 10 PrimeExpora | D83: Ledger | E83: BS | F83: Fixed assets -Tangible | G83: Fixed assets -Tangible
A84: Voltas Water Dispenser | B84: Expora | C84: =_xlfn.CONCAT(Table4[[#This Row],[Ledger Name]],Table4[[#This Row],[Entity Name]]) -> Voltas Water DispenserExpora | D84: Ledger | E84: BS | F84: Fixed assets -Tangible | G84: Fixed assets -Tangible
A85: VU 55' Ultra HD TV | B85: Expora | C85: =_xlfn.CONCAT(Table4[[#This Row],[Ledger Name]],Table4[[#This Row],[Entity Name]]) -> VU 55' Ultra HD TVExpora | D85: Ledger | E85: BS | F85: Fixed assets -Tangible | G85: Fixed assets -Tangible
A86: Total for Office Equipment | B86: Expora | C86: =_xlfn.CONCAT(Table4[[#This Row],[Ledger Name]],Table4[[#This Row],[Entity Name]]) -> Total for Office EquipmentExpora | D86: Group | E86: 0 | F86: 0 | G86: 0
A87: Petty Cash | B87: Expora | C87: =_xlfn.CONCAT(Table4[[#This Row],[Ledger Name]],Table4[[#This Row],[Entity Name]]) -> Petty CashExpora | D87: Ledger | E87: BS | F87: Cash and bank balances | G87: Cash Balance
C88: =_xlfn.CONCAT(Table4[[#This Row],[Ledger Name]],Table4[[#This Row],[Entity Name]]) | D88: Ledger | E88: BS | F88: Other Current Asset | G88: LOAN TO SUBSIDIARIES
A89: Prepaid Expenses | B89: Expora | C89: =_xlfn.CONCAT(Table4[[#This Row],[Ledger Name]],Table4[[#This Row],[Entity Name]]) -> Prepaid ExpensesExpora | D89: Ledger | E89: BS | F89: Other Current Asset | G89: Prepaid Expenses
A90: Reverse Charge Tax Input but not due | B90: Expora | C90: =_xlfn.CONCAT(Table4[[#This Row],[Ledger Name]],Table4[[#This Row],[Entity Name]]) -> Reverse Charge Tax Input but not dueExpora | D90: Ledger | E90: BS | F90: Other Current Asset | G90: GST Input tax Assets
A91: Rodtep Receivable | B91: Expora | C91: =_xlfn.CONCAT(Table4[[#This Row],[Ledger Name]],Table4[[#This Row],[Entity Name]]) -> Rodtep ReceivableExpora | D91: Ledger | E91: BS | F91: Other Current Asset | G91: Rodtep Receivable
A92: Security Deposit | B92: Expora | C92: =_xlfn.CONCAT(Table4[[#This Row],[Ledger Name]],Table4[[#This Row],[Entity Name]]) -> Security DepositExpora | D92: Ledger | E92: BS | F92: Other Current Asset | G92: Security Deposit
A93: Security Deposit (Shipping) | B93: Expora | C93: =_xlfn.CONCAT(Table4[[#This Row],[Ledger Name]],Table4[[#This Row],[Entity Name]]) -> Security Deposit (Shipping)Expora | D93: Ledger | E93: BS | F93: Other Current Asset | G93: Security Deposit
A94: Security Deposit - Delhi Office | B94: Expora | C94: =_xlfn.CONCAT(Table4[[#This Row],[Ledger Name]],Table4[[#This Row],[Entity Name]]) -> Security Deposit - Delhi OfficeExpora | D94: Ledger | E94: BS | F94: Other Current Asset | G94: Security Deposit
A95: Security Deposit - Reliance Internet | B95: Expora | C95: =_xlfn.CONCAT(Table4[[#This Row],[Ledger Name]],Table4[[#This Row],[Entity Name]]) -> Security Deposit - Reliance InternetExpora | D95: Ledger | E95: BS | F95: Other Current Asset | G95: Security Deposit
A96: Security Deposit - Vidyavihar Office | B96: Expora | C96: =_xlfn.CONCAT(Table4[[#This Row],[Ledger Name]],Table4[[#This Row],[Entity Name]]) -> Security Deposit - Vidyavihar OfficeExpora | D96: Ledger | E96: BS | F96: Other Current Asset | G96: Security Deposit
A97: Security Deposit-Guntur Office | B97: Expora | C97: =_xlfn.CONCAT(Table4[[#This Row],[Ledger Name]],Table4[[#This Row],[Entity Name]]) -> Security Deposit-Guntur OfficeExpora | D97: Ledger | E97: BS | F97: Other Current Asset | G97: Security Deposit
A98: Total for Security Deposit | B98: Expora | C98: =_xlfn.CONCAT(Table4[[#This Row],[Ledger Name]],Table4[[#This Row],[Entity Name]]) -> Total for Security DepositExpora | D98: Group | E98: 0 | F98: 0
A99: TCS | B99: Expora | C99: =_xlfn.CONCAT(Table4[[#This Row],[Ledger Name]],Table4[[#This Row],[Entity Name]]) -> TCSExpora | D99: Ledger | E99: BS | F99: Other Current Asset | G99: TCS Receivable
A100: TCS Receivable | B100: Expora | C100: =_xlfn.CONCAT(Table4[[#This Row],[Ledger Name]],Table4[[#This Row],[Entity Name]]) -> TCS ReceivableExpora | D100: Ledger | E100: BS | F100: Other Current Asset | G100: TCS Receivable
A101: TDS Receivable | B101: Expora | C101: =_xlfn.CONCAT(Table4[[#This Row],[Ledger Name]],Table4[[#This Row],[Entity Name]]) -> TDS ReceivableExpora | D101: Ledger | E101: BS | F101: Other Current Asset | G101: TDS Receivable
A102: Tradearch Market Platforms Pvt Ltd -OD ACCOUNT AXIS | B102: Expora | C102: =_xlfn.CONCAT(Table4[[#This Row],[Ledger Name]],Table4[[#This Row],[Entity Name]]) -> Tradearch Market Platforms Pvt Ltd -OD ACCOUNT AXISExpora | D102: Ledger | E102: BS | F102: Short-term borrowings | G102: Bank OD
A103: Tradearch Market Platforms Pvt Ltd- SC | B103: Expora | C103: =_xlfn.CONCAT(Table4[[#This Row],[Ledger Name]],Table4[[#This Row],[Entity Name]]) -> Tradearch Market Platforms Pvt Ltd- SCExpora | D103: Ledger | E103: BS | F103: Cash and bank balances | G103: Bank Balance
A104: Liabilities | B104: Expora | C104: =_xlfn.CONCAT(Table4[[#This Row],[Ledger Name]],Table4[[#This Row],[Entity Name]]) -> LiabilitiesExpora | D104: Group | E104: 0 | F104: 0 | G104: 0
A105: 4505060100457296 | B105: Expora | C105: =_xlfn.CONCAT(Table4[[#This Row],[Ledger Name]],Table4[[#This Row],[Entity Name]]) -> 4505060100457296Expora | D105: Ledger | E105: BS | F105: Other Current Asset | G105: Credit Card Balance
A106: 4505060100457304 | B106: Expora | C106: =_xlfn.CONCAT(Table4[[#This Row],[Ledger Name]],Table4[[#This Row],[Entity Name]]) -> 4505060100457304Expora | D106: Ledger | E106: BS | F106: Other Current Asset | G106: Credit Card Balance
A107: Accounts Payable | B107: Expora | C107: =_xlfn.CONCAT(Table4[[#This Row],[Ledger Name]],Table4[[#This Row],[Entity Name]]) -> Accounts PayableExpora | D107: Ledger | E107: BS | F107: Trade payables | G107: Trade payables
...

Sheet AGT TB Apr -25
D1: =C2-D2 -> 0 | G1: =G2/3.67 -> 0 | N1: 26 | O1: 23.48
B2: =SUBTOTAL(9,B4:B161) -> 0 | C2: =SUBTOTAL(9,C4:C161) -> 0 | D2: =SUBTOTAL(9,D4:D161) -> 0 | E2: =SUBTOTAL(9,E4:E161) -> 0 | F2: =SUBTOTAL(9,F4:F161) -> 0 | G2: =SUBTOTAL(9,G4:G161) -> 0
A3: Account | B3: 45748 | C3: 45778 | D3: 45809 | E3: 45839 | F3: 45870 | G3: Total | H3: Apr-25 INR | I3: May-25 INR | J3: June-25 INR | K3: Jul-25 INR | L3: Aug-25 INR | M3: Total INR | N3: Entity Name | O3: Concate | P3: Group/Legder | Q3: PL/BS | R3: Category | S3: Sub Category | T3: Remarks
A4: Accounts Receivable | G4: =SUM(B4:F4) -> 0 | H4: =B4*$N$1 -> 0 | I4: =C4*$N$1 -> 0 | J4: =D4*$N$1 -> 0 | K4: =E4*$N$1 -> 0 | L4: =F4*$N$1 -> 0 | M4: =G4*$N$1 -> 0 | N4: Arha General Trading Co (AGT) | O4: =CONCATENATE(A4,N4) -> Accounts ReceivableArha General Trading Co (AGT) | P4: {=_xlfn.XLOOKUP(O4,Table4[Concate],Table4[[Group/Legder]:[Sub Category]],,0)} -> Ledger | Q4: BS | R4: Trade Receivables | S4: Trade Receivables
A5: AL ANSARI EXCHANGE LLC-Account | G5: =SUM(B5:F5) -> 0 | H5: =B5*$N$1 -> 0 | I5: =C5*$N$1 -> 0 | J5: =D5*$N$1 -> 0 | K5: =E5*$N$1 -> 0 | L5: =F5*$N$1 -> 0 | M5: =G5*$N$1 -> 0 | N5: Arha General Trading Co (AGT) | O5: =CONCATENATE(A5,N5) -> AL ANSARI EXCHANGE LLC-AccountArha General Trading Co (AGT) | P5: {=_xlfn.XLOOKUP(O5,Table4[Concate],Table4[[Group/Legder]:[Sub Category]],,0)} -> Ledger | Q5: BS | R5: Cash and bank balances | S5: Bank Balance
A6: AL BAHR AL ASWAD ADV GIFTS TR LLC | G6: =SUM(B6:F6) -> 0 | H6: =B6*$N$1 -> 0 | I6: =C6*$N$1 -> 0 | J6: =D6*$N$1 -> 0 | K6: =E6*$N$1 -> 0 | L6: =F6*$N$1 -> 0 | M6: =G6*$N$1 -> 0 | N6: Arha General Trading Co (AGT) | O6: =CONCATENATE(A6,N6) -> AL BAHR AL ASWAD ADV GIFTS TR LLCArha General Trading Co (AGT) | P6: {=_xlfn.XLOOKUP(O6,Table4[Concate],Table4[[Group/Legder]:[Sub Category]],,0)} -> Ledger | Q6: BS | R6: Other Current Asset | S6: Prepaid Expenses
A7: ARHA PLATFORMS GENERAL TRADING L.L.C (Mashreq) | G7: =SUM(B7:F7) -> 0 | H7: =B7*$N$1 -> 0 | I7: =C7*$N$1 -> 0 | J7: =D7*$N$1 -> 0 | K7: =E7*$N$1 -> 0 | L7: =F7*$N$1 -> 0 | M7: =G7*$N$1 -> 0 | N7: Arha General Trading Co (AGT) | O7: =CONCATENATE(A7,N7) -> ARHA PLATFORMS GENERAL TRADING L.L.C (Mashreq)Arha General Trading Co (AGT) | P7: {=_xlfn.XLOOKUP(O7,Table4[Concate],Table4[[Group/Legder]:[Sub Category]],,0)} -> Ledger | Q7: BS | R7: Cash and bank balances | S7: Bank Balance
A8: ARHA PLATFORMS GENERAL TRADING L.L.C (USD A/c) | G8: =SUM(B8:F8) -> 0 | H8: =B8*$N$1 -> 0 | I8: =C8*$N$1 -> 0 | J8: =D8*$N$1 -> 0 | K8: =E8*$N$1 -> 0 | L8: =F8*$N$1 -> 0 | M8: =G8*$N$1 -> 0 | N8: Arha General Trading Co (AGT) | O8: =CONCATENATE(A8,N8) -> ARHA PLATFORMS GENERAL TRADING L.L.C (USD A/c)Arha General Trading Co (AGT) | P8: {=_xlfn.XLOOKUP(O8,Table4[Concate],Table4[[Group/Legder]:[Sub Category]],,0)} -> Ledger | Q8: BS | R8: Cash and bank balances | S8: Bank Balance
A9: ARHA PLATFORMS GENERAL TRADING LLC (USD A/c) | G9: =SUM(B9:F9) -> 0 | H9: =B9*$N$1 -> 0 | I9: =C9*$N$1 -> 0 | J9: =D9*$N$1 -> 0 | K9: =E9*$N$1 -> 0 | L9: =F9*$N$1 -> 0 | M9: =G9*$N$1 -> 0 | N9: Arha General Trading Co (AGT) | O9: =CONCATENATE(A9,N9) -> ARHA PLATFORMS GENERAL TRADING LLC (USD A/c)Arha General Trading Co (AGT) | P9: {=_xlfn.XLOOKUP(O9,Table4[Concate],Table4[[Group/Legder]:[Sub Category]],,0)} -> Ledger | Q9: BS | R9: Cash and bank balances | S9: Bank Balance
A10: Clearing GL | G10: =SUM(B10:F10) -> 0 | H10: =B10*$N$1 -> 0 | I10: =C10*$N$1 -> 0 | J10: =D10*$N$1 -> 0 | K10: =E10*$N$1 -> 0 | L10: =F10*$N$1 -> 0 | M10: =G10*$N$1 -> 0 | N10: Arha General Trading Co (AGT) | O10: =CONCATENATE(A10,N10) -> Clearing GLArha General Trading Co (AGT) | P10: {=_xlfn.XLOOKUP(O10,Table4[Concate],Table4[[Group/Legder]:[Sub Category]],,0)} -> Ledger | Q10: BS | R10: Provisions and Other Current Liabilities | S10: Other Provision Payable
A11: Cooler | G11: =SUM(B11:F11) -> 0 | H11: =B11*$N$1 -> 0 | I11: =C11*$N$1 -> 0 | J11: =D11*$N$1 -> 0 | K11: =E11*$N$1 -> 0 | L11: =F11*$N$1 -> 0 | M11: =G11*$N$1 -> 0 | N11: Arha General Trading Co (AGT) | O11: =CONCATENATE(A11,N11) -> CoolerArha General Trading Co (AGT) | P11: {=_xlfn.XLOOKUP(O11,Table4[Concate],Table4[[Group/Legder]:[Sub Category]],,0)} -> Ledger | Q11: BS | R11: Fixed assets -Tangible | S11: Fixed assets -Tangible
A12: Cycle | G12: =SUM(B12:F12) -> 0 | H12: =B12*$N$1 -> 0 | I12: =C12*$N$1 -> 0 | J12: =D12*$N$1 -> 0 | K12: =E12*$N$1 -> 0 | L12: =F12*$N$1 -> 0 | M12: =G12*$N$1 -> 0 | N12: Arha General Trading Co (AGT) | O12: =CONCATENATE(A12,N12) -> CycleArha General Trading Co (AGT) | P12: {=_xlfn.XLOOKUP(O12,Table4[Concate],Table4[[Group/Legder]:[Sub Category]],,0)} -> Ledger | Q12: BS | R12: Fixed assets -Tangible | S12: Fixed assets -Tangible
A13: Deepak Motwani ( Cash Sales) | G13: =SUM(B13:F13) -> 0 | H13: =B13*$N$1 -> 0 | I13: =C13*$N$1 -> 0 | J13: =D13*$N$1 -> 0 | K13: =E13*$N$1 -> 0 | L13: =F13*$N$1 -> 0 | M13: =G13*$N$1 -> 0 | N13: Arha General Trading Co (AGT) | O13: =CONCATENATE(A13,N13) -> Deepak Motwani ( Cash Sales)Arha General Trading Co (AGT) | P13: {=_xlfn.XLOOKUP(O13,Table4[Concate],Table4[[Group/Legder]:[Sub Category]],,0)} -> Ledger | Q13: BS | R13: Cash and bank balances | S13: Cash Balance
A14: Car Deposit | G14: =SUM(B14:F14) -> 0 | H14: =B14*$N$1 -> 0 | I14: =C14*$N$1 -> 0 | J14: =D14*$N$1 -> 0 | K14: =E14*$N$1 -> 0 | L14: =F14*$N$1 -> 0 | M14: =G14*$N$1 -> 0 | N14: Arha General Trading Co (AGT) | O14: =CONCATENATE(A14,N14) -> Car DepositArha General Trading Co (AGT) | P14: {=_xlfn.XLOOKUP(O14,Table4[Concate],Table4[[Group/Legder]:[Sub Category]],,0)} -> Ledger | Q14: BS | R14: Other Current Asset | S14: Security Deposit
A15: Electricity and Water Deposit | G15: =SUM(B15:F15) -> 0 | H15: =B15*$N$1 -> 0 | I15: =C15*$N$1 -> 0 | J15: =D15*$N$1 -> 0 | K15: =E15*$N$1 -> 0 | L15: =F15*$N$1 -> 0 | M15: =G15*$N$1 -> 0 | N15: Arha General Trading Co (AGT) | O15: =CONCATENATE(A15,N15) -> Electricity and Water DepositArha General Trading Co (AGT) | P15: {=_xlfn.XLOOKUP(O15,Table4[Concate],Table4[[Group/Legder]:[Sub Category]],,0)} -> Ledger | Q15: BS | R15: Other Current Asset | S15: Security Deposit
... A87: ARGT/LOC/2026/259 | G87: =SUM(B87:F87) -> 0 | H87: =B87*$N$1 -> 0 | I87: =C87*$N$1 -> 0 | J87: =D87*$N$1 -> 0 | K87: =E87*$N$1 -> 0 | L87: =F87*$N$1 -> 0 | M87: =G87*$N$1 -> 0 | N87: Arha General Trading Co (AGT) | O87: =CONCATENATE(A87,N87) -> ARGT/LOC/2026/259Arha General Trading Co (AGT) | P87: {=_xlfn.XLOOKUP(O87,Table4[Concate],Table4[[Group/Legder]:[Sub Category]],,0)} -> Ledger | Q87: PL | R87: Direct Expenses | S87: Freight & forwarding Charges
A88: ARGT/LOC/2026/266 | G88: =SUM(B88:F88) -> 0 | H88: =B88*$N$1 -> 0 | I88: =C88*$N$1 -> 0 | J88: =D88*$N$1 -> 0 | K88: =E88*$N$1 -> 0 | L88: =F88*$N$1 -> 0 | M88: =G88*$N$1 -> 0 | N88: Arha General Trading Co (AGT) | O88: =CONCATENATE(A88,N88) -> ARGT/LOC/2026/266Arha General Trading Co (AGT) | P88: {=_xlfn.XLOOKUP(O88,Table4[Concate],Table4[[Group/Legder]:[Sub Category]],,0)} -> Ledger | Q88: PL | R88: Direct Expenses | S88: Freight & forwarding Charges | T88: Loan
A89: ARGT/LOC/2026/268 | G89: =SUM(B89:F89) -> 0 | H89: =B89*$N$1 -> 0 | I89: =C89*$N$1 -> 0 | J89: =D89*$N$1 -> 0 | K89: =E89*$N$1 -> 0 | L89: =F89*$N$1 -> 0 | M89: =G89*$N$1 -> 0 | N89: Arha General Trading Co (AGT) | O89: =CONCATENATE(A89,N89) -> ARGT/LOC/2026/268Arha General Trading Co (AGT) | P89: {=_xlfn.XLOOKUP(O89,Table4[Concate],Table4[[Group/Legder]:[Sub Category]],,0)} -> Ledger | Q89: PL | R89: Direct Expenses | S89: Freight & forwarding Charges
A90: ARGT/LOC/2026/274 | G90: =SUM(B90:F90) -> 0 | H90: =B90*$N$1 -> 0 | I90: =C90*$N$1 -> 0 | J90: =D90*$N$1 -> 0 | K90: =E90*$N$1 -> 0 | L90: =F90*$N$1 -> 0 | M90: =G90*$N$1 -> 0 | N90: Arha General Trading Co (AGT) | O90: =CONCATENATE(A90,N90) -> ARGT/LOC/2026/274Arha General Trading Co (AGT) | P90: {=_xlfn.XLOOKUP(O90,Table4[Concate],Table4[[Group/Legder]:[Sub Category]],,0)} -> Ledger | Q90: PL | R90: Direct Expenses | S90: Freight & forwarding Charges
A91: ARGT/LOC/2026/275 | G91: =SUM(B91:F91) -> 0 | H91: =B91*$N$1 -> 0 | I91: =C91*$N$1 -> 0 | J91: =D91*$N$1 -> 0 | K91: =E91*$N$1 -> 0 | L91: =F91*$N$1 -> 0 | M91: =G91*$N$1 -> 0 | N91: Arha General Trading Co (AGT) | O91: =CONCATENATE(A91,N91) -> ARGT/LOC/2026/275Arha General Trading Co (AGT) | P91: {=_xlfn.XLOOKUP(O91,Table4[Concate],Table4[[Group/Legder]:[Sub Category]],,0)} -> Ledger | Q91: PL | R91: Direct Expenses | S91: Freight & forwarding Charges
A92: ARGT/LOC/2026/276 | G92: =SUM(B92:F92) -> 0 | H92: =B92*$N$1 -> 0 | I92: =C92*$N$1 -> 0 | J92: =D92*$N$1 -> 0 | K92: =E92*$N$1 -> 0 | L92: =F92*$N$1 -> 0 | M92: =G92*$N$1 -> 0 | N92: Arha General Trading Co (AGT) | O92: =CONCATENATE(A92,N92) -> ARGT/LOC/2026/276Arha General Trading Co (AGT) | P92: {=_xlfn.XLOOKUP(O92,Table4[Concate],Table4[[Group/Legder]:[Sub Category]],,0)} -> Ledger | Q92: PL | R92: Direct Expenses | S92: Freight & forwarding Charges
A93: ARGT/LOC/2026/283A | G93: =SUM(B93:F93) -> 0 | H93: =B93*$N$1 -> 0 | I93: =C93*$N$1 -> 0 | J93: =D93*$N$1 -> 0 | K93: =E93*$N$1 -> 0 | L93: =F93*$N$1 -> 0 | M93: =G93*$N$1 -> 0 | N93: Arha General Trading Co (AGT) | O93: =CONCATENATE(A93,N93) -> ARGT/LOC/2026/283AArha General Trading Co (AGT) | P93: {=_xlfn.XLOOKUP(O93,Table4[Concate],Table4[[Group/Legder]:[Sub Category]],,0)} -> Ledger | Q93: PL | R93: Direct Expenses | S93: Freight & forwarding Charges
A94: ARGT/LOC/2026/284 | G94: =SUM(B94:F94) -> 0 | H94: =B94*$N$1 -> 0 | I94: =C94*$N$1 -> 0 | J94: =D94*$N$1 -> 0 | K94: =E94*$N$1 -> 0 | L94: =F94*$N$1 -> 0 | M94: =G94*$N$1 -> 0 | N94: Arha General Trading Co (AGT) | O94: =CONCATENATE(A94,N94) -> ARGT/LOC/2026/284Arha General Trading Co (AGT) | P94: {=_xlfn.XLOOKUP(O94,Table4[Concate],Table4[[Group/Legder]:[Sub Category]],,0)} -> Ledger | Q94: PL | R94: Direct Expenses | S94: Freight & forwarding Charges
A95: ARGT/LOC/2026/287 | G95: =SUM(B95:F95) -> 0 | H95: =B95*$N$1 -> 0 | I95: =C95*$N$1 -> 0 | J95: =D95*$N$1 -> 0 | K95: =E95*$N$1 -> 0 | L95: =F95*$N$1 -> 0 | M95: =G95*$N$1 -> 0 | N95: Arha General Trading Co (AGT) | O95: =CONCATENATE(A95,N95) -> ARGT/LOC/2026/287Arha General Trading Co (AGT) | P95: {=_xlfn.XLOOKUP(O95,Table4[Concate],Table4[[Group/Legder]:[Sub Category]],,0)} -> Ledger | Q95: PL | R95: Direct Expenses | S95: Freight & forwarding Charges
A96: ARGT/LOC/2026/289 | G96: =SUM(B96:F96) -> 0 | H96: =B96*$N$1 -> 0 | I96: =C96*$N$1 -> 0 | J96: =D96*$N$1 -> 0 | K96: =E96*$N$1 -> 0 | L96: =F96*$N$1 -> 0 | M96: =G96*$N$1 -> 0 | N96: Arha General Trading Co (AGT) | O96: =CONCATENATE(A96,N96) -> ARGT/LOC/2026/289Arha General Trading Co (AGT) | P96: {=_xlfn.XLOOKUP(O96,Table4[Concate],Table4[[Group/Legder]:[Sub Category]],,0)} -> Ledger | Q96: PL | R96: Direct Expenses | S96: Freight & forwarding Charges
A97: ARGT/LOC/2026/293 | G97: =SUM(B97:F97) -> 0 | H97: =B97*$N$1 -> 0 | I97: =C97*$N$1 -> 0 | J97: =D97*$N$1 -> 0 | K97: =E97*$N$1 -> 0 | L97: =F97*$N$1 -> 0 | M97: =G97*$N$1 -> 0 | N97: Arha General Trading Co (AGT) | O97: =CONCATENATE(A97,N97) -> ARGT/LOC/2026/293Arha General Trading Co (AGT) | P97: {=_xlfn.XLOOKUP(O97,Table4[Concate],Table4[[Group/Legder]:[Sub Category]],,0)} -> Ledger | Q97: PL | R97: Direct Expenses | S97: Freight & forwarding Charges
A98: ARGT/LOC/2026/296 | G98: =SUM(B98:F98) -> 0 | H98: =B98*$N$1 -> 0 | I98: =C98*$N$1 -> 0 | J98: =D98*$N$1 -> 0 | K98: =E98*$N$1 -> 0 | L98: =F98*$N$1 -> 0 | M98: =G98*$N$1 -> 0 | N98: Arha General Trading Co (AGT) | O98: =CONCATENATE(A98,N98) -> ARGT/LOC/2026/296Arha General Trading Co (AGT) | P98: {=_xlfn.XLOOKUP(O98,Table4[Concate],Table4[[Group/Legder]:[Sub Category]],,0)} -> Ledger | Q98: PL | R98: Direct Expenses | S98: Freight & forwarding Charges
A99: ARGT/LOC/2026/304 | G99: =SUM(B99:F99) -> 0 | H99: =B99*$N$1 -> 0 | I99: =C99*$N$1 -> 0 | J99: =D99*$N$1 -> 0 | K99: =E99*$N$1 -> 0 | L99: =F99*$N$1 -> 0 | M99: =G99*$N$1 -> 0 | N99: Arha General Trading Co (AGT) | O99: =CONCATENATE(A99,N99) -> ARGT/LOC/2026/304Arha General Trading Co (AGT) | P99: {=_xlfn.XLOOKUP(O99,Table4[Concate],Table4[[Group/Legder]:[Sub Category]],,0)} -> Ledger | Q99: PL | R99: Direct Expenses | S99: Freight & forwarding Charges
A100: ARGT/LOC/2026/309 | G100: =SUM(B100:F100) -> 0 | H100: =B100*$N$1 -> 0 | I100: =C100*$N$1 -> 0 | J100: =D100*$N$1 -> 0 | K100: =E100*$N$1 -> 0 | L100: =F100*$N$1 -> 0 | M100: =G100*$N$1 -> 0 | N100: Arha General Trading Co (AGT) | O100: =CONCATENATE(A100,N100) -> ARGT/LOC/2026/309Arha General Trading Co (AGT) | P100: {=_xlfn.XLOOKUP(O100,Table4[Concate],Table4[[Group/Legder]:[Sub Category]],,0)} -> Ledger | Q100: PL | R100: Direct Expenses | S100: Freight & forwarding Charges
... A112: Bad Debt | G112: =SUM(B112:F112) -> 0 | H112: =B112*$N$1 -> 0 | I112: =C112*$N$1 -> 0 | J112: =D112*$N$1 -> 0 | K112: =E112*$N$1 -> 0 | L112: =F112*$N$1 -> 0 | M112: =G112*$N$1 -> 0 | N112: Arha General Trading Co (AGT) | O112: =CONCATENATE(A112,N112) -> Bad DebtArha General Trading Co (AGT) | P112: {=_xlfn.XLOOKUP(O112,Table4[Concate],Table4[[Group/Legder]:[Sub Category]],,0)} -> Ledger | Q112: PL | R112: Bad Debt/Provision for Loss | S112: Provision for Doubtful debts
A113: Bank Charges Against Import/MTT Transaction | G113: =SUM(B113:F113) -> 0 | H113: =B113*$N$1 -> 0 | I113: =C113*$N$1 -> 0 | J113: =D113*$N$1 -> 0 | K113: =E113*$N$1 -> 0 | L113: =F113*$N$1 -> 0 | M113: =G113*$N$1 -> 0 | N113: Arha General Trading Co (AGT) | O113: =CONCATENATE(A113,N113) -> Bank Charges Against Import/MTT TransactionArha General Trading Co (AGT) | P113: {=_xlfn.XLOOKUP(O113,Table4[Concate],Table4[[Group/Legder]:[Sub Category]],,0)} -> Ledger | Q113: PL | R113: Direct Expenses | S113: Bank charges against Import/MTT Transaction | T113: Reversal of COGS entry passed and new COGS recorded
A114: Bank Fees and Charges | G114: =SUM(B114:F114) -> 0 | H114: =B114*$N$1 -> 0 | I114: =C114*$N$1 -> 0 | J114: =D114*$N$1 -> 0 | K114: =E114*$N$1 -> 0 | L114: =F114*$N$1 -> 0 | M114: =G114*$N$1 -> 0 | N114: Arha General Trading Co (AGT) | O114: =CONCATENATE(A114,N114) -> Bank Fees and ChargesArha General Trading Co (AGT) | P114: {=_xlfn.XLOOKUP(O114,Table4[Concate],Table4[[Group/Legder]:[Sub Category]],,0)} -> Ledger | Q114: PL | R114: Other Expenses | S114: Other Bank Charges
A115: BCPL/53/26 | G115: =SUM(B115:F115) -> 0 | H115: =B115*$N$1 -> 0 | I115: =C115*$N$1 -> 0 | J115: =D115*$N$1 -> 0 | K115: =E115*$N$1 -> 0 | L115: =F115*$N$1 -> 0 | M115: =G115*$N$1 -> 0 | N115: Arha General Trading Co (AGT) | O115: =CONCATENATE(A115,N115) -> BCPL/53/26Arha General Trading Co (AGT) | P115: {=_xlfn.XLOOKUP(O115,Table4[Concate],Table4[[Group/Legder]:[Sub Category]],,0)} -> Ledger | Q115: PL | R115: Direct Expenses | S115: Freight & forwarding Charges
A116: Brokerage & Commission | G116: =SUM(B116:F116) -> 0 | H116: =B116*$N$1 -> 0 | I116: =C116*$N$1 -> 0 | J116: =D116*$N$1 -> 0 | K116: =E116*$N$1 -> 0 | L116: =F116*$N$1 -> 0 | M116: =G116*$N$1 -> 0 | N116: Arha General Trading Co (AGT) | O116: =CONCATENATE(A116,N116) -> Brokerage & CommissionArha General Trading Co (AGT) | P116: {=_xlfn.XLOOKUP(O116,Table4[Concate],Table4[[Group/Legder]:[Sub Category]],,0)} -> Ledger | Q116: PL | R116: Direct Expenses | S116: Commission & Brokerage Charges. | T116: GP Margin
A117: Certificate of Origin | G117: =SUM(B117:F117) -> 0 | H117: =B117*$N$1 -> 0 | I117: =C117*$N$1 -> 0 | J117: =D117*$N$1 -> 0 | K117: =E117*$N$1 -> 0 | L117: =F117*$N$1 -> 0 | M117: =G117*$N$1 -> 0 | N117: Arha General Trading Co (AGT) | O117: =CONCATENATE(A117,N117) -> Certificate of OriginArha General Trading Co (AGT) | P117: {=_xlfn.XLOOKUP(O117,Table4[Concate],Table4[[Group/Legder]:[Sub Category]],,0)} -> Ledger | Q117: PL | R117: Direct Expenses | S117: Freight & forwarding Charges | T117: GP Margin
A118: Cleaning Expenses | G118: =SUM(B118:F118) -> 0 | H118: =B118*$N$1 -> 0 | I118: =C118*$N$1 -> 0 | J118: =D118*$N$1 -> 0 | K118: =E118*$N$1 -> 0 | L118: =F118*$N$1 -> 0 | M118: =G118*$N$1 -> 0 | N118: Arha General Trading Co (AGT) | O118: =CONCATENATE(A118,N118) -> Cleaning ExpensesArha General Trading Co (AGT) | P118: {=_xlfn.XLOOKUP(O118,Table4[Concate],Table4[[Group/Legder]:[Sub Category]],,0)} -> Ledger | Q118: PL | R118: Office Expenses | S118: Other Expenses
A119: CONVEYANCE EXP | G119: =SUM(B119:F119) -> 0 | H119: =B119*$N$1 -> 0 | I119: =C119*$N$1 -> 0 | J119: =D119*$N$1 -> 0 | K119: =E119*$N$1 -> 0 | L119: =F119*$N$1 -> 0 | M119: =G119*$N$1 -> 0 | N119: Arha General Trading Co (AGT) | O119: =CONCATENATE(A119,N119) -> CONVEYANCE EXPArha General Trading Co (AGT) | P119: {=_xlfn.XLOOKUP(O119,Table4[Concate],Table4[[Group/Legder]:[Sub Category]],,0)} -> Ledger | Q119: PL | R119: Travelling & Conveyance | S119: Travelling Expenses (Cash & Local)
A120: Cost of Goods Sold | G120: =SUM(B120:F120) -> 0 | H120: =B120*$N$1 -> 0 | I120: =C120*$N$1 -> 0 | J120: =D120*$N$1 -> 0 | K120: =E120*$N$1 -> 0 | L120: =F120*$N$1 -> 0 | M120: =G120*$N$1 -> 0 | N120: Arha General Trading Co (AGT) | O120: =CONCATENATE(A120,N120) -> Cost of Goods SoldArha General Trading Co (AGT) | P120: {=_xlfn.XLOOKUP(O120,Table4[Concate],Table4[[Group/Legder]:[Sub Category]],,0)} -> Ledger | Q120: PL | R120: COGS | S120: COGS
A121: Disposable charges | G121: =SUM(B121:F121) -> 0 | H121: =B121*$N$1 -> 0 | I121: =C121*$N$1 -> 0 | J121: =D121*$N$1 -> 0 | K121: =E121*$N$1 -> 0 | L121: =F121*$N$1 -> 0 | M121: =G121*$N$1 -> 0 | N121: Arha General Trading Co (AGT) | O121: =CONCATENATE(A121,N121) -> Disposable chargesArha General Trading Co (AGT) | P121: {=_xlfn.XLOOKUP(O121,Table4[Concate],Table4[[Group/Legder]:[Sub Category]],,0)} -> Ledger | Q121: PL | R121: Office Expenses | S121: Other Expenses
A122: Employee Insurance | G122: =SUM(B122:F122) -> 0 | H122: =B122*$N$1 -> 0 | I122: =C122*$N$1 -> 0 | J122: =D122*$N$1 -> 0 | K122: =E122*$N$1 -> 0 | L122: =F122*$N$1 -> 0 | M122: =G122*$N$1 -> 0 | N122: Arha General Trading Co (AGT) | O122: =CONCATENATE(A122,N122) -> Employee InsuranceArha General Trading Co (AGT) | P122: {=_xlfn.XLOOKUP(O122,Table4[Concate],Table4[[Group/Legder]:[Sub Category]],,0)} -> Ledger | Q122: PL | R122: Employee Costs | S122: Staff Welfare
A123: Employee Welfare | G123: =SUM(B123:F123) -> 0 | H123: =B123*$N$1 -> 0 | I123: =C123*$N$1 -> 0 | J123: =D123*$N$1 -> 0 | K123: =E123*$N$1 -> 0 | L123: =F123*$N$1 -> 0 | M123: =G123*$N$1 -> 0 | N123: Arha General Trading Co (AGT) | O123: =CONCATENATE(A123,N123) -> Employee WelfareArha General Trading Co (AGT) | P123: {=_xlfn.XLOOKUP(O123,Table4[Concate],Table4[[Group/Legder]:[Sub Category]],,0)} -> Ledger | Q123: PL | R123: Employee Costs | S123: Staff Welfare
A124: Employment Visa Exp | G124: =SUM(B124:F124) -> 0 | H124: =B124*$N$1 -> 0 | I124: =C124*$N$1 -> 0 | J124: =D124*$N$1 -> 0 | K124: =E124*$N$1 -> 0 | L124: =F124*$N$1 -> 0 | M124: =G124*$N$1 -> 0 | N124: Arha General Trading Co (AGT) | O124: =CONCATENATE(A124,N124) -> Employment Visa ExpArha General Trading Co (AGT) | P124: {=_xlfn.XLOOKUP(O124,Table4[Concate],Table4[[Group/Legder]:[Sub Category]],,0)} -> Ledger | Q124: PL | R124: Travelling & Conveyance | S124: Travelling Expenses
A125: Exchange Gain or Loss | G125: =SUM(B125:F125) -> 0 | H125: =B125*$N$1 -> 0 | I125: =C125*$N$1 -> 0 | J125: =D125*$N$1 -> 0 | K125: =E125*$N$1 -> 0 | L125: =F125*$N$1 -> 0 | M125: =G125*$N$1 -> 0 | N125: Arha General Trading Co (AGT) | O125: =CONCATENATE(A125,N125) -> Exchange Gain or LossArha General Trading Co (AGT) | P125: {=_xlfn.XLOOKUP(O125,Table4[Concate],Table4[[Group/Legder]:[Sub Category]],,0)} -> Ledger | Q125: PL | R125: Finance Cost | S125: Foreign Exchange Gain/(Loss)
A126: Interest in Vehicle Loan | G126: =SUM(B126:F126) -> 0 | H126: =B126*$N$1 -> 0 | I126: =C126*$N$1 -> 0 | J126: =D126*$N$1 -> 0 | K126: =E126*$N$1 -> 0 | L126: =F126*$N$1 -> 0 | M126: =G126*$N$1 -> 0 | N126: Arha General Trading Co (AGT) | O126: =CONCATENATE(A126,N126) -> Interest in Vehicle LoanArha General Trading Co (AGT) | P126: {=_xlfn.XLOOKUP(O126,Table4[Concate],Table4[[Group/Legder]:[Sub Category]],,0)} -> Ledger | Q126: PL | R126: Finance Cost | S126: Interest On Vehicle Loan
A127: Interest on VAT | G127: =SUM(B127:F127) -> 0 | H127: =B127*$N$1 -> 0 | I127: =C127*$N$1 -> 0 | J127: =D127*$N$1 -> 0 | K127: =E127*$N$1 -> 0 | L127: =F127*$N$1 -> 0 | M127: =G127*$N$1 -> 0 | N127: Arha General Trading Co (AGT) | O127: =CONCATENATE(A127,N127) -> Interest on VATArha General Trading Co (AGT) | P127: {=_xlfn.XLOOKUP(O127,Table4[Concate],Table4[[Group/Legder]:[Sub Category]],,0)} -> Ledger | Q127: PL | R127: Office Expenses | S127: Other Expenses
A128: IT and Internet Expenses | G128: =SUM(B128:F128) -> 0 | H128: =B128*$N$1 -> 0 | I128: =C128*$N$1 -> 0 | J128: =D128*$N$1 -> 0 | K128: =E128*$N$1 -> 0 | L128: =F128*$N$1 -> 0 | M128: =G128*$N$1 -> 0 | N128: Arha General Trading Co (AGT) | O128: =CONCATENATE(A128,N128) -> IT and Internet ExpensesArha General Trading Co (AGT) | P128: {=_xlfn.XLOOKUP(O128,Table4[Concate],Table4[[Group/Legder]:[Sub Category]],,0)} -> Ledger | Q128: PL | R128: Office Expenses | S128: Telephone Expenses
A129: KGT-IN-062053 | G129: =SUM(B129:F129) -> 0 | H129: =B129*$N$1 -> 0 | I129: =C129*$N$1 -> 0 | J129: =D129*$N$1 -> 0 | K129: =E129*$N$1 -> 0 | L129: =F129*$N$1 -> 0 | M129: =G129*$N$1 -> 0 | N129: Arha General Trading Co (AGT) | O129: =CONCATENATE(A129,N129) -> KGT-IN-062053Arha General Trading Co (AGT) | P129: {=_xlfn.XLOOKUP(O129,Table4[Concate],Table4[[Group/Legder]:[Sub Category]],,0)} -> Ledger | Q129: PL | R129: Direct Expenses | S129: Freight & forwarding Charges
... A160: Written off | G160: =SUM(B160:F160) -> 0 | H160: =B160*$N$1 -> 0 | I160: =C160*$N$1 -> 0 | J160: =D160*$N$1 -> 0 | K160: =E160*$N$1 -> 0 | L160: =F160*$N$1 -> 0 | M160: =G160*$N$1 -> 0 | N160: Arha General Trading Co (AGT) | O160: =CONCATENATE(A160,N160) -> Written offArha General Trading Co (AGT) | P160: {=_xlfn.XLOOKUP(O160,Table4[Concate],Table4[[Group/Legder]:[Sub Category]],,0)} -> Ledger | Q160: PL | R160: Office Expenses | S160: Other Expenses
